Workbook
Name Cat_DF_Abonnements: Données!$H$2:$H$10
Name Cat_DF_Epargne: Données!$I$2:$I$10
Name Cat_DF_Logement: Données!$F$2:$F$10
Name Cat_DF_Obligations: Données!$J$2:$J$10
Name Cat_DF_Transport: Données!$G$2:$G$10
Name Cat_DV_Autres: Données!$N$2:$N$3
Name Cat_DV_Loisirs: Données!$M$2:$M$10
Name Cat_DV_Transport: Données!$L$2:$L$10
Name Cat_DV_VieQuotidienne: Données!$K$2:$K$10
Name Cat_Revenus: Données!$E$2:$E$10
Name CategoryList: Données!$C$1:$C$66
Name Historique_Categorie: Historique!$C$7:$C$9999
Name Historique_Commentaires: Historique!$H$7:$H$9999
Name Historique_Date: Historique!$G$7:$G$9999
Name Historique_Enregistre: Historique!$F$7:$F$9999
Name Historique_Mois: Historique!$A$7:$A$9999
Name Historique_Montant: Historique!$E$7:$E$9999
Name Historique_Section: Historique!$B$7:$B$9999
Name Historique_Statut: Historique!$D$7:$D$9999
Name MonthList: Données!$A$1:$A$13
Name SectionList: Données!$B$1:$B$11

Sheet Budget_mensuel
A1: Budget mensuel - Planification mensuel pour jeune adulte -
A6: R E V E N U S
B7: Janvier | C7: Février | D7: Mars | E7: Avril | F7: Mai | G7: Juin | H7: Juillet | I7: Août | J7: Septembre | K7: Octobre | L7: Novembre | M7: Décembre | N7: TOTAL ANNUEL
A8: Salaire et retraite | B8: =SUMIFS( Historique_Montant, Historique_Mois,B$7, Historique_Section,"Revenus", Historique_Categorie,$A8, Historique_Enregistre,TRUE, Historique_Statut,"OK" ) -> 1800 | C8: =SUMIFS( Historique_Montant, Historique_Mois,C$7, Historique_Section,"Revenus", Historique_Categorie,$A8, Historique_Enregistre,TRUE, Historique_Statut,"OK" ) -> 0 | D8: =SUMIFS( Historique_Montant, Historique_Mois,D$7, Historique_Section,"Revenus", Historique_Categorie,$A8, Historique_Enregistre,TRUE, Historique_Statut,"OK" ) -> 0 | E8: =SUMIFS( Historique_Montant, Historique_Mois,E$7, Historique_Section,"Revenus", Historique_Categorie,$A8, Historique_Enregistre,TRUE, Historique_Statut,"OK" ) -> 0 | F8: =SUMIFS( Historique_Montant, Historique_Mois,F$7, Historique_Section,"Revenus", Historique_Categorie,$A8, Historique_Enregistre,TRUE, Historique_Statut,"OK" ) -> 0 | G8: =SUMIFS( Historique_Montant, Historique_Mois,G$7, Historique_Section,"Revenus", Historique_Categorie,$A8, Historique_Enregistre,TRUE, Historique_Statut,"OK" ) -> 0 | H8: =SUMIFS( Historique_Montant, Historique_Mois,H$7, Historique_Section,"Revenus", Historique_Categorie,$A8, Historique_Enregistre,TRUE, Historique_Statut,"OK" ) -> 0 | I8: =SUMIFS( Historique_Montant, Historique_Mois,I$7, Historique_Section,"Revenus", Historique_Categorie,$A8, Historique_Enregistre,TRUE, Historique_Statut,"OK" ) -> 0 | ... M8: =SUMIFS( Historique_Montant, Historique_Mois,M$7, Historique_Section,"Revenus", Historique_Categorie,$A8, Historique_Enregistre,TRUE, Historique_Statut,"OK" ) -> 0 | N8: =SUM(B8:M8) -> 1800
A9: Allocations et prestations sociales | B9: =SUMIFS( Historique_Montant, Historique_Mois,B$7, Historique_Section,"Revenus", Historique_Categorie,$A9, Historique_Enregistre,TRUE, Historique_Statut,"OK" ) -> 0 | C9: =SUMIFS( Historique_Montant, Historique_Mois,C$7, Historique_Section,"Revenus", Historique_Categorie,$A9, Historique_Enregistre,TRUE, Historique_Statut,"OK" ) -> 0 | D9: =SUMIFS( Historique_Montant, Historique_Mois,D$7, Historique_Section,"Revenus", Historique_Categorie,$A9, Historique_Enregistre,TRUE, Historique_Statut,"OK" ) -> 0 | E9: =SUMIFS( Historique_Montant, Historique_Mois,E$7, Historique_Section,"Revenus", Historique_Categorie,$A9, Historique_Enregistre,TRUE, Historique_Statut,"OK" ) -> 0 | F9: =SUMIFS( Historique_Montant, Historique_Mois,F$7, Historique_Section,"Revenus", Historique_Categorie,$A9, Historique_Enregistre,TRUE, Historique_Statut,"OK" ) -> 0 | G9: =SUMIFS( Historique_Montant, Historique_Mois,G$7, Historique_Section,"Revenus", Historique_Categorie,$A9, Historique_Enregistre,TRUE, Historique_Statut,"OK" ) -> 0 | H9: =SUMIFS( Historique_Montant, Historique_Mois,H$7, Historique_Section,"Revenus", Historique_Categorie,$A9, Historique_Enregistre,TRUE, Historique_Statut,"OK" ) -> 0 | I9: =SUMIFS( Historique_Montant, Historique_Mois,I$7, Historique_Section,"Revenus", Historique_Categorie,$A9, Historique_Enregistre,TRUE, Historique_Statut,"OK" ) -> 0 | ... M9: =SUMIFS( Historique_Montant, Historique_Mois,M$7, Historique_Section,"Revenus", Historique_Categorie,$A9, Historique_Enregistre,TRUE, Historique_Statut,"OK" ) -> 0 | N9: =SUM(B9:M9) -> 0
A10: Loyers | B10: =SUMIFS( Historique_Montant, Historique_Mois,B$7, Historique_Section,"Revenus", Historique_Categorie,$A10, Historique_Enregistre,TRUE, Historique_Statut,"OK" ) -> 0 | C10: =SUMIFS( Historique_Montant, Historique_Mois,C$7, Historique_Section,"Revenus", Historique_Categorie,$A10, Historique_Enregistre,TRUE, Historique_Statut,"OK" ) -> 0 | D10: =SUMIFS( Historique_Montant, Historique_Mois,D$7, Historique_Section,"Revenus", Historique_Categorie,$A10, Historique_Enregistre,TRUE, Historique_Statut,"OK" ) -> 0 | E10: =SUMIFS( Historique_Montant, Historique_Mois,E$7, Historique_Section,"Revenus", Historique_Categorie,$A10, Historique_Enregistre,TRUE, Historique_Statut,"OK" ) -> 0 | F10: =SUMIFS( Historique_Montant, Historique_Mois,F$7, Historique_Section,"Revenus", Historique_Categorie,$A10, Historique_Enregistre,TRUE, Historique_Statut,"OK" ) -> 0 | G10: =SUMIFS( Historique_Montant, Historique_Mois,G$7, Historique_Section,"Revenus", Historique_Categorie,$A10, Historique_Enregistre,TRUE, Historique_Statut,"OK" ) -> 0 | H10: =SUMIFS( Historique_Montant, Historique_Mois,H$7, Historique_Section,"Revenus", Historique_Categorie,$A10, Historique_Enregistre,TRUE, Historique_Statut,"OK" ) -> 0 | I10: =SUMIFS( Historique_Montant, Historique_Mois,I$7, Historique_Section,"Revenus", Historique_Categorie,$A10, Historique_Enregistre,TRUE, Historique_Statut,"OK" ) -> 0 | ... M10: =SUMIFS( Historique_Montant, Historique_Mois,M$7, Historique_Section,"Revenus", Historique_Categorie,$A10, Historique_Enregistre,TRUE, Historique_Statut,"OK" ) -> 0 | N10: =SUM(B10:M10) -> 0
A11: Remboursements et virements | B11: =SUMIFS( Historique_Montant, Historique_Mois,B$7, Historique_Section,"Revenus", Historique_Categorie,$A11, Historique_Enregistre,TRUE, Historique_Statut,"OK" ) -> 0 | C11: =SUMIFS( Historique_Montant, Historique_Mois,C$7, Historique_Section,"Revenus", Historique_Categorie,$A11, Historique_Enregistre,TRUE, Historique_Statut,"OK" ) -> 0 | D11: =SUMIFS( Historique_Montant, Historique_Mois,D$7, Historique_Section,"Revenus", Historique_Categorie,$A11, Historique_Enregistre,TRUE, Historique_Statut,"OK" ) -> 0 | E11: =SUMIFS( Historique_Montant, Historique_Mois,E$7, Historique_Section,"Revenus", Historique_Categorie,$A11, Historique_Enregistre,TRUE, Historique_Statut,"OK" ) -> 0 | F11: =SUMIFS( Historique_Montant, Historique_Mois,F$7, Historique_Section,"Revenus", Historique_Categorie,$A11, Historique_Enregistre,TRUE, Historique_Statut,"OK" ) -> 0 | G11: =SUMIFS( Historique_Montant, Historique_Mois,G$7, Historique_Section,"Revenus", Historique_Categorie,$A11, Historique_Enregistre,TRUE, Historique_Statut,"OK" ) -> 0 | H11: =SUMIFS( Historique_Montant, Historique_Mois,H$7, Historique_Section,"Revenus", Historique_Categorie,$A11, Historique_Enregistre,TRUE, Historique_Statut,"OK" ) -> 0 | I11: =SUMIFS( Historique_Montant, Historique_Mois,I$7, Historique_Section,"Revenus", Historique_Categorie,$A11, Historique_Enregistre,TRUE, Historique_Statut,"OK" ) -> 0 | ... M11: =SUMIFS( Historique_Montant, Historique_Mois,M$7, Historique_Section,"Revenus", Historique_Categorie,$A11, Historique_Enregistre,TRUE, Historique_Statut,"OK" ) -> 0 | N11: =SUM(B11:M11) -> 0
A12: Vente d'objets | B12: =SUMIFS( Historique_Montant, Historique_Mois,B$7, Historique_Section,"Revenus", Historique_Categorie,$A12, Historique_Enregistre,TRUE, Historique_Statut,"OK" ) -> 0 | C12: =SUMIFS( Historique_Montant, Historique_Mois,C$7, Historique_Section,"Revenus", Historique_Categorie,$A12, Historique_Enregistre,TRUE, Historique_Statut,"OK" ) -> 0 | D12: =SUMIFS( Historique_Montant, Historique_Mois,D$7, Historique_Section,"Revenus", Historique_Categorie,$A12, Historique_Enregistre,TRUE, Historique_Statut,"OK" ) -> 0 | E12: =SUMIFS( Historique_Montant, Historique_Mois,E$7, Historique_Section,"Revenus", Historique_Categorie,$A12, Historique_Enregistre,TRUE, Historique_Statut,"OK" ) -> 0 | F12: =SUMIFS( Historique_Montant, Historique_Mois,F$7, Historique_Section,"Revenus", Historique_Categorie,$A12, Historique_Enregistre,TRUE, Historique_Statut,"OK" ) -> 0 | G12: =SUMIFS( Historique_Montant, Historique_Mois,G$7, Historique_Section,"Revenus", Historique_Categorie,$A12, Historique_Enregistre,TRUE, Historique_Statut,"OK" ) -> 0 | H12: =SUMIFS( Historique_Montant, Historique_Mois,H$7, Historique_Section,"Revenus", Historique_Categorie,$A12, Historique_Enregistre,TRUE, Historique_Statut,"OK" ) -> 0 | I12: =SUMIFS( Historique_Montant, Historique_Mois,I$7, Historique_Section,"Revenus", Historique_Categorie,$A12, Historique_Enregistre,TRUE, Historique_Statut,"OK" ) -> 0 | ... M12: =SUMIFS( Historique_Montant, Historique_Mois,M$7, Historique_Section,"Revenus", Historique_Categorie,$A12, Historique_Enregistre,TRUE, Historique_Statut,"OK" ) -> 0 | N12: =SUM(B12:M12) -> 0
B13: =SUMIFS( Historique_Montant, Historique_Mois,B$7, Historique_Section,"Revenus", Historique_Categorie,$A13, Historique_Enregistre,TRUE, Historique_Statut,"OK" ) -> 0 | C13: =SUMIFS( Historique_Montant, Historique_Mois,C$7, Historique_Section,"Revenus", Historique_Categorie,$A13, Historique_Enregistre,TRUE, Historique_Statut,"OK" ) -> 0 | D13: =SUMIFS( Historique_Montant, Historique_Mois,D$7, Historique_Section,"Revenus", Historique_Categorie,$A13, Historique_Enregistre,TRUE, Historique_Statut,"OK" ) -> 0 | E13: =SUMIFS( Historique_Montant, Historique_Mois,E$7, Historique_Section,"Revenus", Historique_Categorie,$A13, Historique_Enregistre,TRUE, Historique_Statut,"OK" ) -> 0 | F13: =SUMIFS( Historique_Montant, Historique_Mois,F$7, Historique_Section,"Revenus", Historique_Categorie,$A13, Historique_Enregistre,TRUE, Historique_Statut,"OK" ) -> 0 | G13: =SUMIFS( Historique_Montant, Historique_Mois,G$7, Historique_Section,"Revenus", Historique_Categorie,$A13, Historique_Enregistre,TRUE, Historique_Statut,"OK" ) -> 0 | H13: =SUMIFS( Historique_Montant, Historique_Mois,H$7, Historique_Section,"Revenus", Historique_Categorie,$A13, Historique_Enregistre,TRUE, Historique_Statut,"OK" ) -> 0 | I13: =SUMIFS( Historique_Montant, Historique_Mois,I$7, Historique_Section,"Revenus", Historique_Categorie,$A13, Historique_Enregistre,TRUE, Historique_Statut,"OK" ) -> 0 | ... M13: =SUMIFS( Historique_Montant, Historique_Mois,M$7, Historique_Section,"Revenus", Historique_Categorie,$A13, Historique_Enregistre,TRUE, Historique_Statut,"OK" ) -> 0 | N13: =SUM(B13:M13) -> 0
B14: =SUMIFS( Historique_Montant, Historique_Mois,B$7, Historique_Section,"Revenus", Historique_Categorie,$A14, Historique_Enregistre,TRUE, Historique_Statut,"OK" ) -> 0 | C14: =SUMIFS( Historique_Montant, Historique_Mois,C$7, Historique_Section,"Revenus", Historique_Categorie,$A14, Historique_Enregistre,TRUE, Historique_Statut,"OK" ) -> 0 | D14: =SUMIFS( Historique_Montant, Historique_Mois,D$7, Historique_Section,"Revenus", Historique_Categorie,$A14, Historique_Enregistre,TRUE, Historique_Statut,"OK" ) -> 0 | E14: =SUMIFS( Historique_Montant, Historique_Mois,E$7, Historique_Section,"Revenus", Historique_Categorie,$A14, Historique_Enregistre,TRUE, Historique_Statut,"OK" ) -> 0 | F14: =SUMIFS( Historique_Montant, Historique_Mois,F$7, Historique_Section,"Revenus", Historique_Categorie,$A14, Historique_Enregistre,TRUE, Historique_Statut,"OK" ) -> 0 | G14: =SUMIFS( Historique_Montant, Historique_Mois,G$7, Historique_Section,"Revenus", Historique_Categorie,$A14, Historique_Enregistre,TRUE, Historique_Statut,"OK" ) -> 0 | H14: =SUMIFS( Historique_Montant, Historique_Mois,H$7, Historique_Section,"Revenus", Historique_Categorie,$A14, Historique_Enregistre,TRUE, Historique_Statut,"OK" ) -> 0 | I14: =SUMIFS( Historique_Montant, Historique_Mois,I$7, Historique_Section,"Revenus", Historique_Categorie,$A14, Historique_Enregistre,TRUE, Historique_Statut,"OK" ) -> 0 | ... M14: =SUMIFS( Historique_Montant, Historique_Mois,M$7, Historique_Section,"Revenus", Historique_Categorie,$A14, Historique_Enregistre,TRUE, Historique_Statut,"OK" ) -> 0 | N14: =SUM(B14:M14) -> 0
A15: Autres (revenus) | B15: =SUMIFS( Historique_Montant, Historique_Mois,B$7, Historique_Section,"Revenus", Historique_Categorie,$A15, Historique_Enregistre,TRUE, Historique_Statut,"OK" ) -> 0 | C15: =SUMIFS( Historique_Montant, Historique_Mois,C$7, Historique_Section,"Revenus", Historique_Categorie,$A15, Historique_Enregistre,TRUE, Historique_Statut,"OK" ) -> 0 | D15: =SUMIFS( Historique_Montant, Historique_Mois,D$7, Historique_Section,"Revenus", Historique_Categorie,$A15, Historique_Enregistre,TRUE, Historique_Statut,"OK" ) -> 0 | E15: =SUMIFS( Historique_Montant, Historique_Mois,E$7, Historique_Section,"Revenus", Historique_Categorie,$A15, Historique_Enregistre,TRUE, Historique_Statut,"OK" ) -> 0 | F15: =SUMIFS( Historique_Montant, Historique_Mois,F$7, Historique_Section,"Revenus", Historique_Categorie,$A15, Historique_Enregistre,TRUE, Historique_Statut,"OK" ) -> 0 | G15: =SUMIFS( Historique_Montant, Historique_Mois,G$7, Historique_Section,"Revenus", Historique_Categorie,$A15, Historique_Enregistre,TRUE, Historique_Statut,"OK" ) -> 0 | H15: =SUMIFS( Historique_Montant, Historique_Mois,H$7, Historique_Section,"Revenus", Historique_Categorie,$A15, Historique_Enregistre,TRUE, Historique_Statut,"OK" ) -> 0 | I15: =SUMIFS( Historique_Montant, Historique_Mois,I$7, Historique_Section,"Revenus", Historique_Categorie,$A15, Historique_Enregistre,TRUE, Historique_Statut,"OK" ) -> 0 | ... M15: =SUMIFS( Historique_Montant, Historique_Mois,M$7, Historique_Section,"Revenus", Historique_Categorie,$A15, Historique_Enregistre,TRUE, Historique_Statut,"OK" ) -> 0 | N15: =SUM(B15:M15) -> 0
A16: TOTAL REVENUS | B16: =SUM(SUM(B8:B15)) -> 1800 | C16: =SUM(SUM(C8:C15)) -> 0 | D16: =SUM(SUM(D8:D15)) -> 0 | E16: =SUM(SUM(E8:E15)) -> 0 | F16: =SUM(SUM(F8:F15)) -> 0 | G16: =SUM(SUM(G8:G15)) -> 0 | H16: =SUM(SUM(H8:H15)) -> 0 | I16: =SUM(SUM(I8:I15)) -> 0 | ... M16: =SUM(SUM(M8:M15)) -> 0 | N16: =SUM(B16:M16) -> 1800
A18: D É P E N S E S F I X E S
B19: Janvier | C19: Février | D19: Mars | E19: Avril | F19: Mai | G19: Juin | H19: Juillet | I19: Août | J19: Septembre | K19: Octobre | L19: Novembre | M19: Décembre | N19: TOTAL ANNUEL
A20: Logement | B20: =SUM(B21:B28) -> 0 | C20: =SUM(C21:C28) -> 0 | D20: =SUM(D21:D28) -> 0 | E20: =SUM(E21:E28) -> 0 | F20: =SUM(F21:F28) -> 0 | G20: =SUM(G21:G28) -> 0 | H20: =SUM(H21:H28) -> 0 | I20: =SUM(I21:I28) -> 0 | ... M20: =SUM(M21:M28) -> 0 | N20: =SUM(B20:M20) -> 0
A21: Loyer | B21: =SUMIFS( Historique_Montant, Historique_Mois,B$7, Historique_Section,"Dépenses fixes - "&$A$20, Historique_Categorie,$A21, Historique_Enregistre,TRUE, Historique_Statut,"OK" ) -> 0 | C21: =SUMIFS( Historique_Montant, Historique_Mois,C$7, Historique_Section,"Dépenses fixes - "&$A$20, Historique_Categorie,$A21, Historique_Enregistre,TRUE, Historique_Statut,"OK" ) -> 0 | D21: =SUMIFS( Historique_Montant, Historique_Mois,D$7, Historique_Section,"Dépenses fixes - "&$A$20, Historique_Categorie,$A21, Historique_Enregistre,TRUE, Historique_Statut,"OK" ) -> 0 | E21: =SUMIFS( Historique_Montant, Historique_Mois,E$7, Historique_Section,"Dépenses fixes - "&$A$20, Historique_Categorie,$A21, Historique_Enregistre,TRUE, Historique_Statut,"OK" ) -> 0 | F21: =SUMIFS( Historique_Montant, Historique_Mois,F$7, Historique_Section,"Dépenses fixes - "&$A$20, Historique_Categorie,$A21, Historique_Enregistre,TRUE, Historique_Statut,"OK" ) -> 0 | G21: =SUMIFS( Historique_Montant, Historique_Mois,G$7, Historique_Section,"Dépenses fixes - "&$A$20, Historique_Categorie,$A21, Historique_Enregistre,TRUE, Historique_Statut,"OK" ) -> 0 | H21: =SUMIFS( Historique_Montant, Historique_Mois,H$7, Historique_Section,"Dépenses fixes - "&$A$20, Historique_Categorie,$A21, Historique_Enregistre,TRUE, Historique_Statut,"OK" ) -> 0 | I21: =SUMIFS( Historique_Montant, Historique_Mois,I$7, Historique_Section,"Dépenses fixes - "&$A$20, Historique_Categorie,$A21, Historique_Enregistre,TRUE, Historique_Statut,"OK" ) -> 0 | ... M21: =SUMIFS( Historique_Montant, Historique_Mois,M$7, Historique_Section,"Dépenses fixes - "&$A$20, Historique_Categorie,$A21, Historique_Enregistre,TRUE, Historique_Statut,"OK" ) -> 0 | N21: =SUM(B21:M21) -> 0
A22: Charges de copropriété | B22: =SUMIFS( Historique_Montant, Historique_Mois,B$7, Historique_Section,"Dépenses fixes - "&$A$20, Historique_Categorie,$A22, Historique_Enregistre,TRUE, Historique_Statut,"OK" ) -> 0 | C22: =SUMIFS( Historique_Montant, Historique_Mois,C$7, Historique_Section,"Dépenses fixes - "&$A$20, Historique_Categorie,$A22, Historique_Enregistre,TRUE, Historique_Statut,"OK" ) -> 0 | D22: =SUMIFS( Historique_Montant, Historique_Mois,D$7, Historique_Section,"Dépenses fixes - "&$A$20, Historique_Categorie,$A22, Historique_Enregistre,TRUE, Historique_Statut,"OK" ) -> 0 | E22: =SUMIFS( Historique_Montant, Historique_Mois,E$7, Historique_Section,"Dépenses fixes - "&$A$20, Historique_Categorie,$A22, Historique_Enregistre,TRUE, Historique_Statut,"OK" ) -> 0 | F22: =SUMIFS( Historique_Montant, Historique_Mois,F$7, Historique_Section,"Dépenses fixes - "&$A$20, Historique_Categorie,$A22, Historique_Enregistre,TRUE, Historique_Statut,"OK" ) -> 0 | G22: =SUMIFS( Historique_Montant, Historique_Mois,G$7, Historique_Section,"Dépenses fixes - "&$A$20, Historique_Categorie,$A22, Historique_Enregistre,TRUE, Historique_Statut,"OK" ) -> 0 | H22: =SUMIFS( Historique_Montant, Historique_Mois,H$7, Historique_Section,"Dépenses fixes - "&$A$20, Historique_Categorie,$A22, Historique_Enregistre,TRUE, Historique_Statut,"OK" ) -> 0 | I22: =SUMIFS( Historique_Montant, Historique_Mois,I$7, Historique_Section,"Dépenses fixes - "&$A$20, Historique_Categorie,$A22, Historique_Enregistre,TRUE, Historique_Statut,"OK" ) -> 0 | ... M22: =SUMIFS( Historique_Montant, Historique_Mois,M$7, Historique_Section,"Dépenses fixes - "&$A$20, Historique_Categorie,$A22, Historique_Enregistre,TRUE, Historique_Statut,"OK" ) -> 0 | N22: =SUM(B22:M22) -> 0
A23: Taxe d'habitation, taxe foncière | B23: =SUMIFS( Historique_Montant, Historique_Mois,B$7, Historique_Section,"Dépenses fixes - "&$A$20, Historique_Categorie,$A23, Historique_Enregistre,TRUE, Historique_Statut,"OK" ) -> 0 | C23: =SUMIFS( Historique_Montant, Historique_Mois,C$7, Historique_Section,"Dépenses fixes - "&$A$20, Historique_Categorie,$A23, Historique_Enregistre,TRUE, Historique_Statut,"OK" ) -> 0 | D23: =SUMIFS( Historique_Montant, Historique_Mois,D$7, Historique_Section,"Dépenses fixes - "&$A$20, Historique_Categorie,$A23, Historique_Enregistre,TRUE, Historique_Statut,"OK" ) -> 0 | E23: =SUMIFS( Historique_Montant, Historique_Mois,E$7, Historique_Section,"Dépenses fixes - "&$A$20, Historique_Categorie,$A23, Historique_Enregistre,TRUE, Historique_Statut,"OK" ) -> 0 | F23: =SUMIFS( Historique_Montant, Historique_Mois,F$7, Historique_Section,"Dépenses fixes - "&$A$20, Historique_Categorie,$A23, Historique_Enregistre,TRUE, Historique_Statut,"OK" ) -> 0 | G23: =SUMIFS( Historique_Montant, Historique_Mois,G$7, Historique_Section,"Dépenses fixes - "&$A$20, Historique_Categorie,$A23, Historique_Enregistre,TRUE, Historique_Statut,"OK" ) -> 0 | H23: =SUMIFS( Historique_Montant, Historique_Mois,H$7, Historique_Section,"Dépenses fixes - "&$A$20, Historique_Categorie,$A23, Historique_Enregistre,TRUE, Historique_Statut,"OK" ) -> 0 | I23: =SUMIFS( Historique_Montant, Historique_Mois,I$7, Historique_Section,"Dépenses fixes - "&$A$20, Historique_Categorie,$A23, Historique_Enregistre,TRUE, Historique_Statut,"OK" ) -> 0 | ... M23: =SUMIFS( Historique_Montant, Historique_Mois,M$7, Historique_Section,"Dépenses fixes - "&$A$20, Historique_Categorie,$A23, Historique_Enregistre,TRUE, Historique_Statut,"OK" ) -> 0 | N23: =SUM(B23:M23) -> 0
A24: Charge appartement | B24: =SUMIFS( Historique_Montant, Historique_Mois,B$7, Historique_Section,"Dépenses fixes - "&$A$20, Historique_Categorie,$A24, Historique_Enregistre,TRUE, Historique_Statut,"OK" ) -> 0 | C24: =SUMIFS( Historique_Montant, Historique_Mois,C$7, Historique_Section,"Dépenses fixes - "&$A$20, Historique_Categorie,$A24, Historique_Enregistre,TRUE, Historique_Statut,"OK" ) -> 0 | D24: =SUMIFS( Historique_Montant, Historique_Mois,D$7, Historique_Section,"Dépenses fixes - "&$A$20, Historique_Categorie,$A24, Historique_Enregistre,TRUE, Historique_Statut,"OK" ) -> 0 | E24: =SUMIFS( Historique_Montant, Historique_Mois,E$7, Historique_Section,"Dépenses fixes - "&$A$20, Historique_Categorie,$A24, Historique_Enregistre,TRUE, Historique_Statut,"OK" ) -> 0 | F24: =SUMIFS( Historique_Montant, Historique_Mois,F$7, Historique_Section,"Dépenses fixes - "&$A$20, Historique_Categorie,$A24, Historique_Enregistre,TRUE, Historique_Statut,"OK" ) -> 0 | G24: =SUMIFS( Historique_Montant, Historique_Mois,G$7, Historique_Section,"Dépenses fixes - "&$A$20, Historique_Categorie,$A24, Historique_Enregistre,TRUE, Historique_Statut,"OK" ) -> 0 | H24: =SUMIFS( Historique_Montant, Historique_Mois,H$7, Historique_Section,"Dépenses fixes - "&$A$20, Historique_Categorie,$A24, Historique_Enregistre,TRUE, Historique_Statut,"OK" ) -> 0 | I24: =SUMIFS( Historique_Montant, Historique_Mois,I$7, Historique_Section,"Dépenses fixes - "&$A$20, Historique_Categorie,$A24, Historique_Enregistre,TRUE, Historique_Statut,"OK" ) -> 0 | ... M24: =SUMIFS( Historique_Montant, Historique_Mois,M$7, Historique_Section,"Dépenses fixes - "&$A$20, Historique_Categorie,$A24, Historique_Enregistre,TRUE, Historique_Statut,"OK" ) -> 0 | N24: =SUM(B24:M24) -> 0
A25: Assurance habitation | B25: =SUMIFS( Historique_Montant, Historique_Mois,B$7, Historique_Section,"Dépenses fixes - "&$A$20, Historique_Categorie,$A25, Historique_Enregistre,TRUE, Historique_Statut,"OK" ) -> 0 | C25: =SUMIFS( Historique_Montant, Historique_Mois,C$7, Historique_Section,"Dépenses fixes - "&$A$20, Historique_Categorie,$A25, Historique_Enregistre,TRUE, Historique_Statut,"OK" ) -> 0 | D25: =SUMIFS( Historique_Montant, Historique_Mois,D$7, Historique_Section,"Dépenses fixes - "&$A$20, Historique_Categorie,$A25, Historique_Enregistre,TRUE, Historique_Statut,"OK" ) -> 0 | E25: =SUMIFS( Historique_Montant, Historique_Mois,E$7, Historique_Section,"Dépenses fixes - "&$A$20, Historique_Categorie,$A25, Historique_Enregistre,TRUE, Historique_Statut,"OK" ) -> 0 | F25: =SUMIFS( Historique_Montant, Historique_Mois,F$7, Historique_Section,"Dépenses fixes - "&$A$20, Historique_Categorie,$A25, Historique_Enregistre,TRUE, Historique_Statut,"OK" ) -> 0 | G25: =SUMIFS( Historique_Montant, Historique_Mois,G$7, Historique_Section,"Dépenses fixes - "&$A$20, Historique_Categorie,$A25, Historique_Enregistre,TRUE, Historique_Statut,"OK" ) -> 0 | H25: =SUMIFS( Historique_Montant, Historique_Mois,H$7, Historique_Section,"Dépenses fixes - "&$A$20, Historique_Categorie,$A25, Historique_Enregistre,TRUE, Historique_Statut,"OK" ) -> 0 | I25: =SUMIFS( Historique_Montant, Historique_Mois,I$7, Historique_Section,"Dépenses fixes - "&$A$20, Historique_Categorie,$A25, Historique_Enregistre,TRUE, Historique_Statut,"OK" ) -> 0 | ... M25: =SUMIFS( Historique_Montant, Historique_Mois,M$7, Historique_Section,"Dépenses fixes - "&$A$20, Historique_Categorie,$A25, Historique_Enregistre,TRUE, Historique_Statut,"OK" ) -> 0 | N25: =SUM(B25:M25) -> 0
B26: =SUMIFS( Historique_Montant, Historique_Mois,B$7, Historique_Section,"Dépenses fixes - "&$A$20, Historique_Categorie,$A26, Historique_Enregistre,TRUE, Historique_Statut,"OK" ) -> 0 | C26: =SUMIFS( Historique_Montant, Historique_Mois,C$7, Historique_Section,"Dépenses fixes - "&$A$20, Historique_Categorie,$A26, Historique_Enregistre,TRUE, Historique_Statut,"OK" ) -> 0 | D26: =SUMIFS( Historique_Montant, Historique_Mois,D$7, Historique_Section,"Dépenses fixes - "&$A$20, Historique_Categorie,$A26, Historique_Enregistre,TRUE, Historique_Statut,"OK" ) -> 0 | E26: =SUMIFS( Historique_Montant, Historique_Mois,E$7, Historique_Section,"Dépenses fixes - "&$A$20, Historique_Categorie,$A26, Historique_Enregistre,TRUE, Historique_Statut,"OK" ) -> 0 | F26: =SUMIFS( Historique_Montant, Historique_Mois,F$7, Historique_Section,"Dépenses fixes - "&$A$20, Historique_Categorie,$A26, Historique_Enregistre,TRUE, Historique_Statut,"OK" ) -> 0 | G26: =SUMIFS( Historique_Montant, Historique_Mois,G$7, Historique_Section,"Dépenses fixes - "&$A$20, Historique_Categorie,$A26, Historique_Enregistre,TRUE, Historique_Statut,"OK" ) -> 0 | H26: =SUMIFS( Historique_Montant, Historique_Mois,H$7, Historique_Section,"Dépenses fixes - "&$A$20, Historique_Categorie,$A26, Historique_Enregistre,TRUE, Historique_Statut,"OK" ) -> 0 | I26: =SUMIFS( Historique_Montant, Historique_Mois,I$7, Historique_Section,"Dépenses fixes - "&$A$20, Historique_Categorie,$A26, Historique_Enregistre,TRUE, Historique_Statut,"OK" ) -> 0 | ... M26: =SUMIFS( Historique_Montant, Historique_Mois,M$7, Historique_Section,"Dépenses fixes - "&$A$20, Historique_Categorie,$A26, Historique_Enregistre,TRUE, Historique_Statut,"OK" ) -> 0 | N26: =SUM(B26:M26) -> 0
B27: =SUMIFS( Historique_Montant, Historique_Mois,B$7, Historique_Section,"Dépenses fixes - "&$A$20, Historique_Categorie,$A27, Historique_Enregistre,TRUE, Historique_Statut,"OK" ) -> 0 | C27: =SUMIFS( Historique_Montant, Historique_Mois,C$7, Historique_Section,"Dépenses fixes - "&$A$20, Historique_Categorie,$A27, Historique_Enregistre,TRUE, Historique_Statut,"OK" ) -> 0 | D27: =SUMIFS( Historique_Montant, Historique_Mois,D$7, Historique_Section,"Dépenses fixes - "&$A$20, Historique_Categorie,$A27, Historique_Enregistre,TRUE, Historique_Statut,"OK" ) -> 0 | E27: =SUMIFS( Historique_Montant, Historique_Mois,E$7, Historique_Section,"Dépenses fixes - "&$A$20, Historique_Categorie,$A27, Historique_Enregistre,TRUE, Historique_Statut,"OK" ) -> 0 | F27: =SUMIFS( Historique_Montant, Historique_Mois,F$7, Historique_Section,"Dépenses fixes - "&$A$20, Historique_Categorie,$A27, Historique_Enregistre,TRUE, Historique_Statut,"OK" ) -> 0 | G27: =SUMIFS( Historique_Montant, Historique_Mois,G$7, Historique_Section,"Dépenses fixes - "&$A$20, Historique_Categorie,$A27, Historique_Enregistre,TRUE, Historique_Statut,"OK" ) -> 0 | H27: =SUMIFS( Historique_Montant, Historique_Mois,H$7, Historique_Section,"Dépenses fixes - "&$A$20, Historique_Categorie,$A27, Historique_Enregistre,TRUE, Historique_Statut,"OK" ) -> 0 | I27: =SUMIFS( Historique_Montant, Historique_Mois,I$7, Historique_Section,"Dépenses fixes - "&$A$20, Historique_Categorie,$A27, Historique_Enregistre,TRUE, Historique_Statut,"OK" ) -> 0 | ... M27: =SUMIFS( Historique_Montant, Historique_Mois,M$7, Historique_Section,"Dépenses fixes - "&$A$20, Historique_Categorie,$A27, Historique_Enregistre,TRUE, Historique_Statut,"OK" ) -> 0 | N27: =SUM(B27:M27) -> 0
A28: Autres (logement) | B28: =SUMIFS( Historique_Montant, Historique_Mois,B$7, Historique_Section,"Dépenses fixes - "&$A$20, Historique_Categorie,$A28, Historique_Enregistre,TRUE, Historique_Statut,"OK" ) -> 0 | C28: =SUMIFS( Historique_Montant, Historique_Mois,C$7, Historique_Section,"Dépenses fixes - "&$A$20, Historique_Categorie,$A28, Historique_Enregistre,TRUE, Historique_Statut,"OK" ) -> 0 | D28: =SUMIFS( Historique_Montant, Historique_Mois,D$7, Historique_Section,"Dépenses fixes - "&$A$20, Historique_Categorie,$A28, Historique_Enregistre,TRUE, Historique_Statut,"OK" ) -> 0 | E28: =SUMIFS( Historique_Montant, Historique_Mois,E$7, Historique_Section,"Dépenses fixes - "&$A$20, Historique_Categorie,$A28, Historique_Enregistre,TRUE, Historique_Statut,"OK" ) -> 0 | F28: =SUMIFS( Historique_Montant, Historique_Mois,F$7, Historique_Section,"Dépenses fixes - "&$A$20, Historique_Categorie,$A28, Historique_Enregistre,TRUE, Historique_Statut,"OK" ) -> 0 | G28: =SUMIFS( Historique_Montant, Historique_Mois,G$7, Historique_Section,"Dépenses fixes - "&$A$20, Historique_Categorie,$A28, Historique_Enregistre,TRUE, Historique_Statut,"OK" ) -> 0 | H28: =SUMIFS( Historique_Montant, Historique_Mois,H$7, Historique_Section,"Dépenses fixes - "&$A$20, Historique_Categorie,$A28, Historique_Enregistre,TRUE, Historique_Statut,"OK" ) -> 0 | I28: =SUMIFS( Historique_Montant, Historique_Mois,I$7, Historique_Section,"Dépenses fixes - "&$A$20, Historique_Categorie,$A28, Historique_Enregistre,TRUE, Historique_Statut,"OK" ) -> 0 | ... M28: =SUMIFS( Historique_Montant, Historique_Mois,M$7, Historique_Section,"Dépenses fixes - "&$A$20, Historique_Categorie,$A28, Historique_Enregistre,TRUE, Historique_Statut,"OK" ) -> 0 | N28: =SUM(B28:M28) -> 0
A29: Transport | B29: =SUM(B30:B34) -> 0 | C29: =SUM(C30:C34) -> 0 | D29: =SUM(D30:D34) -> 0 | E29: =SUM(E30:E34) -> 0 | F29: =SUM(F30:F34) -> 0 | G29: =SUM(G30:G34) -> 0 | H29: =SUM(H30:H34) -> 0 | I29: =SUM(I30:I34) -> 0 | ... M29: =SUM(M30:M34) -> 0 | N29: =SUM(B29:M29) -> 0
A30: Crédit auto | B30: =SUMIFS( Historique_Montant, Historique_Mois,B$7, Historique_Section,"Dépenses fixes - "&$A$29, Historique_Categorie,$A30, Historique_Enregistre,TRUE, Historique_Statut,"OK" ) -> 0 | C30: =SUMIFS( Historique_Montant, Historique_Mois,C$7, Historique_Section,"Dépenses fixes - "&$A$29, Historique_Categorie,$A30, Historique_Enregistre,TRUE, Historique_Statut,"OK" ) -> 0 | D30: =SUMIFS( Historique_Montant, Historique_Mois,D$7, Historique_Section,"Dépenses fixes - "&$A$29, Historique_Categorie,$A30, Historique_Enregistre,TRUE, Historique_Statut,"OK" ) -> 0 | E30: =SUMIFS( Historique_Montant, Historique_Mois,E$7, Historique_Section,"Dépenses fixes - "&$A$29, Historique_Categorie,$A30, Historique_Enregistre,TRUE, Historique_Statut,"OK" ) -> 0 | F30: =SUMIFS( Historique_Montant, Historique_Mois,F$7, Historique_Section,"Dépenses fixes - "&$A$29, Historique_Categorie,$A30, Historique_Enregistre,TRUE, Historique_Statut,"OK" ) -> 0 | G30: =SUMIFS( Historique_Montant, Historique_Mois,G$7, Historique_Section,"Dépenses fixes - "&$A$29, Historique_Categorie,$A30, Historique_Enregistre,TRUE, Historique_Statut,"OK" ) -> 0 | H30: =SUMIFS( Historique_Montant, Historique_Mois,H$7, Historique_Section,"Dépenses fixes - "&$A$29, Historique_Categorie,$A30, Historique_Enregistre,TRUE, Historique_Statut,"OK" ) -> 0 | I30: =SUMIFS( Historique_Montant, Historique_Mois,I$7, Historique_Section,"Dépenses fixes - "&$A$29, Historique_Categorie,$A30, Historique_Enregistre,TRUE, Historique_Statut,"OK" ) -> 0 | ... M30: =SUMIFS( Historique_Montant, Historique_Mois,M$7, Historique_Section,"Dépenses fixes - "&$A$29, Historique_Categorie,$A30, Historique_Enregistre,TRUE, Historique_Statut,"OK" ) -> 0 | N30: =SUM(B30:M30) -> 0
A31: Assurance auto | B31: =SUMIFS( Historique_Montant, Historique_Mois,B$7, Historique_Section,"Dépenses fixes - "&$A$29, Historique_Categorie,$A31, Historique_Enregistre,TRUE, Historique_Statut,"OK" ) -> 0 | C31: =SUMIFS( Historique_Montant, Historique_Mois,C$7, Historique_Section,"Dépenses fixes - "&$A$29, Historique_Categorie,$A31, Historique_Enregistre,TRUE, Historique_Statut,"OK" ) -> 0 | D31: =SUMIFS( Historique_Montant, Historique_Mois,D$7, Historique_Section,"Dépenses fixes - "&$A$29, Historique_Categorie,$A31, Historique_Enregistre,TRUE, Historique_Statut,"OK" ) -> 0 | E31: =SUMIFS( Historique_Montant, Historique_Mois,E$7, Historique_Section,"Dépenses fixes - "&$A$29, Historique_Categorie,$A31, Historique_Enregistre,TRUE, Historique_Statut,"OK" ) -> 0 | F31: =SUMIFS( Historique_Montant, Historique_Mois,F$7, Historique_Section,"Dépenses fixes - "&$A$29, Historique_Categorie,$A31, Historique_Enregistre,TRUE, Historique_Statut,"OK" ) -> 0 | G31: =SUMIFS( Historique_Montant, Historique_Mois,G$7, Historique_Section,"Dépenses fixes - "&$A$29, Historique_Categorie,$A31, Historique_Enregistre,TRUE, Historique_Statut,"OK" ) -> 0 | H31: =SUMIFS( Historique_Montant, Historique_Mois,H$7, Historique_Section,"Dépenses fixes - "&$A$29, Historique_Categorie,$A31, Historique_Enregistre,TRUE, Historique_Statut,"OK" ) -> 0 | I31: =SUMIFS( Historique_Montant, Historique_Mois,I$7, Historique_Section,"Dépenses fixes - "&$A$29, Historique_Categorie,$A31, Historique_Enregistre,TRUE, Historique_Statut,"OK" ) -> 0 | ... M31: =SUMIFS( Historique_Montant, Historique_Mois,M$7, Historique_Section,"Dépenses fixes - "&$A$29, Historique_Categorie,$A31, Historique_Enregistre,TRUE, Historique_Statut,"OK" ) -> 0 | N31: =SUM(B31:M31) -> 0
B32: =SUMIFS( Historique_Montant, Historique_Mois,B$7, Historique_Section,"Dépenses fixes - "&$A$29, Historique_Categorie,$A32, Historique_Enregistre,TRUE, Historique_Statut,"OK" ) -> 0 | C32: =SUMIFS( Historique_Montant, Historique_Mois,C$7, Historique_Section,"Dépenses fixes - "&$A$29, Historique_Categorie,$A32, Historique_Enregistre,TRUE, Historique_Statut,"OK" ) -> 0 | D32: =SUMIFS( Historique_Montant, Historique_Mois,D$7, Historique_Section,"Dépenses fixes - "&$A$29, Historique_Categorie,$A32, Historique_Enregistre,TRUE, Historique_Statut,"OK" ) -> 0 | E32: =SUMIFS( Historique_Montant, Historique_Mois,E$7, Historique_Section,"Dépenses fixes - "&$A$29, Historique_Categorie,$A32, Historique_Enregistre,TRUE, Historique_Statut,"OK" ) -> 0 | F32: =SUMIFS( Historique_Montant, Historique_Mois,F$7, Historique_Section,"Dépenses fixes - "&$A$29, Historique_Categorie,$A32, Historique_Enregistre,TRUE, Historique_Statut,"OK" ) -> 0 | G32: =SUMIFS( Historique_Montant, Historique_Mois,G$7, Historique_Section,"Dépenses fixes - "&$A$29, Historique_Categorie,$A32, Historique_Enregistre,TRUE, Historique_Statut,"OK" ) -> 0 | H32: =SUMIFS( Historique_Montant, Historique_Mois,H$7, Historique_Section,"Dépenses fixes - "&$A$29, Historique_Categorie,$A32, Historique_Enregistre,TRUE, Historique_Statut,"OK" ) -> 0 | I32: =SUMIFS( Historique_Montant, Historique_Mois,I$7, Historique_Section,"Dépenses fixes - "&$A$29, Historique_Categorie,$A32, Historique_Enregistre,TRUE, Historique_Statut,"OK" ) -> 0 | ... M32: =SUMIFS( Historique_Montant, Historique_Mois,M$7, Historique_Section,"Dépenses fixes - "&$A$29, Historique_Categorie,$A32, Historique_Enregistre,TRUE, Historique_Statut,"OK" ) -> 0 | N32: =SUM(B32:M32) -> 0
B33: =SUMIFS( Historique_Montant, Historique_Mois,B$7, Historique_Section,"Dépenses fixes - "&$A$29, Historique_Categorie,$A33, Historique_Enregistre,TRUE, Historique_Statut,"OK" ) -> 0 | C33: =SUMIFS( Historique_Montant, Historique_Mois,C$7, Historique_Section,"Dépenses fixes - "&$A$29, Historique_Categorie,$A33, Historique_Enregistre,TRUE, Historique_Statut,"OK" ) -> 0 | D33: =SUMIFS( Historique_Montant, Historique_Mois,D$7, Historique_Section,"Dépenses fixes - "&$A$29, Historique_Categorie,$A33, Historique_Enregistre,TRUE, Historique_Statut,"OK" ) -> 0 | E33: =SUMIFS( Historique_Montant, Historique_Mois,E$7, Historique_Section,"Dépenses fixes - "&$A$29, Historique_Categorie,$A33, Historique_Enregistre,TRUE, Historique_Statut,"OK" ) -> 0 | F33: =SUMIFS( Historique_Montant, Historique_Mois,F$7, Historique_Section,"Dépenses fixes - "&$A$29, Historique_Categorie,$A33, Historique_Enregistre,TRUE, Historique_Statut,"OK" ) -> 0 | G33: =SUMIFS( Historique_Montant, Historique_Mois,G$7, Historique_Section,"Dépenses fixes - "&$A$29, Historique_Categorie,$A33, Historique_Enregistre,TRUE, Historique_Statut,"OK" ) -> 0 | H33: =SUMIFS( Historique_Montant, Historique_Mois,H$7, Historique_Section,"Dépenses fixes - "&$A$29, Historique_Categorie,$A33, Historique_Enregistre,TRUE, Historique_Statut,"OK" ) -> 0 | I33: =SUMIFS( Historique_Montant, Historique_Mois,I$7, Historique_Section,"Dépenses fixes - "&$A$29, Historique_Categorie,$A33, Historique_Enregistre,TRUE, Historique_Statut,"OK" ) -> 0 | ... M33: =SUMIFS( Historique_Montant, Historique_Mois,M$7, Historique_Section,"Dépenses fixes - "&$A$29, Historique_Categorie,$A33, Historique_Enregistre,TRUE, Historique_Statut,"OK" ) -> 0 | N33: =SUM(B33:M33) -> 0
A34: Autres (transport) | B34: =SUMIFS( Historique_Montant, Historique_Mois,B$7, Historique_Section,"Dépenses fixes - "&$A$29, Historique_Categorie,$A34, Historique_Enregistre,TRUE, Historique_Statut,"OK" ) -> 0 | C34: =SUMIFS( Historique_Montant, Historique_Mois,C$7, Historique_Section,"Dépenses fixes - "&$A$29, Historique_Categorie,$A34, Historique_Enregistre,TRUE, Historique_Statut,"OK" ) -> 0 | D34: =SUMIFS( Historique_Montant, Historique_Mois,D$7, Historique_Section,"Dépenses fixes - "&$A$29, Historique_Categorie,$A34, Historique_Enregistre,TRUE, Historique_Statut,"OK" ) -> 0 | E34: =SUMIFS( Historique_Montant, Historique_Mois,E$7, Historique_Section,"Dépenses fixes - "&$A$29, Historique_Categorie,$A34, Historique_Enregistre,TRUE, Historique_Statut,"OK" ) -> 0 | F34: =SUMIFS( Historique_Montant, Historique_Mois,F$7, Historique_Section,"Dépenses fixes - "&$A$29, Historique_Categorie,$A34, Historique_Enregistre,TRUE, Historique_Statut,"OK" ) -> 0 | G34: =SUMIFS( Historique_Montant, Historique_Mois,G$7, Historique_Section,"Dépenses fixes - "&$A$29, Historique_Categorie,$A34, Historique_Enregistre,TRUE, Historique_Statut,"OK" ) -> 0 | H34: =SUMIFS( Historique_Montant, Historique_Mois,H$7, Historique_Section,"Dépenses fixes - "&$A$29, Historique_Categorie,$A34, Historique_Enregistre,TRUE, Historique_Statut,"OK" ) -> 0 | I34: =SUMIFS( Historique_Montant, Historique_Mois,I$7, Historique_Section,"Dépenses fixes - "&$A$29, Historique_Categorie,$A34, Historique_Enregistre,TRUE, Historique_Statut,"OK" ) -> 0 | ... M34: =SUMIFS( Historique_Montant, Historique_Mois,M$7, Historique_Section,"Dépenses fixes - "&$A$29, Historique_Categorie,$A34, Historique_Enregistre,TRUE, Historique_Statut,"OK" ) -> 0 | N34: =SUM(B34:M34) -> 0
A35: Abonnements | B35: =SUM(B36:B44) -> 0 | C35: =SUM(C36:C44) -> 0 | D35: =SUM(D36:D44) -> 0 | E35: =SUM(E36:E44) -> 0 | F35: =SUM(F36:F44) -> 0 | G35: =SUM(G36:G44) -> 0 | H35: =SUM(H36:H44) -> 0 | I35: =SUM(I36:I44) -> 0 | ... M35: =SUM(M36:M44) -> 0 | N35: =SUM(B35:M35) -> 0
A36: Mutuelle | B36: =SUMIFS( Historique_Montant, Historique_Mois,B$7, Historique_Section,"Dépenses fixes - "&$A$35, Historique_Categorie,$A36, Historique_Enregistre,TRUE, Historique_Statut,"OK" ) -> 0 | C36: =SUMIFS( Historique_Montant, Historique_Mois,C$7, Historique_Section,"Dépenses fixes - "&$A$35, Historique_Categorie,$A36, Historique_Enregistre,TRUE, Historique_Statut,"OK" ) -> 0 | D36: =SUMIFS( Historique_Montant, Historique_Mois,D$7, Historique_Section,"Dépenses fixes - "&$A$35, Historique_Categorie,$A36, Historique_Enregistre,TRUE, Historique_Statut,"OK" ) -> 0 | E36: =SUMIFS( Historique_Montant, Historique_Mois,E$7, Historique_Section,"Dépenses fixes - "&$A$35, Historique_Categorie,$A36, Historique_Enregistre,TRUE, Historique_Statut,"OK" ) -> 0 | F36: =SUMIFS( Historique_Montant, Historique_Mois,F$7, Historique_Section,"Dépenses fixes - "&$A$35, Historique_Categorie,$A36, Historique_Enregistre,TRUE, Historique_Statut,"OK" ) -> 0 | G36: =SUMIFS( Historique_Montant, Historique_Mois,G$7, Historique_Section,"Dépenses fixes - "&$A$35, Historique_Categorie,$A36, Historique_Enregistre,TRUE, Historique_Statut,"OK" ) -> 0 | H36: =SUMIFS( Historique_Montant, Historique_Mois,H$7, Historique_Section,"Dépenses fixes - "&$A$35, Historique_Categorie,$A36, Historique_Enregistre,TRUE, Historique_Statut,"OK" ) -> 0 | I36: =SUMIFS( Historique_Montant, Historique_Mois,I$7, Historique_Section,"Dépenses fixes - "&$A$35, Historique_Categorie,$A36, Historique_Enregistre,TRUE, Historique_Statut,"OK" ) -> 0 | ... M36: =SUMIFS( Historique_Montant, Historique_Mois,M$7, Historique_Section,"Dépenses fixes - "&$A$35, Historique_Categorie,$A36, Historique_Enregistre,TRUE, Historique_Statut,"OK" ) -> 0 | N36: =SUM(B36:M36) -> 0
A37: Box, internet, forfait(s) mobile(s) | B37: =SUMIFS( Historique_Montant, Historique_Mois,B$7, Historique_Section,"Dépenses fixes - "&$A$35, Historique_Categorie,$A37, Historique_Enregistre,TRUE, Historique_Statut,"OK" ) -> 0 | C37: =SUMIFS( Historique_Montant, Historique_Mois,C$7, Historique_Section,"Dépenses fixes - "&$A$35, Historique_Categorie,$A37, Historique_Enregistre,TRUE, Historique_Statut,"OK" ) -> 0 | D37: =SUMIFS( Historique_Montant, Historique_Mois,D$7, Historique_Section,"Dépenses fixes - "&$A$35, Historique_Categorie,$A37, Historique_Enregistre,TRUE, Historique_Statut,"OK" ) -> 0 | E37: =SUMIFS( Historique_Montant, Historique_Mois,E$7, Historique_Section,"Dépenses fixes - "&$A$35, Historique_Categorie,$A37, Historique_Enregistre,TRUE, Historique_Statut,"OK" ) -> 0 | F37: =SUMIFS( Historique_Montant, Historique_Mois,F$7, Historique_Section,"Dépenses fixes - "&$A$35, Historique_Categorie,$A37, Historique_Enregistre,TRUE, Historique_Statut,"OK" ) -> 0 | G37: =SUMIFS( Historique_Montant, Historique_Mois,G$7, Historique_Section,"Dépenses fixes - "&$A$35, Historique_Categorie,$A37, Historique_Enregistre,TRUE, Historique_Statut,"OK" ) -> 0 | H37: =SUMIFS( Historique_Montant, Historique_Mois,H$7, Historique_Section,"Dépenses fixes - "&$A$35, Historique_Categorie,$A37, Historique_Enregistre,TRUE, Historique_Statut,"OK" ) -> 0 | I37: =SUMIFS( Historique_Montant, Historique_Mois,I$7, Historique_Section,"Dépenses fixes - "&$A$35, Historique_Categorie,$A37, Historique_Enregistre,TRUE, Historique_Statut,"OK" ) -> 0 | ... M37: =SUMIFS( Historique_Montant, Historique_Mois,M$7, Historique_Section,"Dépenses fixes - "&$A$35, Historique_Categorie,$A37, Historique_Enregistre,TRUE, Historique_Statut,"OK" ) -> 0 | N37: =SUM(B37:M37) -> 0
A38: Vidéo (Netflix, Canal+…) | B38: =SUMIFS( Historique_Montant, Historique_Mois,B$7, Historique_Section,"Dépenses fixes - "&$A$35, Historique_Categorie,$A38, Historique_Enregistre,TRUE, Historique_Statut,"OK" ) -> 0 | C38: =SUMIFS( Historique_Montant, Historique_Mois,C$7, Historique_Section,"Dépenses fixes - "&$A$35, Historique_Categorie,$A38, Historique_Enregistre,TRUE, Historique_Statut,"OK" ) -> 0 | D38: =SUMIFS( Historique_Montant, Historique_Mois,D$7, Historique_Section,"Dépenses fixes - "&$A$35, Historique_Categorie,$A38, Historique_Enregistre,TRUE, Historique_Statut,"OK" ) -> 0 | E38: =SUMIFS( Historique_Montant, Historique_Mois,E$7, Historique_Section,"Dépenses fixes - "&$A$35, Historique_Categorie,$A38, Historique_Enregistre,TRUE, Historique_Statut,"OK" ) -> 0 | F38: =SUMIFS( Historique_Montant, Historique_Mois,F$7, Historique_Section,"Dépenses fixes - "&$A$35, Historique_Categorie,$A38, Historique_Enregistre,TRUE, Historique_Statut,"OK" ) -> 0 | G38: =SUMIFS( Historique_Montant, Historique_Mois,G$7, Historique_Section,"Dépenses fixes - "&$A$35, Historique_Categorie,$A38, Historique_Enregistre,TRUE, Historique_Statut,"OK" ) -> 0 | H38: =SUMIFS( Historique_Montant, Historique_Mois,H$7, Historique_Section,"Dépenses fixes - "&$A$35, Historique_Categorie,$A38, Historique_Enregistre,TRUE, Historique_Statut,"OK" ) -> 0 | I38: =SUMIFS( Historique_Montant, Historique_Mois,I$7, Historique_Section,"Dépenses fixes - "&$A$35, Historique_Categorie,$A38, Historique_Enregistre,TRUE, Historique_Statut,"OK" ) -> 0 | ... M38: =SUMIFS( Historique_Montant, Historique_Mois,M$7, Historique_Section,"Dépenses fixes - "&$A$35, Historique_Categorie,$A38, Historique_Enregistre,TRUE, Historique_Statut,"OK" ) -> 0 | N38: =SUM(B38:M38) -> 0
A39: Musique (Spotify…) | B39: =SUMIFS( Historique_Montant, Historique_Mois,B$7, Historique_Section,"Dépenses fixes - "&$A$35, Historique_Categorie,$A39, Historique_Enregistre,TRUE, Historique_Statut,"OK" ) -> 0 | C39: =SUMIFS( Historique_Montant, Historique_Mois,C$7, Historique_Section,"Dépenses fixes - "&$A$35, Historique_Categorie,$A39, Historique_Enregistre,TRUE, Historique_Statut,"OK" ) -> 0 | D39: =SUMIFS( Historique_Montant, Historique_Mois,D$7, Historique_Section,"Dépenses fixes - "&$A$35, Historique_Categorie,$A39, Historique_Enregistre,TRUE, Historique_Statut,"OK" ) -> 0 | E39: =SUMIFS( Historique_Montant, Historique_Mois,E$7, Historique_Section,"Dépenses fixes - "&$A$35, Historique_Categorie,$A39, Historique_Enregistre,TRUE, Historique_Statut,"OK" ) -> 0 | F39: =SUMIFS( Historique_Montant, Historique_Mois,F$7, Historique_Section,"Dépenses fixes - "&$A$35, Historique_Categorie,$A39, Historique_Enregistre,TRUE, Historique_Statut,"OK" ) -> 0 | G39: =SUMIFS( Historique_Montant, Historique_Mois,G$7, Historique_Section,"Dépenses fixes - "&$A$35, Historique_Categorie,$A39, Historique_Enregistre,TRUE, Historique_Statut,"OK" ) -> 0 | H39: =SUMIFS( Historique_Montant, Historique_Mois,H$7, Historique_Section,"Dépenses fixes - "&$A$35, Historique_Categorie,$A39, Historique_Enregistre,TRUE, Historique_Statut,"OK" ) -> 0 | I39: =SUMIFS( Historique_Montant, Historique_Mois,I$7, Historique_Section,"Dépenses fixes - "&$A$35, Historique_Categorie,$A39, Historique_Enregistre,TRUE, Historique_Statut,"OK" ) -> 0 | ... M39: =SUMIFS( Historique_Montant, Historique_Mois,M$7, Historique_Section,"Dépenses fixes - "&$A$35, Historique_Categorie,$A39, Historique_Enregistre,TRUE, Historique_Statut,"OK" ) -> 0 | N39: =SUM(B39:M39) -> 0
A40: Shopping (Amazon Prime…) | B40: =SUMIFS( Historique_Montant, Historique_Mois,B$7, Historique_Section,"Dépenses fixes - "&$A$35, Historique_Categorie,$A40, Historique_Enregistre,TRUE, Historique_Statut,"OK" ) -> 0 | C40: =SUMIFS( Historique_Montant, Historique_Mois,C$7, Historique_Section,"Dépenses fixes - "&$A$35, Historique_Categorie,$A40, Historique_Enregistre,TRUE, Historique_Statut,"OK" ) -> 0 | D40: =SUMIFS( Historique_Montant, Historique_Mois,D$7, Historique_Section,"Dépenses fixes - "&$A$35, Historique_Categorie,$A40, Historique_Enregistre,TRUE, Historique_Statut,"OK" ) -> 0 | E40: =SUMIFS( Historique_Montant, Historique_Mois,E$7, Historique_Section,"Dépenses fixes - "&$A$35, Historique_Categorie,$A40, Historique_Enregistre,TRUE, Historique_Statut,"OK" ) -> 0 | F40: =SUMIFS( Historique_Montant, Historique_Mois,F$7, Historique_Section,"Dépenses fixes - "&$A$35, Historique_Categorie,$A40, Historique_Enregistre,TRUE, Historique_Statut,"OK" ) -> 0 | G40: =SUMIFS( Historique_Montant, Historique_Mois,G$7, Historique_Section,"Dépenses fixes - "&$A$35, Historique_Categorie,$A40, Historique_Enregistre,TRUE, Historique_Statut,"OK" ) -> 0 | H40: =SUMIFS( Historique_Montant, Historique_Mois,H$7, Historique_Section,"Dépenses fixes - "&$A$35, Historique_Categorie,$A40, Historique_Enregistre,TRUE, Historique_Statut,"OK" ) -> 0 | I40: =SUMIFS( Historique_Montant, Historique_Mois,I$7, Historique_Section,"Dépenses fixes - "&$A$35, Historique_Categorie,$A40, Historique_Enregistre,TRUE, Historique_Statut,"OK" ) -> 0 | ... M40: =SUMIFS( Historique_Montant, Historique_Mois,M$7, Historique_Section,"Dépenses fixes - "&$A$35, Historique_Categorie,$A40, Historique_Enregistre,TRUE, Historique_Statut,"OK" ) -> 0 | N40: =SUM(B40:M40) -> 0
A41: Sport (salle, club…) | B41: =SUMIFS( Historique_Montant, Historique_Mois,B$7, Historique_Section,"Dépenses fixes - "&$A$35, Historique_Categorie,$A41, Historique_Enregistre,TRUE, Historique_Statut,"OK" ) -> 0 | C41: =SUMIFS( Historique_Montant, Historique_Mois,C$7, Historique_Section,"Dépenses fixes - "&$A$35, Historique_Categorie,$A41, Historique_Enregistre,TRUE, Historique_Statut,"OK" ) -> 0 | D41: =SUMIFS( Historique_Montant, Historique_Mois,D$7, Historique_Section,"Dépenses fixes - "&$A$35, Historique_Categorie,$A41, Historique_Enregistre,TRUE, Historique_Statut,"OK" ) -> 0 | E41: =SUMIFS( Historique_Montant, Historique_Mois,E$7, Historique_Section,"Dépenses fixes - "&$A$35, Historique_Categorie,$A41, Historique_Enregistre,TRUE, Historique_Statut,"OK" ) -> 0 | F41: =SUMIFS( Historique_Montant, Historique_Mois,F$7, Historique_Section,"Dépenses fixes - "&$A$35, Historique_Categorie,$A41, Historique_Enregistre,TRUE, Historique_Statut,"OK" ) -> 0 | G41: =SUMIFS( Historique_Montant, Historique_Mois,G$7, Historique_Section,"Dépenses fixes - "&$A$35, Historique_Categorie,$A41, Historique_Enregistre,TRUE, Historique_Statut,"OK" ) -> 0 | H41: =SUMIFS( Historique_Montant, Historique_Mois,H$7, Historique_Section,"Dépenses fixes - "&$A$35, Historique_Categorie,$A41, Historique_Enregistre,TRUE, Historique_Statut,"OK" ) -> 0 | I41: =SUMIFS( Historique_Montant, Historique_Mois,I$7, Historique_Section,"Dépenses fixes - "&$A$35, Historique_Categorie,$A41, Historique_Enregistre,TRUE, Historique_Statut,"OK" ) -> 0 | ... M41: =SUMIFS( Historique_Montant, Historique_Mois,M$7, Historique_Section,"Dépenses fixes - "&$A$35, Historique_Categorie,$A41, Historique_Enregistre,TRUE, Historique_Statut,"OK" ) -> 0 | N41: =SUM(B41:M41) -> 0
A42: Frais bancaire | B42: =SUMIFS( Historique_Montant, Historique_Mois,B$7, Historique_Section,"Dépenses fixes - "&$A$35, Historique_Categorie,$A42, Historique_Enregistre,TRUE, Historique_Statut,"OK" ) -> 0 | C42: =SUMIFS( Historique_Montant, Historique_Mois,C$7, Historique_Section,"Dépenses fixes - "&$A$35, Historique_Categorie,$A42, Historique_Enregistre,TRUE, Historique_Statut,"OK" ) -> 0 | D42: =SUMIFS( Historique_Montant, Historique_Mois,D$7, Historique_Section,"Dépenses fixes - "&$A$35, Historique_Categorie,$A42, Historique_Enregistre,TRUE, Historique_Statut,"OK" ) -> 0 | E42: =SUMIFS( Historique_Montant, Historique_Mois,E$7, Historique_Section,"Dépenses fixes - "&$A$35, Historique_Categorie,$A42, Historique_Enregistre,TRUE, Historique_Statut,"OK" ) -> 0 | F42: =SUMIFS( Historique_Montant, Historique_Mois,F$7, Historique_Section,"Dépenses fixes - "&$A$35, Historique_Categorie,$A42, Historique_Enregistre,TRUE, Historique_Statut,"OK" ) -> 0 | G42: =SUMIFS( Historique_Montant, Historique_Mois,G$7, Historique_Section,"Dépenses fixes - "&$A$35, Historique_Categorie,$A42, Historique_Enregistre,TRUE, Historique_Statut,"OK" ) -> 0 | H42: =SUMIFS( Historique_Montant, Historique_Mois,H$7, Historique_Section,"Dépenses fixes - "&$A$35, Historique_Categorie,$A42, Historique_Enregistre,TRUE, Historique_Statut,"OK" ) -> 0 | I42: =SUMIFS( Historique_Montant, Historique_Mois,I$7, Historique_Section,"Dépenses fixes - "&$A$35, Historique_Categorie,$A42, Historique_Enregistre,TRUE, Historique_Statut,"OK" ) -> 0 | ... M42: =SUMIFS( Historique_Montant, Historique_Mois,M$7, Historique_Section,"Dépenses fixes - "&$A$35, Historique_Categorie,$A42, Historique_Enregistre,TRUE, Historique_Statut,"OK" ) -> 0 | N42: =SUM(B42:M42) -> 0
B43: =SUMIFS( Historique_Montant, Historique_Mois,B$7, Historique_Section,"Dépenses fixes - "&$A$35, Historique_Categorie,$A43, Historique_Enregistre,TRUE, Historique_Statut,"OK" ) -> 0 | C43: =SUMIFS( Historique_Montant, Historique_Mois,C$7, Historique_Section,"Dépenses fixes - "&$A$35, Historique_Categorie,$A43, Historique_Enregistre,TRUE, Historique_Statut,"OK" ) -> 0 | D43: =SUMIFS( Historique_Montant, Historique_Mois,D$7, Historique_Section,"Dépenses fixes - "&$A$35, Historique_Categorie,$A43, Historique_Enregistre,TRUE, Historique_Statut,"OK" ) -> 0 | E43: =SUMIFS( Historique_Montant, Historique_Mois,E$7, Historique_Section,"Dépenses fixes - "&$A$35, Historique_Categorie,$A43, Historique_Enregistre,TRUE, Historique_Statut,"OK" ) -> 0 | F43: =SUMIFS( Historique_Montant, Historique_Mois,F$7, Historique_Section,"Dépenses fixes - "&$A$35, Historique_Categorie,$A43, Historique_Enregistre,TRUE, Historique_Statut,"OK" ) -> 0 | G43: =SUMIFS( Historique_Montant, Historique_Mois,G$7, Historique_Section,"Dépenses fixes - "&$A$35, Historique_Categorie,$A43, Historique_Enregistre,TRUE, Historique_Statut,"OK" ) -> 0 | H43: =SUMIFS( Historique_Montant, Historique_Mois,H$7, Historique_Section,"Dépenses fixes - "&$A$35, Historique_Categorie,$A43, Historique_Enregistre,TRUE, Historique_Statut,"OK" ) -> 0 | I43: =SUMIFS( Historique_Montant, Historique_Mois,I$7, Historique_Section,"Dépenses fixes - "&$A$35, Historique_Categorie,$A43, Historique_Enregistre,TRUE, Historique_Statut,"OK" ) -> 0 | ... M43: =SUMIFS( Historique_Montant, Historique_Mois,M$7, Historique_Section,"Dépenses fixes - "&$A$35, Historique_Categorie,$A43, Historique_Enregistre,TRUE, Historique_Statut,"OK" ) -> 0 | N43: =SUM(B43:M43) -> 0
A44: Autres (abonnements) | B44: =SUMIFS( Historique_Montant, Historique_Mois,B$7, Historique_Section,"Dépenses fixes - "&$A$35, Historique_Categorie,$A44, Historique_Enregistre,TRUE, Historique_Statut,"OK" ) -> 0 | C44: =SUMIFS( Historique_Montant, Historique_Mois,C$7, Historique_Section,"Dépenses fixes - "&$A$35, Historique_Categorie,$A44, Historique_Enregistre,TRUE, Historique_Statut,"OK" ) -> 0 | D44: =SUMIFS( Historique_Montant, Historique_Mois,D$7, Historique_Section,"Dépenses fixes - "&$A$35, Historique_Categorie,$A44, Historique_Enregistre,TRUE, Historique_Statut,"OK" ) -> 0 | E44: =SUMIFS( Historique_Montant, Historique_Mois,E$7, Historique_Section,"Dépenses fixes - "&$A$35, Historique_Categorie,$A44, Historique_Enregistre,TRUE, Historique_Statut,"OK" ) -> 0 | F44: =SUMIFS( Historique_Montant, Historique_Mois,F$7, Historique_Section,"Dépenses fixes - "&$A$35, Historique_Categorie,$A44, Historique_Enregistre,TRUE, Historique_Statut,"OK" ) -> 0 | G44: =SUMIFS( Historique_Montant, Historique_Mois,G$7, Historique_Section,"Dépenses fixes - "&$A$35, Historique_Categorie,$A44, Historique_Enregistre,TRUE, Historique_Statut,"OK" ) -> 0 | H44: =SUMIFS( Historique_Montant, Historique_Mois,H$7, Historique_Section,"Dépenses fixes - "&$A$35, Historique_Categorie,$A44, Historique_Enregistre,TRUE, Historique_Statut,"OK" ) -> 0 | I44: =SUMIFS( Historique_Montant, Historique_Mois,I$7, Historique_Section,"Dépenses fixes - "&$A$35, Historique_Categorie,$A44, Historique_Enregistre,TRUE, Historique_Statut,"OK" ) -> 0 | ... M44: =SUMIFS( Historique_Montant, Historique_Mois,M$7, Historique_Section,"Dépenses fixes - "&$A$35, Historique_Categorie,$A44, Historique_Enregistre,TRUE, Historique_Statut,"OK" ) -> 0 | N44: =SUM(B44:M44) -> 0
A45: Epargne et investissement | B45: =SUM(B46:B53) -> 0 | C45: =SUM(C46:C53) -> 0 | D45: =SUM(D46:D53) -> 0 | E45: =SUM(E46:E53) -> 0 | F45: =SUM(F46:F53) -> 0 | G45: =SUM(G46:G53) -> 0 | H45: =SUM(H46:H53) -> 0 | I45: =SUM(I46:I53) -> 0 | ... M45: =SUM(M46:M53) -> 0 | N45: =SUM(B45:M45) -> 0
A46: Assurance vie | B46: =SUMIFS( Historique_Montant, Historique_Mois,B$7, Historique_Section,"Dépenses fixes - "&$A$45, Historique_Categorie,$A46, Historique_Enregistre,TRUE, Historique_Statut,"OK" ) -> 0 | C46: =SUMIFS( Historique_Montant, Historique_Mois,C$7, Historique_Section,"Dépenses fixes - "&$A$45, Historique_Categorie,$A46, Historique_Enregistre,TRUE, Historique_Statut,"OK" ) -> 0 | D46: =SUMIFS( Historique_Montant, Historique_Mois,D$7, Historique_Section,"Dépenses fixes - "&$A$45, Historique_Categorie,$A46, Historique_Enregistre,TRUE, Historique_Statut,"OK" ) -> 0 | E46: =SUMIFS( Historique_Montant, Historique_Mois,E$7, Historique_Section,"Dépenses fixes - "&$A$45, Historique_Categorie,$A46, Historique_Enregistre,TRUE, Historique_Statut,"OK" ) -> 0 | F46: =SUMIFS( Historique_Montant, Historique_Mois,F$7, Historique_Section,"Dépenses fixes - "&$A$45, Historique_Categorie,$A46, Historique_Enregistre,TRUE, Historique_Statut,"OK" ) -> 0 | G46: =SUMIFS( Historique_Montant, Historique_Mois,G$7, Historique_Section,"Dépenses fixes - "&$A$45, Historique_Categorie,$A46, Historique_Enregistre,TRUE, Historique_Statut,"OK" ) -> 0 | H46: =SUMIFS( Historique_Montant, Historique_Mois,H$7, Historique_Section,"Dépenses fixes - "&$A$45, Historique_Categorie,$A46, Historique_Enregistre,TRUE, Historique_Statut,"OK" ) -> 0 | I46: =SUMIFS( Historique_Montant, Historique_Mois,I$7, Historique_Section,"Dépenses fixes - "&$A$45, Historique_Categorie,$A46, Historique_Enregistre,TRUE, Historique_Statut,"OK" ) -> 0 | ... M46: =SUMIFS( Historique_Montant, Historique_Mois,M$7, Historique_Section,"Dépenses fixes - "&$A$45, Historique_Categorie,$A46, Historique_Enregistre,TRUE, Historique_Statut,"OK" ) -> 0 | N46: =SUM(B46:M46) -> 0
A47: PER | B47: =SUMIFS( Historique_Montant, Historique_Mois,B$7, Historique_Section,"Dépenses fixes - "&$A$45, Historique_Categorie,$A47, Historique_Enregistre,TRUE, Historique_Statut,"OK" ) -> 0 | C47: =SUMIFS( Historique_Montant, Historique_Mois,C$7, Historique_Section,"Dépenses fixes - "&$A$45, Historique_Categorie,$A47, Historique_Enregistre,TRUE, Historique_Statut,"OK" ) -> 0 | D47: =SUMIFS( Historique_Montant, Historique_Mois,D$7, Historique_Section,"Dépenses fixes - "&$A$45, Historique_Categorie,$A47, Historique_Enregistre,TRUE, Historique_Statut,"OK" ) -> 0 | E47: =SUMIFS( Historique_Montant, Historique_Mois,E$7, Historique_Section,"Dépenses fixes - "&$A$45, Historique_Categorie,$A47, Historique_Enregistre,TRUE, Historique_Statut,"OK" ) -> 0 | F47: =SUMIFS( Historique_Montant, Historique_Mois,F$7, Historique_Section,"Dépenses fixes - "&$A$45, Historique_Categorie,$A47, Historique_Enregistre,TRUE, Historique_Statut,"OK" ) -> 0 | G47: =SUMIFS( Historique_Montant, Historique_Mois,G$7, Historique_Section,"Dépenses fixes - "&$A$45, Historique_Categorie,$A47, Historique_Enregistre,TRUE, Historique_Statut,"OK" ) -> 0 | H47: =SUMIFS( Historique_Montant, Historique_Mois,H$7, Historique_Section,"Dépenses fixes - "&$A$45, Historique_Categorie,$A47, Historique_Enregistre,TRUE, Historique_Statut,"OK" ) -> 0 | I47: =SUMIFS( Historique_Montant, Historique_Mois,I$7, Historique_Section,"Dépenses fixes - "&$A$45, Historique_Categorie,$A47, Historique_Enregistre,TRUE, Historique_Statut,"OK" ) -> 0 | ... M47: =SUMIFS( Historique_Montant, Historique_Mois,M$7, Historique_Section,"Dépenses fixes - "&$A$45, Historique_Categorie,$A47, Historique_Enregistre,TRUE, Historique_Statut,"OK" ) -> 0 | N47: =SUM(B47:M47) -> 0
A48: PEA | B48: =SUMIFS( Historique_Montant, Historique_Mois,B$7, Historique_Section,"Dépenses fixes - "&$A$45, Historique_Categorie,$A48, Historique_Enregistre,TRUE, Historique_Statut,"OK" ) -> 0 | C48: =SUMIFS( Historique_Montant, Historique_Mois,C$7, Historique_Section,"Dépenses fixes - "&$A$45, Historique_Categorie,$A48, Historique_Enregistre,TRUE, Historique_Statut,"OK" ) -> 0 | D48: =SUMIFS( Historique_Montant, Historique_Mois,D$7, Historique_Section,"Dépenses fixes - "&$A$45, Historique_Categorie,$A48, Historique_Enregistre,TRUE, Historique_Statut,"OK" ) -> 0 | E48: =SUMIFS( Historique_Montant, Historique_Mois,E$7, Historique_Section,"Dépenses fixes - "&$A$45, Historique_Categorie,$A48, Historique_Enregistre,TRUE, Historique_Statut,"OK" ) -> 0 | F48: =SUMIFS( Historique_Montant, Historique_Mois,F$7, Historique_Section,"Dépenses fixes - "&$A$45, Historique_Categorie,$A48, Historique_Enregistre,TRUE, Historique_Statut,"OK" ) -> 0 | G48: =SUMIFS( Historique_Montant, Historique_Mois,G$7, Historique_Section,"Dépenses fixes - "&$A$45, Historique_Categorie,$A48, Historique_Enregistre,TRUE, Historique_Statut,"OK" ) -> 0 | H48: =SUMIFS( Historique_Montant, Historique_Mois,H$7, Historique_Section,"Dépenses fixes - "&$A$45, Historique_Categorie,$A48, Historique_Enregistre,TRUE, Historique_Statut,"OK" ) -> 0 | I48: =SUMIFS( Historique_Montant, Historique_Mois,I$7, Historique_Section,"Dépenses fixes - "&$A$45, Historique_Categorie,$A48, Historique_Enregistre,TRUE, Historique_Statut,"OK" ) -> 0 | ... M48: =SUMIFS( Historique_Montant, Historique_Mois,M$7, Historique_Section,"Dépenses fixes - "&$A$45, Historique_Categorie,$A48, Historique_Enregistre,TRUE, Historique_Statut,"OK" ) -> 0 | N48: =SUM(B48:M48) -> 0
A49: Epargne de sécurité | B49: =SUMIFS( Historique_Montant, Historique_Mois,B$7, Historique_Section,"Dépenses fixes - "&$A$45, Historique_Categorie,$A49, Historique_Enregistre,TRUE, Historique_Statut,"OK" ) -> 0 | C49: =SUMIFS( Historique_Montant, Historique_Mois,C$7, Historique_Section,"Dépenses fixes - "&$A$45, Historique_Categorie,$A49, Historique_Enregistre,TRUE, Historique_Statut,"OK" ) -> 0 | D49: =SUMIFS( Historique_Montant, Historique_Mois,D$7, Historique_Section,"Dépenses fixes - "&$A$45, Historique_Categorie,$A49, Historique_Enregistre,TRUE, Historique_Statut,"OK" ) -> 0 | E49: =SUMIFS( Historique_Montant, Historique_Mois,E$7, Historique_Section,"Dépenses fixes - "&$A$45, Historique_Categorie,$A49, Historique_Enregistre,TRUE, Historique_Statut,"OK" ) -> 0 | F49: =SUMIFS( Historique_Montant, Historique_Mois,F$7, Historique_Section,"Dépenses fixes - "&$A$45, Historique_Categorie,$A49, Historique_Enregistre,TRUE, Historique_Statut,"OK" ) -> 0 | G49: =SUMIFS( Historique_Montant, Historique_Mois,G$7, Historique_Section,"Dépenses fixes - "&$A$45, Historique_Categorie,$A49, Historique_Enregistre,TRUE, Historique_Statut,"OK" ) -> 0 | H49: =SUMIFS( Historique_Montant, Historique_Mois,H$7, Historique_Section,"Dépenses fixes - "&$A$45, Historique_Categorie,$A49, Historique_Enregistre,TRUE, Historique_Statut,"OK" ) -> 0 | I49: =SUMIFS( Historique_Montant, Historique_Mois,I$7, Historique_Section,"Dépenses fixes - "&$A$45, Historique_Categorie,$A49, Historique_Enregistre,TRUE, Historique_Statut,"OK" ) -> 0 | ... M49: =SUMIFS( Historique_Montant, Historique_Mois,M$7, Historique_Section,"Dépenses fixes - "&$A$45, Historique_Categorie,$A49, Historique_Enregistre,TRUE, Historique_Statut,"OK" ) -> 0 | N49: =SUM(B49:M49) -> 0
A50: Compte joint | B50: =SUMIFS( Historique_Montant, Historique_Mois,B$7, Historique_Section,"Dépenses fixes - "&$A$45, Historique_Categorie,$A50, Historique_Enregistre,TRUE, Historique_Statut,"OK" ) -> 0 | C50: =SUMIFS( Historique_Montant, Historique_Mois,C$7, Historique_Section,"Dépenses fixes - "&$A$45, Historique_Categorie,$A50, Historique_Enregistre,TRUE, Historique_Statut,"OK" ) -> 0 | D50: =SUMIFS( Historique_Montant, Historique_Mois,D$7, Historique_Section,"Dépenses fixes - "&$A$45, Historique_Categorie,$A50, Historique_Enregistre,TRUE, Historique_Statut,"OK" ) -> 0 | E50: =SUMIFS( Historique_Montant, Historique_Mois,E$7, Historique_Section,"Dépenses fixes - "&$A$45, Historique_Categorie,$A50, Historique_Enregistre,TRUE, Historique_Statut,"OK" ) -> 0 | F50: =SUMIFS( Historique_Montant, Historique_Mois,F$7, Historique_Section,"Dépenses fixes - "&$A$45, Historique_Categorie,$A50, Historique_Enregistre,TRUE, Historique_Statut,"OK" ) -> 0 | G50: =SUMIFS( Historique_Montant, Historique_Mois,G$7, Historique_Section,"Dépenses fixes - "&$A$45, Historique_Categorie,$A50, Historique_Enregistre,TRUE, Historique_Statut,"OK" ) -> 0 | H50: =SUMIFS( Historique_Montant, Historique_Mois,H$7, Historique_Section,"Dépenses fixes - "&$A$45, Historique_Categorie,$A50, Historique_Enregistre,TRUE, Historique_Statut,"OK" ) -> 0 | I50: =SUMIFS( Historique_Montant, Historique_Mois,I$7, Historique_Section,"Dépenses fixes - "&$A$45, Historique_Categorie,$A50, Historique_Enregistre,TRUE, Historique_Statut,"OK" ) -> 0 | ... M50: =SUMIFS( Historique_Montant, Historique_Mois,M$7, Historique_Section,"Dépenses fixes - "&$A$45, Historique_Categorie,$A50, Historique_Enregistre,TRUE, Historique_Statut,"OK" ) -> 0 | N50: =SUM(B50:M50) -> 0
B51: =SUMIFS( Historique_Montant, Historique_Mois,B$7, Historique_Section,"Dépenses fixes - "&$A$45, Historique_Categorie,$A51, Historique_Enregistre,TRUE, Historique_Statut,"OK" ) -> 0 | C51: =SUMIFS( Historique_Montant, Historique_Mois,C$7, Historique_Section,"Dépenses fixes - "&$A$45, Historique_Categorie,$A51, Historique_Enregistre,TRUE, Historique_Statut,"OK" ) -> 0 | D51: =SUMIFS( Historique_Montant, Historique_Mois,D$7, Historique_Section,"Dépenses fixes - "&$A$45, Historique_Categorie,$A51, Historique_Enregistre,TRUE, Historique_Statut,"OK" ) -> 0 | E51: =SUMIFS( Historique_Montant, Historique_Mois,E$7, Historique_Section,"Dépenses fixes - "&$A$45, Historique_Categorie,$A51, Historique_Enregistre,TRUE, Historique_Statut,"OK" ) -> 0 | F51: =SUMIFS( Historique_Montant, Historique_Mois,F$7, Historique_Section,"Dépenses fixes - "&$A$45, Historique_Categorie,$A51, Historique_Enregistre,TRUE, Historique_Statut,"OK" ) -> 0 | G51: =SUMIFS( Historique_Montant, Historique_Mois,G$7, Historique_Section,"Dépenses fixes - "&$A$45, Historique_Categorie,$A51, Historique_Enregistre,TRUE, Historique_Statut,"OK" ) -> 0 | H51: =SUMIFS( Historique_Montant, Historique_Mois,H$7, Historique_Section,"Dépenses fixes - "&$A$45, Historique_Categorie,$A51, Historique_Enregistre,TRUE, Historique_Statut,"OK" ) -> 0 | I51: =SUMIFS( Historique_Montant, Historique_Mois,I$7, Historique_Section,"Dépenses fixes - "&$A$45, Historique_Categorie,$A51, Historique_Enregistre,TRUE, Historique_Statut,"OK" ) -> 0 | ... M51: =SUMIFS( Historique_Montant, Historique_Mois,M$7, Historique_Section,"Dépenses fixes - "&$A$45, Historique_Categorie,$A51, Historique_Enregistre,TRUE, Historique_Statut,"OK" ) -> 0 | N51: =SUM(B51:M51) -> 0
B52: =SUMIFS( Historique_Montant, Historique_Mois,B$7, Historique_Section,"Dépenses fixes - "&$A$45, Historique_Categorie,$A52, Historique_Enregistre,TRUE, Historique_Statut,"OK" ) -> 0 | C52: =SUMIFS( Historique_Montant, Historique_Mois,C$7, Historique_Section,"Dépenses fixes - "&$A$45, Historique_Categorie,$A52, Historique_Enregistre,TRUE, Historique_Statut,"OK" ) -> 0 | D52: =SUMIFS( Historique_Montant, Historique_Mois,D$7, Historique_Section,"Dépenses fixes - "&$A$45, Historique_Categorie,$A52, Historique_Enregistre,TRUE, Historique_Statut,"OK" ) -> 0 | E52: =SUMIFS( Historique_Montant, Historique_Mois,E$7, Historique_Section,"Dépenses fixes - "&$A$45, Historique_Categorie,$A52, Historique_Enregistre,TRUE, Historique_Statut,"OK" ) -> 0 | F52: =SUMIFS( Historique_Montant, Historique_Mois,F$7, Historique_Section,"Dépenses fixes - "&$A$45, Historique_Categorie,$A52, Historique_Enregistre,TRUE, Historique_Statut,"OK" ) -> 0 | G52: =SUMIFS( Historique_Montant, Historique_Mois,G$7, Historique_Section,"Dépenses fixes - "&$A$45, Historique_Categorie,$A52, Historique_Enregistre,TRUE, Historique_Statut,"OK" ) -> 0 | H52: =SUMIFS( Historique_Montant, Historique_Mois,H$7, Historique_Section,"Dépenses fixes - "&$A$45, Historique_Categorie,$A52, Historique_Enregistre,TRUE, Historique_Statut,"OK" ) -> 0 | I52: =SUMIFS( Historique_Montant, Historique_Mois,I$7, Historique_Section,"Dépenses fixes - "&$A$45, Historique_Categorie,$A52, Historique_Enregistre,TRUE, Historique_Statut,"OK" ) -> 0 | ... M52: =SUMIFS( Historique_Montant, Historique_Mois,M$7, Historique_Section,"Dépenses fixes - "&$A$45, Historique_Categorie,$A52, Historique_Enregistre,TRUE, Historique_Statut,"OK" ) -> 0 | N52: =SUM(B52:M52) -> 0
A53: Autres (épargne et investissement) | B53: =SUMIFS( Historique_Montant, Historique_Mois,B$7, Historique_Section,"Dépenses fixes - "&$A$45, Historique_Categorie,$A53, Historique_Enregistre,TRUE, Historique_Statut,"OK" ) -> 0 | C53: =SUMIFS( Historique_Montant, Historique_Mois,C$7, Historique_Section,"Dépenses fixes - "&$A$45, Historique_Categorie,$A53, Historique_Enregistre,TRUE, Historique_Statut,"OK" ) -> 0 | D53: =SUMIFS( Historique_Montant, Historique_Mois,D$7, Historique_Section,"Dépenses fixes - "&$A$45, Historique_Categorie,$A53, Historique_Enregistre,TRUE, Historique_Statut,"OK" ) -> 0 | E53: =SUMIFS( Historique_Montant, Historique_Mois,E$7, Historique_Section,"Dépenses fixes - "&$A$45, Historique_Categorie,$A53, Historique_Enregistre,TRUE, Historique_Statut,"OK" ) -> 0 | F53: =SUMIFS( Historique_Montant, Historique_Mois,F$7, Historique_Section,"Dépenses fixes - "&$A$45, Historique_Categorie,$A53, Historique_Enregistre,TRUE, Historique_Statut,"OK" ) -> 0 | G53: =SUMIFS( Historique_Montant, Historique_Mois,G$7, Historique_Section,"Dépenses fixes - "&$A$45, Historique_Categorie,$A53, Historique_Enregistre,TRUE, Historique_Statut,"OK" ) -> 0 | H53: =SUMIFS( Historique_Montant, Historique_Mois,H$7, Historique_Section,"Dépenses fixes - "&$A$45, Historique_Categorie,$A53, Historique_Enregistre,TRUE, Historique_Statut,"OK" ) -> 0 | I53: =SUMIFS( Historique_Montant, Historique_Mois,I$7, Historique_Section,"Dépenses fixes - "&$A$45, Historique_Categorie,$A53, Historique_Enregistre,TRUE, Historique_Statut,"OK" ) -> 0 | ... M53: =SUMIFS( Historique_Montant, Historique_Mois,M$7, Historique_Section,"Dépenses fixes - "&$A$45, Historique_Categorie,$A53, Historique_Enregistre,TRUE, Historique_Statut,"OK" ) -> 0 | N53: =SUM(B53:M53) -> 0
A54: Obligations publiques | B54: =SUM(B55:B58) -> 0 | C54: =SUM(C55:C58) -> 0 | D54: =SUM(D55:D58) -> 0 | E54: =SUM(E55:E58) -> 0 | F54: =SUM(F55:F58) -> 0 | G54: =SUM(G55:G58) -> 0 | H54: =SUM(H55:H58) -> 0 | I54: =SUM(I55:I58) -> 0 | ... M54: =SUM(M55:M58) -> 0 | N54: =SUM(B54:M54) -> 0
A55: Impôts, taxes et amendes | B55: =SUMIFS( Historique_Montant, Historique_Mois,B$7, Historique_Section,"Dépenses fixes - "&$A$54, Historique_Categorie,$A55, Historique_Enregistre,TRUE, Historique_Statut,"OK" ) -> 0 | C55: =SUMIFS( Historique_Montant, Historique_Mois,C$7, Historique_Section,"Dépenses fixes - "&$A$54, Historique_Categorie,$A55, Historique_Enregistre,TRUE, Historique_Statut,"OK" ) -> 0 | D55: =SUMIFS( Historique_Montant, Historique_Mois,D$7, Historique_Section,"Dépenses fixes - "&$A$54, Historique_Categorie,$A55, Historique_Enregistre,TRUE, Historique_Statut,"OK" ) -> 0 | E55: =SUMIFS( Historique_Montant, Historique_Mois,E$7, Historique_Section,"Dépenses fixes - "&$A$54, Historique_Categorie,$A55, Historique_Enregistre,TRUE, Historique_Statut,"OK" ) -> 0 | F55: =SUMIFS( Historique_Montant, Historique_Mois,F$7, Historique_Section,"Dépenses fixes - "&$A$54, Historique_Categorie,$A55, Historique_Enregistre,TRUE, Historique_Statut,"OK" ) -> 0 | G55: =SUMIFS( Historique_Montant, Historique_Mois,G$7, Historique_Section,"Dépenses fixes - "&$A$54, Historique_Categorie,$A55, Historique_Enregistre,TRUE, Historique_Statut,"OK" ) -> 0 | H55: =SUMIFS( Historique_Montant, Historique_Mois,H$7, Historique_Section,"Dépenses fixes - "&$A$54, Historique_Categorie,$A55, Historique_Enregistre,TRUE, Historique_Statut,"OK" ) -> 0 | I55: =SUMIFS( Historique_Montant, Historique_Mois,I$7, Historique_Section,"Dépenses fixes - "&$A$54, Historique_Categorie,$A55, Historique_Enregistre,TRUE, Historique_Statut,"OK" ) -> 0 | ... M55: =SUMIFS( Historique_Montant, Historique_Mois,M$7, Historique_Section,"Dépenses fixes - "&$A$54, Historique_Categorie,$A55, Historique_Enregistre,TRUE, Historique_Statut,"OK" ) -> 0 | N55: =SUM(B55:M55) -> 0
B56: =SUMIFS( Historique_Montant, Historique_Mois,B$7, Historique_Section,"Dépenses fixes - "&$A$54, Historique_Categorie,$A56, Historique_Enregistre,TRUE, Historique_Statut,"OK" ) -> 0 | C56: =SUMIFS( Historique_Montant, Historique_Mois,C$7, Historique_Section,"Dépenses fixes - "&$A$54, Historique_Categorie,$A56, Historique_Enregistre,TRUE, Historique_Statut,"OK" ) -> 0 | D56: =SUMIFS( Historique_Montant, Historique_Mois,D$7, Historique_Section,"Dépenses fixes - "&$A$54, Historique_Categorie,$A56, Historique_Enregistre,TRUE, Historique_Statut,"OK" ) -> 0 | E56: =SUMIFS( Historique_Montant, Historique_Mois,E$7, Historique_Section,"Dépenses fixes - "&$A$54, Historique_Categorie,$A56, Historique_Enregistre,TRUE, Historique_Statut,"OK" ) -> 0 | F56: =SUMIFS( Historique_Montant, Historique_Mois,F$7, Historique_Section,"Dépenses fixes - "&$A$54, Historique_Categorie,$A56, Historique_Enregistre,TRUE, Historique_Statut,"OK" ) -> 0 | G56: =SUMIFS( Historique_Montant, Historique_Mois,G$7, Historique_Section,"Dépenses fixes - "&$A$54, Historique_Categorie,$A56, Historique_Enregistre,TRUE, Historique_Statut,"OK" ) -> 0 | H56: =SUMIFS( Historique_Montant, Historique_Mois,H$7, Historique_Section,"Dépenses fixes - "&$A$54, Historique_Categorie,$A56, Historique_Enregistre,TRUE, Historique_Statut,"OK" ) -> 0 | I56: =SUMIFS( Historique_Montant, Historique_Mois,I$7, Historique_Section,"Dépenses fixes - "&$A$54, Historique_Categorie,$A56, Historique_Enregistre,TRUE, Historique_Statut,"OK" ) -> 0 | ... M56: =SUMIFS( Historique_Montant, Historique_Mois,M$7, Historique_Section,"Dépenses fixes - "&$A$54, Historique_Categorie,$A56, Historique_Enregistre,TRUE, Historique_Statut,"OK" ) -> 0 | N56: =SUM(B56:M56) -> 0
B57: =SUMIFS( Historique_Montant, Historique_Mois,B$7, Historique_Section,"Dépenses fixes - "&$A$54, Historique_Categorie,$A57, Historique_Enregistre,TRUE, Historique_Statut,"OK" ) -> 0 | C57: =SUMIFS( Historique_Montant, Historique_Mois,C$7, Historique_Section,"Dépenses fixes - "&$A$54, Historique_Categorie,$A57, Historique_Enregistre,TRUE, Historique_Statut,"OK" ) -> 0 | D57: =SUMIFS( Historique_Montant, Historique_Mois,D$7, Historique_Section,"Dépenses fixes - "&$A$54, Historique_Categorie,$A57, Historique_Enregistre,TRUE, Historique_Statut,"OK" ) -> 0 | E57: =SUMIFS( Historique_Montant, Historique_Mois,E$7, Historique_Section,"Dépenses fixes - "&$A$54, Historique_Categorie,$A57, Historique_Enregistre,TRUE, Historique_Statut,"OK" ) -> 0 | F57: =SUMIFS( Historique_Montant, Historique_Mois,F$7, Historique_Section,"Dépenses fixes - "&$A$54, Historique_Categorie,$A57, Historique_Enregistre,TRUE, Historique_Statut,"OK" ) -> 0 | G57: =SUMIFS( Historique_Montant, Historique_Mois,G$7, Historique_Section,"Dépenses fixes - "&$A$54, Historique_Categorie,$A57, Historique_Enregistre,TRUE, Historique_Statut,"OK" ) -> 0 | H57: =SUMIFS( Historique_Montant, Historique_Mois,H$7, Historique_Section,"Dépenses fixes - "&$A$54, Historique_Categorie,$A57, Historique_Enregistre,TRUE, Historique_Statut,"OK" ) -> 0 | I57: =SUMIFS( Historique_Montant, Historique_Mois,I$7, Historique_Section,"Dépenses fixes - "&$A$54, Historique_Categorie,$A57, Historique_Enregistre,TRUE, Historique_Statut,"OK" ) -> 0 | ... M57: =SUMIFS( Historique_Montant, Historique_Mois,M$7, Historique_Section,"Dépenses fixes - "&$A$54, Historique_Categorie,$A57, Historique_Enregistre,TRUE, Historique_Statut,"OK" ) -> 0 | N57: =SUM(B57:M57) -> 0
A58: Autres (obligations publiques) | B58: =SUMIFS( Historique_Montant, Historique_Mois,B$7, Historique_Section,"Dépenses fixes - "&$A$54, Historique_Categorie,$A58, Historique_Enregistre,TRUE, Historique_Statut,"OK" ) -> 0 | C58: =SUMIFS( Historique_Montant, Historique_Mois,C$7, Historique_Section,"Dépenses fixes - "&$A$54, Historique_Categorie,$A58, Historique_Enregistre,TRUE, Historique_Statut,"OK" ) -> 0 | D58: =SUMIFS( Historique_Montant, Historique_Mois,D$7, Historique_Section,"Dépenses fixes - "&$A$54, Historique_Categorie,$A58, Historique_Enregistre,TRUE, Historique_Statut,"OK" ) -> 0 | E58: =SUMIFS( Historique_Montant, Historique_Mois,E$7, Historique_Section,"Dépenses fixes - "&$A$54, Historique_Categorie,$A58, Historique_Enregistre,TRUE, Historique_Statut,"OK" ) -> 0 | F58: =SUMIFS( Historique_Montant, Historique_Mois,F$7, Historique_Section,"Dépenses fixes - "&$A$54, Historique_Categorie,$A58, Historique_Enregistre,TRUE, Historique_Statut,"OK" ) -> 0 | G58: =SUMIFS( Historique_Montant, Historique_Mois,G$7, Historique_Section,"Dépenses fixes - "&$A$54, Historique_Categorie,$A58, Historique_Enregistre,TRUE, Historique_Statut,"OK" ) -> 0 | H58: =SUMIFS( Historique_Montant, Historique_Mois,H$7, Historique_Section,"Dépenses fixes - "&$A$54, Historique_Categorie,$A58, Historique_Enregistre,TRUE, Historique_Statut,"OK" ) -> 0 | I58: =SUMIFS( Historique_Montant, Historique_Mois,I$7, Historique_Section,"Dépenses fixes - "&$A$54, Historique_Categorie,$A58, Historique_Enregistre,TRUE, Historique_Statut,"OK" ) -> 0 | ... M58: =SUMIFS( Historique_Montant, Historique_Mois,M$7, Historique_Section,"Dépenses fixes - "&$A$54, Historique_Categorie,$A58, Historique_Enregistre,TRUE, Historique_Statut,"OK" ) -> 0 | N58: =SUM(B58:M58) -> 0
A59: TOTAL DÉPENSES FIXES | B59: =SUM(B20,B29,B35,B45,B54) -> 0 | C59: =SUM(C20,C29,C35,C45,C54) -> 0 | D59: =SUM(D20,D29,D35,D45,D54) -> 0 | E59: =SUM(E20,E29,E35,E45,E54) -> 0 | F59: =SUM(F20,F29,F35,F45,F54) -> 0 | G59: =SUM(G20,G29,G35,G45,G54) -> 0 | H59: =SUM(H20,H29,H35,H45,H54) -> 0 | I59: =SUM(I20,I29,I35,I45,I54) -> 0 | ... M59: =SUM(M20,M29,M35,M45,M54) -> 0 | N59: =SUM(B59:M59) -> 0
A61: RESTE pour les dépenses variables | B61: =B16-B59 -> 1800 | C61: =C16-C59 -> 0 | D61: =D16-D59 -> 0 | E61: =E16-E59 -> 0 | F61: =F16-F59 -> 0 | G61: =G16-G59 -> 0 | H61: =H16-H59 -> 0 | I61: =I16-I59 -> 0 | ... M61: =M16-M59 -> 0 | N61: =SUM(B61:M61) -> 1800
A64: D É P E N S E S V A R I A B L E S
B65: Janvier | C65: Février | D65: Mars | E65: Avril | F65: Mai | G65: Juin | H65: Juillet | I65: Août | J65: Septembre | K65: Octobre | L65: Novembre | M65: Décembre | N65: TOTAL ANNUEL
A66: Vie quotidienne | B66: =SUM(B67:B73) -> 0 | C66: =SUM(C67:C73) -> 0 | D66: =SUM(D67:D73) -> 0 | E66: =SUM(E67:E73) -> 0 | F66: =SUM(F67:F73) -> 0 | G66: =SUM(G67:G73) -> 0 | H66: =SUM(H67:H73) -> 0 | I66: =SUM(I67:I73) -> 0 | ... M66: =SUM(M67:M73) -> 0 | N66: =SUM(B66:M66) -> 0
A67: Restaurants, bar et cantine | B67: =SUMIFS( Historique_Montant, Historique_Mois,B$7, Historique_Section,"Dépenses variables - "&$A$66, Historique_Categorie,$A67, Historique_Enregistre,TRUE, Historique_Statut,"OK" ) -> 0 | C67: =SUMIFS( Historique_Montant, Historique_Mois,C$7, Historique_Section,"Dépenses variables - "&$A$66, Historique_Categorie,$A67, Historique_Enregistre,TRUE, Historique_Statut,"OK" ) -> 0 | D67: =SUMIFS( Historique_Montant, Historique_Mois,D$7, Historique_Section,"Dépenses variables - "&$A$66, Historique_Categorie,$A67, Historique_Enregistre,TRUE, Historique_Statut,"OK" ) -> 0 | E67: =SUMIFS( Historique_Montant, Historique_Mois,E$7, Historique_Section,"Dépenses variables - "&$A$66, Historique_Categorie,$A67, Historique_Enregistre,TRUE, Historique_Statut,"OK" ) -> 0 | F67: =SUMIFS( Historique_Montant, Historique_Mois,F$7, Historique_Section,"Dépenses variables - "&$A$66, Historique_Categorie,$A67, Historique_Enregistre,TRUE, Historique_Statut,"OK" ) -> 0 | G67: =SUMIFS( Historique_Montant, Historique_Mois,G$7, Historique_Section,"Dépenses variables - "&$A$66, Historique_Categorie,$A67, Historique_Enregistre,TRUE, Historique_Statut,"OK" ) -> 0 | H67: =SUMIFS( Historique_Montant, Historique_Mois,H$7, Historique_Section,"Dépenses variables - "&$A$66, Historique_Categorie,$A67, Historique_Enregistre,TRUE, Historique_Statut,"OK" ) -> 0 | I67: =SUMIFS( Historique_Montant, Historique_Mois,I$7, Historique_Section,"Dépenses variables - "&$A$66, Historique_Categorie,$A67, Historique_Enregistre,TRUE, Historique_Statut,"OK" ) -> 0 | ... M67: =SUMIFS( Historique_Montant, Historique_Mois,M$7, Historique_Section,"Dépenses variables - "&$A$66, Historique_Categorie,$A67, Historique_Enregistre,TRUE, Historique_Statut,"OK" ) -> 0 | N67: =SUM(B67:M67) -> 0
A68: Courses alimentaires | B68: =SUMIFS( Historique_Montant, Historique_Mois,B$7, Historique_Section,"Dépenses variables - "&$A$66, Historique_Categorie,$A68, Historique_Enregistre,TRUE, Historique_Statut,"OK" ) -> 0 | C68: =SUMIFS( Historique_Montant, Historique_Mois,C$7, Historique_Section,"Dépenses variables - "&$A$66, Historique_Categorie,$A68, Historique_Enregistre,TRUE, Historique_Statut,"OK" ) -> 0 | D68: =SUMIFS( Historique_Montant, Historique_Mois,D$7, Historique_Section,"Dépenses variables - "&$A$66, Historique_Categorie,$A68, Historique_Enregistre,TRUE, Historique_Statut,"OK" ) -> 0 | E68: =SUMIFS( Historique_Montant, Historique_Mois,E$7, Historique_Section,"Dépenses variables - "&$A$66, Historique_Categorie,$A68, Historique_Enregistre,TRUE, Historique_Statut,"OK" ) -> 0 | F68: =SUMIFS( Historique_Montant, Historique_Mois,F$7, Historique_Section,"Dépenses variables - "&$A$66, Historique_Categorie,$A68, Historique_Enregistre,TRUE, Historique_Statut,"OK" ) -> 0 | G68: =SUMIFS( Historique_Montant, Historique_Mois,G$7, Historique_Section,"Dépenses variables - "&$A$66, Historique_Categorie,$A68, Historique_Enregistre,TRUE, Historique_Statut,"OK" ) -> 0 | H68: =SUMIFS( Historique_Montant, Historique_Mois,H$7, Historique_Section,"Dépenses variables - "&$A$66, Historique_Categorie,$A68, Historique_Enregistre,TRUE, Historique_Statut,"OK" ) -> 0 | I68: =SUMIFS( Historique_Montant, Historique_Mois,I$7, Historique_Section,"Dépenses variables - "&$A$66, Historique_Categorie,$A68, Historique_Enregistre,TRUE, Historique_Statut,"OK" ) -> 0 | ... M68: =SUMIFS( Historique_Montant, Historique_Mois,M$7, Historique_Section,"Dépenses variables - "&$A$66, Historique_Categorie,$A68, Historique_Enregistre,TRUE, Historique_Statut,"OK" ) -> 0 | N68: =SUM(B68:M68) -> 0
A69: Achats courants | B69: =SUMIFS( Historique_Montant, Historique_Mois,B$7, Historique_Section,"Dépenses variables - "&$A$66, Historique_Categorie,$A69, Historique_Enregistre,TRUE, Historique_Statut,"OK" ) -> 0 | C69: =SUMIFS( Historique_Montant, Historique_Mois,C$7, Historique_Section,"Dépenses variables - "&$A$66, Historique_Categorie,$A69, Historique_Enregistre,TRUE, Historique_Statut,"OK" ) -> 0 | D69: =SUMIFS( Historique_Montant, Historique_Mois,D$7, Historique_Section,"Dépenses variables - "&$A$66, Historique_Categorie,$A69, Historique_Enregistre,TRUE, Historique_Statut,"OK" ) -> 0 | E69: =SUMIFS( Historique_Montant, Historique_Mois,E$7, Historique_Section,"Dépenses variables - "&$A$66, Historique_Categorie,$A69, Historique_Enregistre,TRUE, Historique_Statut,"OK" ) -> 0 | F69: =SUMIFS( Historique_Montant, Historique_Mois,F$7, Historique_Section,"Dépenses variables - "&$A$66, Historique_Categorie,$A69, Historique_Enregistre,TRUE, Historique_Statut,"OK" ) -> 0 | G69: =SUMIFS( Historique_Montant, Historique_Mois,G$7, Historique_Section,"Dépenses variables - "&$A$66, Historique_Categorie,$A69, Historique_Enregistre,TRUE, Historique_Statut,"OK" ) -> 0 | H69: =SUMIFS( Historique_Montant, Historique_Mois,H$7, Historique_Section,"Dépenses variables - "&$A$66, Historique_Categorie,$A69, Historique_Enregistre,TRUE, Historique_Statut,"OK" ) -> 0 | I69: =SUMIFS( Historique_Montant, Historique_Mois,I$7, Historique_Section,"Dépenses variables - "&$A$66, Historique_Categorie,$A69, Historique_Enregistre,TRUE, Historique_Statut,"OK" ) -> 0 | ... M69: =SUMIFS( Historique_Montant, Historique_Mois,M$7, Historique_Section,"Dépenses variables - "&$A$66, Historique_Categorie,$A69, Historique_Enregistre,TRUE, Historique_Statut,"OK" ) -> 0 | N69: =SUM(B69:M69) -> 0
A70: Esthétique | B70: =SUMIFS( Historique_Montant, Historique_Mois,B$7, Historique_Section,"Dépenses variables - "&$A$66, Historique_Categorie,$A70, Historique_Enregistre,TRUE, Historique_Statut,"OK" ) -> 0 | C70: =SUMIFS( Historique_Montant, Historique_Mois,C$7, Historique_Section,"Dépenses variables - "&$A$66, Historique_Categorie,$A70, Historique_Enregistre,TRUE, Historique_Statut,"OK" ) -> 0 | D70: =SUMIFS( Historique_Montant, Historique_Mois,D$7, Historique_Section,"Dépenses variables - "&$A$66, Historique_Categorie,$A70, Historique_Enregistre,TRUE, Historique_Statut,"OK" ) -> 0 | E70: =SUMIFS( Historique_Montant, Historique_Mois,E$7, Historique_Section,"Dépenses variables - "&$A$66, Historique_Categorie,$A70, Historique_Enregistre,TRUE, Historique_Statut,"OK" ) -> 0 | F70: =SUMIFS( Historique_Montant, Historique_Mois,F$7, Historique_Section,"Dépenses variables - "&$A$66, Historique_Categorie,$A70, Historique_Enregistre,TRUE, Historique_Statut,"OK" ) -> 0 | G70: =SUMIFS( Historique_Montant, Historique_Mois,G$7, Historique_Section,"Dépenses variables - "&$A$66, Historique_Categorie,$A70, Historique_Enregistre,TRUE, Historique_Statut,"OK" ) -> 0 | H70: =SUMIFS( Historique_Montant, Historique_Mois,H$7, Historique_Section,"Dépenses variables - "&$A$66, Historique_Categorie,$A70, Historique_Enregistre,TRUE, Historique_Statut,"OK" ) -> 0 | I70: =SUMIFS( Historique_Montant, Historique_Mois,I$7, Historique_Section,"Dépenses variables - "&$A$66, Historique_Categorie,$A70, Historique_Enregistre,TRUE, Historique_Statut,"OK" ) -> 0 | ... M70: =SUMIFS( Historique_Montant, Historique_Mois,M$7, Historique_Section,"Dépenses variables - "&$A$66, Historique_Categorie,$A70, Historique_Enregistre,TRUE, Historique_Statut,"OK" ) -> 0 | N70: =SUM(B70:M70) -> 0
A71: Frais de santé | B71: =SUMIFS( Historique_Montant, Historique_Mois,B$7, Historique_Section,"Dépenses variables - "&$A$66, Historique_Categorie,$A71, Historique_Enregistre,TRUE, Historique_Statut,"OK" ) -> 0 | C71: =SUMIFS( Historique_Montant, Historique_Mois,C$7, Historique_Section,"Dépenses variables - "&$A$66, Historique_Categorie,$A71, Historique_Enregistre,TRUE, Historique_Statut,"OK" ) -> 0 | D71: =SUMIFS( Historique_Montant, Historique_Mois,D$7, Historique_Section,"Dépenses variables - "&$A$66, Historique_Categorie,$A71, Historique_Enregistre,TRUE, Historique_Statut,"OK" ) -> 0 | E71: =SUMIFS( Historique_Montant, Historique_Mois,E$7, Historique_Section,"Dépenses variables - "&$A$66, Historique_Categorie,$A71, Historique_Enregistre,TRUE, Historique_Statut,"OK" ) -> 0 | F71: =SUMIFS( Historique_Montant, Historique_Mois,F$7, Historique_Section,"Dépenses variables - "&$A$66, Historique_Categorie,$A71, Historique_Enregistre,TRUE, Historique_Statut,"OK" ) -> 0 | G71: =SUMIFS( Historique_Montant, Historique_Mois,G$7, Historique_Section,"Dépenses variables - "&$A$66, Historique_Categorie,$A71, Historique_Enregistre,TRUE, Historique_Statut,"OK" ) -> 0 | H71: =SUMIFS( Historique_Montant, Historique_Mois,H$7, Historique_Section,"Dépenses variables - "&$A$66, Historique_Categorie,$A71, Historique_Enregistre,TRUE, Historique_Statut,"OK" ) -> 0 | I71: =SUMIFS( Historique_Montant, Historique_Mois,I$7, Historique_Section,"Dépenses variables - "&$A$66, Historique_Categorie,$A71, Historique_Enregistre,TRUE, Historique_Statut,"OK" ) -> 0 | ... M71: =SUMIFS( Historique_Montant, Historique_Mois,M$7, Historique_Section,"Dépenses variables - "&$A$66, Historique_Categorie,$A71, Historique_Enregistre,TRUE, Historique_Statut,"OK" ) -> 0 | N71: =SUM(B71:M71) -> 0
B72: =SUMIFS( Historique_Montant, Historique_Mois,B$7, Historique_Section,"Dépenses variables - "&$A$66, Historique_Categorie,$A72, Historique_Enregistre,TRUE, Historique_Statut,"OK" ) -> 0 | C72: =SUMIFS( Historique_Montant, Historique_Mois,C$7, Historique_Section,"Dépenses variables - "&$A$66, Historique_Categorie,$A72, Historique_Enregistre,TRUE, Historique_Statut,"OK" ) -> 0 | D72: =SUMIFS( Historique_Montant, Historique_Mois,D$7, Historique_Section,"Dépenses variables - "&$A$66, Historique_Categorie,$A72, Historique_Enregistre,TRUE, Historique_Statut,"OK" ) -> 0 | E72: =SUMIFS( Historique_Montant, Historique_Mois,E$7, Historique_Section,"Dépenses variables - "&$A$66, Historique_Categorie,$A72, Historique_Enregistre,TRUE, Historique_Statut,"OK" ) -> 0 | F72: =SUMIFS( Historique_Montant, Historique_Mois,F$7, Historique_Section,"Dépenses variables - "&$A$66, Historique_Categorie,$A72, Historique_Enregistre,TRUE, Historique_Statut,"OK" ) -> 0 | G72: =SUMIFS( Historique_Montant, Historique_Mois,G$7, Historique_Section,"Dépenses variables - "&$A$66, Historique_Categorie,$A72, Historique_Enregistre,TRUE, Historique_Statut,"OK" ) -> 0 | H72: =SUMIFS( Historique_Montant, Historique_Mois,H$7, Historique_Section,"Dépenses variables - "&$A$66, Historique_Categorie,$A72, Historique_Enregistre,TRUE, Historique_Statut,"OK" ) -> 0 | I72: =SUMIFS( Historique_Montant, Historique_Mois,I$7, Historique_Section,"Dépenses variables - "&$A$66, Historique_Categorie,$A72, Historique_Enregistre,TRUE, Historique_Statut,"OK" ) -> 0 | ... M72: =SUMIFS( Historique_Montant, Historique_Mois,M$7, Historique_Section,"Dépenses variables - "&$A$66, Historique_Categorie,$A72, Historique_Enregistre,TRUE, Historique_Statut,"OK" ) -> 0 | N72: =SUM(B72:M72) -> 0
B73: =SUMIFS( Historique_Montant, Historique_Mois,B$7, Historique_Section,"Dépenses variables - "&$A$66, Historique_Categorie,$A73, Historique_Enregistre,TRUE, Historique_Statut,"OK" ) -> 0 | C73: =SUMIFS( Historique_Montant, Historique_Mois,C$7, Historique_Section,"Dépenses variables - "&$A$66, Historique_Categorie,$A73, Historique_Enregistre,TRUE, Historique_Statut,"OK" ) -> 0 | D73: =SUMIFS( Historique_Montant, Historique_Mois,D$7, Historique_Section,"Dépenses variables - "&$A$66, Historique_Categorie,$A73, Historique_Enregistre,TRUE, Historique_Statut,"OK" ) -> 0 | E73: =SUMIFS( Historique_Montant, Historique_Mois,E$7, Historique_Section,"Dépenses variables - "&$A$66, Historique_Categorie,$A73, Historique_Enregistre,TRUE, Historique_Statut,"OK" ) -> 0 | F73: =SUMIFS( Historique_Montant, Historique_Mois,F$7, Historique_Section,"Dépenses variables - "&$A$66, Historique_Categorie,$A73, Historique_Enregistre,TRUE, Historique_Statut,"OK" ) -> 0 | G73: =SUMIFS( Historique_Montant, Historique_Mois,G$7, Historique_Section,"Dépenses variables - "&$A$66, Historique_Categorie,$A73, Historique_Enregistre,TRUE, Historique_Statut,"OK" ) -> 0 | H73: =SUMIFS( Historique_Montant, Historique_Mois,H$7, Historique_Section,"Dépenses variables - "&$A$66, Historique_Categorie,$A73, Historique_Enregistre,TRUE, Historique_Statut,"OK" ) -> 0 | I73: =SUMIFS( Historique_Montant, Historique_Mois,I$7, Historique_Section,"Dépenses variables - "&$A$66, Historique_Categorie,$A73, Historique_Enregistre,TRUE, Historique_Statut,"OK" ) -> 0 | ... M73: =SUMIFS( Historique_Montant, Historique_Mois,M$7, Historique_Section,"Dépenses variables - "&$A$66, Historique_Categorie,$A73, Historique_Enregistre,TRUE, Historique_Statut,"OK" ) -> 0 | N73: =SUM(B73:M73) -> 0
A74: Transport | B74: =SUM(B75:B81) -> 0 | C74: =SUM(C75:C81) -> 0 | D74: =SUM(D75:D81) -> 0 | E74: =SUM(E75:E81) -> 0 | F74: =SUM(F75:F81) -> 0 | G74: =SUM(G75:G81) -> 0 | H74: =SUM(H75:H81) -> 0 | I74: =SUM(I75:I81) -> 0 | ... M74: =SUM(M75:M81) -> 0 | N74: =SUM(B74:M74) -> 0
A75: Entretien voiture | B75: =SUMIFS( Historique_Montant, Historique_Mois,B$7, Historique_Section,"Dépenses variables - "&$A$74, Historique_Categorie,$A75, Historique_Enregistre,TRUE, Historique_Statut,"OK" ) -> 0 | C75: =SUMIFS( Historique_Montant, Historique_Mois,C$7, Historique_Section,"Dépenses variables - "&$A$74, Historique_Categorie,$A75, Historique_Enregistre,TRUE, Historique_Statut,"OK" ) -> 0 | D75: =SUMIFS( Historique_Montant, Historique_Mois,D$7, Historique_Section,"Dépenses variables - "&$A$74, Historique_Categorie,$A75, Historique_Enregistre,TRUE, Historique_Statut,"OK" ) -> 0 | E75: =SUMIFS( Historique_Montant, Historique_Mois,E$7, Historique_Section,"Dépenses variables - "&$A$74, Historique_Categorie,$A75, Historique_Enregistre,TRUE, Historique_Statut,"OK" ) -> 0 | F75: =SUMIFS( Historique_Montant, Historique_Mois,F$7, Historique_Section,"Dépenses variables - "&$A$74, Historique_Categorie,$A75, Historique_Enregistre,TRUE, Historique_Statut,"OK" ) -> 0 | G75: =SUMIFS( Historique_Montant, Historique_Mois,G$7, Historique_Section,"Dépenses variables - "&$A$74, Historique_Categorie,$A75, Historique_Enregistre,TRUE, Historique_Statut,"OK" ) -> 0 | H75: =SUMIFS( Historique_Montant, Historique_Mois,H$7, Historique_Section,"Dépenses variables - "&$A$74, Historique_Categorie,$A75, Historique_Enregistre,TRUE, Historique_Statut,"OK" ) -> 0 | I75: =SUMIFS( Historique_Montant, Historique_Mois,I$7, Historique_Section,"Dépenses variables - "&$A$74, Historique_Categorie,$A75, Historique_Enregistre,TRUE, Historique_Statut,"OK" ) -> 0 | ... M75: =SUMIFS( Historique_Montant, Historique_Mois,M$7, Historique_Section,"Dépenses variables - "&$A$74, Historique_Categorie,$A75, Historique_Enregistre,TRUE, Historique_Statut,"OK" ) -> 0 | N75: =SUM(B75:M75) -> 0
A76: Carburant | B76: =SUMIFS( Historique_Montant, Historique_Mois,B$7, Historique_Section,"Dépenses variables - "&$A$74, Historique_Categorie,$A76, Historique_Enregistre,TRUE, Historique_Statut,"OK" ) -> 0 | C76: =SUMIFS( Historique_Montant, Historique_Mois,C$7, Historique_Section,"Dépenses variables - "&$A$74, Historique_Categorie,$A76, Historique_Enregistre,TRUE, Historique_Statut,"OK" ) -> 0 | D76: =SUMIFS( Historique_Montant, Historique_Mois,D$7, Historique_Section,"Dépenses variables - "&$A$74, Historique_Categorie,$A76, Historique_Enregistre,TRUE, Historique_Statut,"OK" ) -> 0 | E76: =SUMIFS( Historique_Montant, Historique_Mois,E$7, Historique_Section,"Dépenses variables - "&$A$74, Historique_Categorie,$A76, Historique_Enregistre,TRUE, Historique_Statut,"OK" ) -> 0 | F76: =SUMIFS( Historique_Montant, Historique_Mois,F$7, Historique_Section,"Dépenses variables - "&$A$74, Historique_Categorie,$A76, Historique_Enregistre,TRUE, Historique_Statut,"OK" ) -> 0 | G76: =SUMIFS( Historique_Montant, Historique_Mois,G$7, Historique_Section,"Dépenses variables - "&$A$74, Historique_Categorie,$A76, Historique_Enregistre,TRUE, Historique_Statut,"OK" ) -> 0 | H76: =SUMIFS( Historique_Montant, Historique_Mois,H$7, Historique_Section,"Dépenses variables - "&$A$74, Historique_Categorie,$A76, Historique_Enregistre,TRUE, Historique_Statut,"OK" ) -> 0 | I76: =SUMIFS( Historique_Montant, Historique_Mois,I$7, Historique_Section,"Dépenses variables - "&$A$74, Historique_Categorie,$A76, Historique_Enregistre,TRUE, Historique_Statut,"OK" ) -> 0 | ... M76: =SUMIFS( Historique_Montant, Historique_Mois,M$7, Historique_Section,"Dépenses variables - "&$A$74, Historique_Categorie,$A76, Historique_Enregistre,TRUE, Historique_Statut,"OK" ) -> 0 | N76: =SUM(B76:M76) -> 0
A77: Parking | B77: =SUMIFS( Historique_Montant, Historique_Mois,B$7, Historique_Section,"Dépenses variables - "&$A$74, Historique_Categorie,$A77, Historique_Enregistre,TRUE, Historique_Statut,"OK" ) -> 0 | C77: =SUMIFS( Historique_Montant, Historique_Mois,C$7, Historique_Section,"Dépenses variables - "&$A$74, Historique_Categorie,$A77, Historique_Enregistre,TRUE, Historique_Statut,"OK" ) -> 0 | D77: =SUMIFS( Historique_Montant, Historique_Mois,D$7, Historique_Section,"Dépenses variables - "&$A$74, Historique_Categorie,$A77, Historique_Enregistre,TRUE, Historique_Statut,"OK" ) -> 0 | E77: =SUMIFS( Historique_Montant, Historique_Mois,E$7, Historique_Section,"Dépenses variables - "&$A$74, Historique_Categorie,$A77, Historique_Enregistre,TRUE, Historique_Statut,"OK" ) -> 0 | F77: =SUMIFS( Historique_Montant, Historique_Mois,F$7, Historique_Section,"Dépenses variables - "&$A$74, Historique_Categorie,$A77, Historique_Enregistre,TRUE, Historique_Statut,"OK" ) -> 0 | G77: =SUMIFS( Historique_Montant, Historique_Mois,G$7, Historique_Section,"Dépenses variables - "&$A$74, Historique_Categorie,$A77, Historique_Enregistre,TRUE, Historique_Statut,"OK" ) -> 0 | H77: =SUMIFS( Historique_Montant, Historique_Mois,H$7, Historique_Section,"Dépenses variables - "&$A$74, Historique_Categorie,$A77, Historique_Enregistre,TRUE, Historique_Statut,"OK" ) -> 0 | I77: =SUMIFS( Historique_Montant, Historique_Mois,I$7, Historique_Section,"Dépenses variables - "&$A$74, Historique_Categorie,$A77, Historique_Enregistre,TRUE, Historique_Statut,"OK" ) -> 0 | ... M77: =SUMIFS( Historique_Montant, Historique_Mois,M$7, Historique_Section,"Dépenses variables - "&$A$74, Historique_Categorie,$A77, Historique_Enregistre,TRUE, Historique_Statut,"OK" ) -> 0 | N77: =SUM(B77:M77) -> 0
A78: Péage | B78: =SUMIFS( Historique_Montant, Historique_Mois,B$7, Historique_Section,"Dépenses variables - "&$A$74, Historique_Categorie,$A78, Historique_Enregistre,TRUE, Historique_Statut,"OK" ) -> 0 | C78: =SUMIFS( Historique_Montant, Historique_Mois,C$7, Historique_Section,"Dépenses variables - "&$A$74, Historique_Categorie,$A78, Historique_Enregistre,TRUE, Historique_Statut,"OK" ) -> 0 | D78: =SUMIFS( Historique_Montant, Historique_Mois,D$7, Historique_Section,"Dépenses variables - "&$A$74, Historique_Categorie,$A78, Historique_Enregistre,TRUE, Historique_Statut,"OK" ) -> 0 | E78: =SUMIFS( Historique_Montant, Historique_Mois,E$7, Historique_Section,"Dépenses variables - "&$A$74, Historique_Categorie,$A78, Historique_Enregistre,TRUE, Historique_Statut,"OK" ) -> 0 | F78: =SUMIFS( Historique_Montant, Historique_Mois,F$7, Historique_Section,"Dépenses variables - "&$A$74, Historique_Categorie,$A78, Historique_Enregistre,TRUE, Historique_Statut,"OK" ) -> 0 | G78: =SUMIFS( Historique_Montant, Historique_Mois,G$7, Historique_Section,"Dépenses variables - "&$A$74, Historique_Categorie,$A78, Historique_Enregistre,TRUE, Historique_Statut,"OK" ) -> 0 | H78: =SUMIFS( Historique_Montant, Historique_Mois,H$7, Historique_Section,"Dépenses variables - "&$A$74, Historique_Categorie,$A78, Historique_Enregistre,TRUE, Historique_Statut,"OK" ) -> 0 | I78: =SUMIFS( Historique_Montant, Historique_Mois,I$7, Historique_Section,"Dépenses variables - "&$A$74, Historique_Categorie,$A78, Historique_Enregistre,TRUE, Historique_Statut,"OK" ) -> 0 | ... M78: =SUMIFS( Historique_Montant, Historique_Mois,M$7, Historique_Section,"Dépenses variables - "&$A$74, Historique_Categorie,$A78, Historique_Enregistre,TRUE, Historique_Statut,"OK" ) -> 0 | N78: =SUM(B78:M78) -> 0
A79: Transport en commun | B79: =SUMIFS( Historique_Montant, Historique_Mois,B$7, Historique_Section,"Dépenses variables - "&$A$74, Historique_Categorie,$A79, Historique_Enregistre,TRUE, Historique_Statut,"OK" ) -> 0 | C79: =SUMIFS( Historique_Montant, Historique_Mois,C$7, Historique_Section,"Dépenses variables - "&$A$74, Historique_Categorie,$A79, Historique_Enregistre,TRUE, Historique_Statut,"OK" ) -> 0 | D79: =SUMIFS( Historique_Montant, Historique_Mois,D$7, Historique_Section,"Dépenses variables - "&$A$74, Historique_Categorie,$A79, Historique_Enregistre,TRUE, Historique_Statut,"OK" ) -> 0 | E79: =SUMIFS( Historique_Montant, Historique_Mois,E$7, Historique_Section,"Dépenses variables - "&$A$74, Historique_Categorie,$A79, Historique_Enregistre,TRUE, Historique_Statut,"OK" ) -> 0 | F79: =SUMIFS( Historique_Montant, Historique_Mois,F$7, Historique_Section,"Dépenses variables - "&$A$74, Historique_Categorie,$A79, Historique_Enregistre,TRUE, Historique_Statut,"OK" ) -> 0 | G79: =SUMIFS( Historique_Montant, Historique_Mois,G$7, Historique_Section,"Dépenses variables - "&$A$74, Historique_Categorie,$A79, Historique_Enregistre,TRUE, Historique_Statut,"OK" ) -> 0 | H79: =SUMIFS( Historique_Montant, Historique_Mois,H$7, Historique_Section,"Dépenses variables - "&$A$74, Historique_Categorie,$A79, Historique_Enregistre,TRUE, Historique_Statut,"OK" ) -> 0 | I79: =SUMIFS( Historique_Montant, Historique_Mois,I$7, Historique_Section,"Dépenses variables - "&$A$74, Historique_Categorie,$A79, Historique_Enregistre,TRUE, Historique_Statut,"OK" ) -> 0 | ... M79: =SUMIFS( Historique_Montant, Historique_Mois,M$7, Historique_Section,"Dépenses variables - "&$A$74, Historique_Categorie,$A79, Historique_Enregistre,TRUE, Historique_Statut,"OK" ) -> 0 | N79: =SUM(B79:M79) -> 0
B80: =SUMIFS( Historique_Montant, Historique_Mois,B$7, Historique_Section,"Dépenses variables - "&$A$74, Historique_Categorie,$A80, Historique_Enregistre,TRUE, Historique_Statut,"OK" ) -> 0 | C80: =SUMIFS( Historique_Montant, Historique_Mois,C$7, Historique_Section,"Dépenses variables - "&$A$74, Historique_Categorie,$A80, Historique_Enregistre,TRUE, Historique_Statut,"OK" ) -> 0 | D80: =SUMIFS( Historique_Montant, Historique_Mois,D$7, Historique_Section,"Dépenses variables - "&$A$74, Historique_Categorie,$A80, Historique_Enregistre,TRUE, Historique_Statut,"OK" ) -> 0 | E80: =SUMIFS( Historique_Montant, Historique_Mois,E$7, Historique_Section,"Dépenses variables - "&$A$74, Historique_Categorie,$A80, Historique_Enregistre,TRUE, Historique_Statut,"OK" ) -> 0 | F80: =SUMIFS( Historique_Montant, Historique_Mois,F$7, Historique_Section,"Dépenses variables - "&$A$74, Historique_Categorie,$A80, Historique_Enregistre,TRUE, Historique_Statut,"OK" ) -> 0 | G80: =SUMIFS( Historique_Montant, Historique_Mois,G$7, Historique_Section,"Dépenses variables - "&$A$74, Historique_Categorie,$A80, Historique_Enregistre,TRUE, Historique_Statut,"OK" ) -> 0 | H80: =SUMIFS( Historique_Montant, Historique_Mois,H$7, Historique_Section,"Dépenses variables - "&$A$74, Historique_Categorie,$A80, Historique_Enregistre,TRUE, Historique_Statut,"OK" ) -> 0 | I80: =SUMIFS( Historique_Montant, Historique_Mois,I$7, Historique_Section,"Dépenses variables - "&$A$74, Historique_Categorie,$A80, Historique_Enregistre,TRUE, Historique_Statut,"OK" ) -> 0 | ... M80: =SUMIFS( Historique_Montant, Historique_Mois,M$7, Historique_Section,"Dépenses variables - "&$A$74, Historique_Categorie,$A80, Historique_Enregistre,TRUE, Historique_Statut,"OK" ) -> 0 | N80: =SUM(B80:M80) -> 0
B81: =SUMIFS( Historique!$E$6:$E$332, Historique!$A$6:$A$332,B$7, Historique!$B$6:$B$332,"Dépenses variables - "&$A$74, Historique!$C$6:$C$332,$A81, Historique!$F$6:$F$332,TRUE ) -> 0 | C81: =SUMIFS( Historique!$E$6:$E$332, Historique!$A$6:$A$332,C$7, Historique!$B$6:$B$332,"Dépenses variables - "&$A$74, Historique!$C$6:$C$332,$A81, Historique!$F$6:$F$332,TRUE ) -> 0 | D81: =SUMIFS( Historique!$E$6:$E$332, Historique!$A$6:$A$332,D$7, Historique!$B$6:$B$332,"Dépenses variables - "&$A$74, Historique!$C$6:$C$332,$A81, Historique!$F$6:$F$332,TRUE ) -> 0 | E81: =SUMIFS( Historique!$E$6:$E$332, Historique!$A$6:$A$332,E$7, Historique!$B$6:$B$332,"Dépenses variables - "&$A$74, Historique!$C$6:$C$332,$A81, Historique!$F$6:$F$332,TRUE ) -> 0 | F81: =SUMIFS( Historique!$E$6:$E$332, Historique!$A$6:$A$332,F$7, Historique!$B$6:$B$332,"Dépenses variables - "&$A$74, Historique!$C$6:$C$332,$A81, Historique!$F$6:$F$332,TRUE ) -> 0 | G81: =SUMIFS( Historique!$E$6:$E$332, Historique!$A$6:$A$332,G$7, Historique!$B$6:$B$332,"Dépenses variables - "&$A$74, Historique!$C$6:$C$332,$A81, Historique!$F$6:$F$332,TRUE ) -> 0 | H81: =SUMIFS( Historique!$E$6:$E$332, Historique!$A$6:$A$332,H$7, Historique!$B$6:$B$332,"Dépenses variables - "&$A$74, Historique!$C$6:$C$332,$A81, Historique!$F$6:$F$332,TRUE ) -> 0 | I81: =SUMIFS( Historique!$E$6:$E$332, Historique!$A$6:$A$332,I$7, Historique!$B$6:$B$332,"Dépenses variables - "&$A$74, Historique!$C$6:$C$332,$A81, Historique!$F$6:$F$332,TRUE ) -> 0 | ... M81: =SUMIFS( Historique!$E$6:$E$332, Historique!$A$6:$A$332,M$7, Historique!$B$6:$B$332,"Dépenses variables - "&$A$74, Historique!$C$6:$C$332,$A81, Historique!$F$6:$F$332,TRUE ) -> 0 | N81: =SUM(B81:M81) -> 0
A82: Loisirs, voyages et cadeaux | B82: =SUM(B83:B89) -> 0 | C82: =SUM(C83:C89) -> 0 | D82: =SUM(D83:D89) -> 0 | E82: =SUM(E83:E89) -> 0 | F82: =SUM(F83:F89) -> 0 | G82: =SUM(G83:G89) -> 0 | H82: =SUM(H83:H89) -> 0 | I82: =SUM(I83:I89) -> 0 | ... M82: =SUM(M83:M89) -> 0 | N82: =SUM(B82:M82) -> 0
A83: Sorties | B83: =SUMIFS( Historique_Montant, Historique_Mois,B$7, Historique_Section,"Dépenses variables - "&$A$82, Historique_Categorie,$A83, Historique_Enregistre,TRUE, Historique_Statut,"OK" ) -> 0 | C83: =SUMIFS( Historique_Montant, Historique_Mois,C$7, Historique_Section,"Dépenses variables - "&$A$82, Historique_Categorie,$A83, Historique_Enregistre,TRUE, Historique_Statut,"OK" ) -> 0 | D83: =SUMIFS( Historique_Montant, Historique_Mois,D$7, Historique_Section,"Dépenses variables - "&$A$82, Historique_Categorie,$A83, Historique_Enregistre,TRUE, Historique_Statut,"OK" ) -> 0 | E83: =SUMIFS( Historique_Montant, Historique_Mois,E$7, Historique_Section,"Dépenses variables - "&$A$82, Historique_Categorie,$A83, Historique_Enregistre,TRUE, Historique_Statut,"OK" ) -> 0 | F83: =SUMIFS( Historique_Montant, Historique_Mois,F$7, Historique_Section,"Dépenses variables - "&$A$82, Historique_Categorie,$A83, Historique_Enregistre,TRUE, Historique_Statut,"OK" ) -> 0 | G83: =SUMIFS( Historique_Montant, Historique_Mois,G$7, Historique_Section,"Dépenses variables - "&$A$82, Historique_Categorie,$A83, Historique_Enregistre,TRUE, Historique_Statut,"OK" ) -> 0 | H83: =SUMIFS( Historique_Montant, Historique_Mois,H$7, Historique_Section,"Dépenses variables - "&$A$82, Historique_Categorie,$A83, Historique_Enregistre,TRUE, Historique_Statut,"OK" ) -> 0 | I83: =SUMIFS( Historique_Montant, Historique_Mois,I$7, Historique_Section,"Dépenses variables - "&$A$82, Historique_Categorie,$A83, Historique_Enregistre,TRUE, Historique_Statut,"OK" ) -> 0 | ... M83: =SUMIFS( Historique_Montant, Historique_Mois,M$7, Historique_Section,"Dépenses variables - "&$A$82, Historique_Categorie,$A83, Historique_Enregistre,TRUE, Historique_Statut,"OK" ) -> 0 | N83: =SUM(B83:M83) -> 0
A84: Vacances et voyages | B84: =SUMIFS( Historique_Montant, Historique_Mois,B$7, Historique_Section,"Dépenses variables - "&$A$82, Historique_Categorie,$A84, Historique_Enregistre,TRUE, Historique_Statut,"OK" ) -> 0 | C84: =SUMIFS( Historique_Montant, Historique_Mois,C$7, Historique_Section,"Dépenses variables - "&$A$82, Historique_Categorie,$A84, Historique_Enregistre,TRUE, Historique_Statut,"OK" ) -> 0 | D84: =SUMIFS( Historique_Montant, Historique_Mois,D$7, Historique_Section,"Dépenses variables - "&$A$82, Historique_Categorie,$A84, Historique_Enregistre,TRUE, Historique_Statut,"OK" ) -> 0 | E84: =SUMIFS( Historique_Montant, Historique_Mois,E$7, Historique_Section,"Dépenses variables - "&$A$82, Historique_Categorie,$A84, Historique_Enregistre,TRUE, Historique_Statut,"OK" ) -> 0 | F84: =SUMIFS( Historique_Montant, Historique_Mois,F$7, Historique_Section,"Dépenses variables - "&$A$82, Historique_Categorie,$A84, Historique_Enregistre,TRUE, Historique_Statut,"OK" ) -> 0 | G84: =SUMIFS( Historique_Montant, Historique_Mois,G$7, Historique_Section,"Dépenses variables - "&$A$82, Historique_Categorie,$A84, Historique_Enregistre,TRUE, Historique_Statut,"OK" ) -> 0 | H84: =SUMIFS( Historique_Montant, Historique_Mois,H$7, Historique_Section,"Dépenses variables - "&$A$82, Historique_Categorie,$A84, Historique_Enregistre,TRUE, Historique_Statut,"OK" ) -> 0 | I84: =SUMIFS( Historique_Montant, Historique_Mois,I$7, Historique_Section,"Dépenses variables - "&$A$82, Historique_Categorie,$A84, Historique_Enregistre,TRUE, Historique_Statut,"OK" ) -> 0 | ... M84: =SUMIFS( Historique_Montant, Historique_Mois,M$7, Historique_Section,"Dépenses variables - "&$A$82, Historique_Categorie,$A84, Historique_Enregistre,TRUE, Historique_Statut,"OK" ) -> 0 | N84: =SUM(B84:M84) -> 0
A85: Anniversaire et cadeaux | B85: =SUMIFS( Historique_Montant, Historique_Mois,B$7, Historique_Section,"Dépenses variables - "&$A$82, Historique_Categorie,$A85, Historique_Enregistre,TRUE, Historique_Statut,"OK" ) -> 0 | C85: =SUMIFS( Historique_Montant, Historique_Mois,C$7, Historique_Section,"Dépenses variables - "&$A$82, Historique_Categorie,$A85, Historique_Enregistre,TRUE, Historique_Statut,"OK" ) -> 0 | D85: =SUMIFS( Historique_Montant, Historique_Mois,D$7, Historique_Section,"Dépenses variables - "&$A$82, Historique_Categorie,$A85, Historique_Enregistre,TRUE, Historique_Statut,"OK" ) -> 0 | E85: =SUMIFS( Historique_Montant, Historique_Mois,E$7, Historique_Section,"Dépenses variables - "&$A$82, Historique_Categorie,$A85, Historique_Enregistre,TRUE, Historique_Statut,"OK" ) -> 0 | F85: =SUMIFS( Historique_Montant, Historique_Mois,F$7, Historique_Section,"Dépenses variables - "&$A$82, Historique_Categorie,$A85, Historique_Enregistre,TRUE, Historique_Statut,"OK" ) -> 0 | G85: =SUMIFS( Historique_Montant, Historique_Mois,G$7, Historique_Section,"Dépenses variables - "&$A$82, Historique_Categorie,$A85, Historique_Enregistre,TRUE, Historique_Statut,"OK" ) -> 0 | H85: =SUMIFS( Historique_Montant, Historique_Mois,H$7, Historique_Section,"Dépenses variables - "&$A$82, Historique_Categorie,$A85, Historique_Enregistre,TRUE, Historique_Statut,"OK" ) -> 0 | I85: =SUMIFS( Historique_Montant, Historique_Mois,I$7, Historique_Section,"Dépenses variables - "&$A$82, Historique_Categorie,$A85, Historique_Enregistre,TRUE, Historique_Statut,"OK" ) -> 0 | ... M85: =SUMIFS( Historique_Montant, Historique_Mois,M$7, Historique_Section,"Dépenses variables - "&$A$82, Historique_Categorie,$A85, Historique_Enregistre,TRUE, Historique_Statut,"OK" ) -> 0 | N85: =SUM(B85:M85) -> 0
A86: Livres, musique et jeux | B86: =SUMIFS( Historique_Montant, Historique_Mois,B$7, Historique_Section,"Dépenses variables - "&$A$82, Historique_Categorie,$A86, Historique_Enregistre,TRUE, Historique_Statut,"OK" ) -> 0 | C86: =SUMIFS( Historique_Montant, Historique_Mois,C$7, Historique_Section,"Dépenses variables - "&$A$82, Historique_Categorie,$A86, Historique_Enregistre,TRUE, Historique_Statut,"OK" ) -> 0 | D86: =SUMIFS( Historique_Montant, Historique_Mois,D$7, Historique_Section,"Dépenses variables - "&$A$82, Historique_Categorie,$A86, Historique_Enregistre,TRUE, Historique_Statut,"OK" ) -> 0 | E86: =SUMIFS( Historique_Montant, Historique_Mois,E$7, Historique_Section,"Dépenses variables - "&$A$82, Historique_Categorie,$A86, Historique_Enregistre,TRUE, Historique_Statut,"OK" ) -> 0 | F86: =SUMIFS( Historique_Montant, Historique_Mois,F$7, Historique_Section,"Dépenses variables - "&$A$82, Historique_Categorie,$A86, Historique_Enregistre,TRUE, Historique_Statut,"OK" ) -> 0 | G86: =SUMIFS( Historique_Montant, Historique_Mois,G$7, Historique_Section,"Dépenses variables - "&$A$82, Historique_Categorie,$A86, Historique_Enregistre,TRUE, Historique_Statut,"OK" ) -> 0 | H86: =SUMIFS( Historique_Montant, Historique_Mois,H$7, Historique_Section,"Dépenses variables - "&$A$82, Historique_Categorie,$A86, Historique_Enregistre,TRUE, Historique_Statut,"OK" ) -> 0 | I86: =SUMIFS( Historique_Montant, Historique_Mois,I$7, Historique_Section,"Dépenses variables - "&$A$82, Historique_Categorie,$A86, Historique_Enregistre,TRUE, Historique_Statut,"OK" ) -> 0 | ... M86: =SUMIFS( Historique_Montant, Historique_Mois,M$7, Historique_Section,"Dépenses variables - "&$A$82, Historique_Categorie,$A86, Historique_Enregistre,TRUE, Historique_Statut,"OK" ) -> 0 | N86: =SUM(B86:M86) -> 0
A87: Sport (escalade, etc..) | B87: =SUMIFS( Historique_Montant, Historique_Mois,B$7, Historique_Section,"Dépenses variables - "&$A$82, Historique_Categorie,$A87, Historique_Enregistre,TRUE, Historique_Statut,"OK" ) -> 0 | C87: =SUMIFS( Historique_Montant, Historique_Mois,C$7, Historique_Section,"Dépenses variables - "&$A$82, Historique_Categorie,$A87, Historique_Enregistre,TRUE, Historique_Statut,"OK" ) -> 0 | D87: =SUMIFS( Historique_Montant, Historique_Mois,D$7, Historique_Section,"Dépenses variables - "&$A$82, Historique_Categorie,$A87, Historique_Enregistre,TRUE, Historique_Statut,"OK" ) -> 0 | E87: =SUMIFS( Historique_Montant, Historique_Mois,E$7, Historique_Section,"Dépenses variables - "&$A$82, Historique_Categorie,$A87, Historique_Enregistre,TRUE, Historique_Statut,"OK" ) -> 0 | F87: =SUMIFS( Historique_Montant, Historique_Mois,F$7, Historique_Section,"Dépenses variables - "&$A$82, Historique_Categorie,$A87, Historique_Enregistre,TRUE, Historique_Statut,"OK" ) -> 0 | G87: =SUMIFS( Historique_Montant, Historique_Mois,G$7, Historique_Section,"Dépenses variables - "&$A$82, Historique_Categorie,$A87, Historique_Enregistre,TRUE, Historique_Statut,"OK" ) -> 0 | H87: =SUMIFS( Historique_Montant, Historique_Mois,H$7, Historique_Section,"Dépenses variables - "&$A$82, Historique_Categorie,$A87, Historique_Enregistre,TRUE, Historique_Statut,"OK" ) -> 0 | I87: =SUMIFS( Historique_Montant, Historique_Mois,I$7, Historique_Section,"Dépenses variables - "&$A$82, Historique_Categorie,$A87, Historique_Enregistre,TRUE, Historique_Statut,"OK" ) -> 0 | ... M87: =SUMIFS( Historique_Montant, Historique_Mois,M$7, Historique_Section,"Dépenses variables - "&$A$82, Historique_Categorie,$A87, Historique_Enregistre,TRUE, Historique_Statut,"OK" ) -> 0 | N87: =SUM(B87:M87) -> 0
B88: =SUMIFS( Historique_Montant, Historique_Mois,B$7, Historique_Section,"Dépenses variables - "&$A$82, Historique_Categorie,$A88, Historique_Enregistre,TRUE, Historique_Statut,"OK" ) -> 0 | C88: =SUMIFS( Historique_Montant, Historique_Mois,C$7, Historique_Section,"Dépenses variables - "&$A$82, Historique_Categorie,$A88, Historique_Enregistre,TRUE, Historique_Statut,"OK" ) -> 0 | D88: =SUMIFS( Historique_Montant, Historique_Mois,D$7, Historique_Section,"Dépenses variables - "&$A$82, Historique_Categorie,$A88, Historique_Enregistre,TRUE, Historique_Statut,"OK" ) -> 0 | E88: =SUMIFS( Historique_Montant, Historique_Mois,E$7, Historique_Section,"Dépenses variables - "&$A$82, Historique_Categorie,$A88, Historique_Enregistre,TRUE, Historique_Statut,"OK" ) -> 0 | F88: =SUMIFS( Historique_Montant, Historique_Mois,F$7, Historique_Section,"Dépenses variables - "&$A$82, Historique_Categorie,$A88, Historique_Enregistre,TRUE, Historique_Statut,"OK" ) -> 0 | G88: =SUMIFS( Historique_Montant, Historique_Mois,G$7, Historique_Section,"Dépenses variables - "&$A$82, Historique_Categorie,$A88, Historique_Enregistre,TRUE, Historique_Statut,"OK" ) -> 0 | H88: =SUMIFS( Historique_Montant, Historique_Mois,H$7, Historique_Section,"Dépenses variables - "&$A$82, Historique_Categorie,$A88, Historique_Enregistre,TRUE, Historique_Statut,"OK" ) -> 0 | I88: =SUMIFS( Historique_Montant, Historique_Mois,I$7, Historique_Section,"Dépenses variables - "&$A$82, Historique_Categorie,$A88, Historique_Enregistre,TRUE, Historique_Statut,"OK" ) -> 0 | ... M88: =SUMIFS( Historique_Montant, Historique_Mois,M$7, Historique_Section,"Dépenses variables - "&$A$82, Historique_Categorie,$A88, Historique_Enregistre,TRUE, Historique_Statut,"OK" ) -> 0 | N88: =SUM(B88:M88) -> 0
B89: =SUMIFS( Historique_Montant, Historique_Mois,B$7, Historique_Section,"Dépenses variables - "&$A$82, Historique_Categorie,$A89, Historique_Enregistre,TRUE, Historique_Statut,"OK" ) -> 0 | C89: =SUMIFS( Historique_Montant, Historique_Mois,C$7, Historique_Section,"Dépenses variables - "&$A$82, Historique_Categorie,$A89, Historique_Enregistre,TRUE, Historique_Statut,"OK" ) -> 0 | D89: =SUMIFS( Historique_Montant, Historique_Mois,D$7, Historique_Section,"Dépenses variables - "&$A$82, Historique_Categorie,$A89, Historique_Enregistre,TRUE, Historique_Statut,"OK" ) -> 0 | E89: =SUMIFS( Historique_Montant, Historique_Mois,E$7, Historique_Section,"Dépenses variables - "&$A$82, Historique_Categorie,$A89, Historique_Enregistre,TRUE, Historique_Statut,"OK" ) -> 0 | F89: =SUMIFS( Historique_Montant, Historique_Mois,F$7, Historique_Section,"Dépenses variables - "&$A$82, Historique_Categorie,$A89, Historique_Enregistre,TRUE, Historique_Statut,"OK" ) -> 0 | G89: =SUMIFS( Historique_Montant, Historique_Mois,G$7, Historique_Section,"Dépenses variables - "&$A$82, Historique_Categorie,$A89, Historique_Enregistre,TRUE, Historique_Statut,"OK" ) -> 0 | H89: =SUMIFS( Historique_Montant, Historique_Mois,H$7, Historique_Section,"Dépenses variables - "&$A$82, Historique_Categorie,$A89, Historique_Enregistre,TRUE, Historique_Statut,"OK" ) -> 0 | I89: =SUMIFS( Historique_Montant, Historique_Mois,I$7, Historique_Section,"Dépenses variables - "&$A$82, Historique_Categorie,$A89, Historique_Enregistre,TRUE, Historique_Statut,"OK" ) -> 0 | ... M89: =SUMIFS( Historique_Montant, Historique_Mois,M$7, Historique_Section,"Dépenses variables - "&$A$82, Historique_Categorie,$A89, Historique_Enregistre,TRUE, Historique_Statut,"OK" ) -> 0 | N89: =SUM(B89:M89) -> 0
A90: Autres | B90: =B91 -> 0 | C90: =C91 -> 0 | D90: =D91 -> 0 | E90: =E91 -> 0 | F90: =F91 -> 0 | G90: =G91 -> 0 | H90: =H91 -> 0 | I90: =I91 -> 0 | ... M90: =M91 -> 0 | N90: =SUM(B90:M90) -> 0
A91: Autres (dépenses variables) | B91: =SUMIFS( Historique_Montant, Historique_Mois,B$7, Historique_Section,"Dépenses variables - "&$A$90, Historique_Categorie,$A91, Historique_Enregistre,TRUE, Historique_Statut,"OK" ) -> 0 | C91: =SUMIFS( Historique_Montant, Historique_Mois,C$7, Historique_Section,"Dépenses variables - "&$A$90, Historique_Categorie,$A91, Historique_Enregistre,TRUE, Historique_Statut,"OK" ) -> 0 | D91: =SUMIFS( Historique_Montant, Historique_Mois,D$7, Historique_Section,"Dépenses variables - "&$A$90, Historique_Categorie,$A91, Historique_Enregistre,TRUE, Historique_Statut,"OK" ) -> 0 | E91: =SUMIFS( Historique_Montant, Historique_Mois,E$7, Historique_Section,"Dépenses variables - "&$A$90, Historique_Categorie,$A91, Historique_Enregistre,TRUE, Historique_Statut,"OK" ) -> 0 | F91: =SUMIFS( Historique_Montant, Historique_Mois,F$7, Historique_Section,"Dépenses variables - "&$A$90, Historique_Categorie,$A91, Historique_Enregistre,TRUE, Historique_Statut,"OK" ) -> 0 | G91: =SUMIFS( Historique_Montant, Historique_Mois,G$7, Historique_Section,"Dépenses variables - "&$A$90, Historique_Categorie,$A91, Historique_Enregistre,TRUE, Historique_Statut,"OK" ) -> 0 | H91: =SUMIFS( Historique_Montant, Historique_Mois,H$7, Historique_Section,"Dépenses variables - "&$A$90, Historique_Categorie,$A91, Historique_Enregistre,TRUE, Historique_Statut,"OK" ) -> 0 | I91: =SUMIFS( Historique_Montant, Historique_Mois,I$7, Historique_Section,"Dépenses variables - "&$A$90, Historique_Categorie,$A91, Historique_Enregistre,TRUE, Historique_Statut,"OK" ) -> 0 | ... M91: =SUMIFS( Historique_Montant, Historique_Mois,M$7, Historique_Section,"Dépenses variables - "&$A$90, Historique_Categorie,$A91, Historique_Enregistre,TRUE, Historique_Statut,"OK" ) -> 0 | N91: =SUM(B91:M91) -> 0
A92: TOTAL DÉPENSES VARIABLES | B92: =SUM(B66,B74,B82,B90) -> 0 | C92: =SUM(C66,C74,C82,C90) -> 0 | D92: =SUM(D66,D74,D82,D90) -> 0 | E92: =SUM(E66,E74,E82,E90) -> 0 | F92: =SUM(F66,F74,F82,F90) -> 0 | G92: =SUM(G66,G74,G82,G90) -> 0 | H92: =SUM(H66,H74,H82,H90) -> 0 | I92: =SUM(I66,I74,I82,I90) -> 0 | ... M92: =SUM(M66,M74,M82,M90) -> 0 | N92: =SUM(B92:M92) -> 0
A94: RESTE AU TOTAL | B94: =B61-B92 -> 1800 | C94: =C61-C92 -> 0 | D94: =D61-D92 -> 0 | E94: =E61-E92 -> 0 | F94: =F61-F92 -> 0 | G94: =G61-G92 -> 0 | H94: =H61-H92 -> 0 | I94: =I61-I92 -> 0 | ... M94: =M61-M92 -> 0 | N94: =SUM(B94:M94) -> 1800

Sheet Historique
A1: Historique du budget - Journal de saisie — classé par mois. ☑ = enregistré -
A5: Mois | B5: Section | C5: Catégorie | D5: Statut | E5: Montant | F5: Enregistré | G5: Date | H5: Commentaire
D6: =IF(OR(Historique!$B6="",Historique!$C6=""),"",IF(IFERROR(COUNTIF(INDEX(Données!$E$2:$Z$100,0,MATCH(Historique!$B6,Données!$E$1:$Z$1,0)),Historique!$C6),0)>0,"OK","⚠ ERREUR"))
A7: Janvier | B7: Revenus | C7: Salaire et retraite | D7: =IF(OR(Historique!$B7="",Historique!$C7=""),"",IF(IFERROR(COUNTIF(INDEX(Données!$E$2:$Z$100,0,MATCH(Historique!$B7,Données!$E$1:$Z$1,0)),Historique!$C7),0)>0,"OK","⚠ ERREUR")) -> OK | E7: 1800 | F7: TRUE | G7: 46023 | H7: Exemple1 | J7: =IF(B7="","",_xlfn.XLOOKUP(B7,Données!$P$2:$P$11,Données!$Q$2:$Q$11,"")) -> Cat_Revenus
A8: Janvier | B8: Dépenses fixes - Transport | C8: Crédit auto | D8: =IF(OR(Historique!$B8="",Historique!$C8=""),"",IF(IFERROR(COUNTIF(INDEX(Données!$E$2:$Z$100,0,MATCH(Historique!$B8,Données!$E$1:$Z$1,0)),Historique!$C8),0)>0,"OK","⚠ ERREUR")) -> OK | E8: 250 | F8: FALSE | G8: 46023 | H8: Exemple2 | J8: =IF(B8="","",_xlfn.XLOOKUP(B8,Données!$P$2:$P$11,Données!$Q$2:$Q$11,"")) -> Cat_DF_Transport
D9: =IF(OR(Historique!$B9="",Historique!$C9=""),"",IF(IFERROR(COUNTIF(INDEX(Données!$E$2:$Z$100,0,MATCH(Historique!$B9,Données!$E$1:$Z$1,0)),Historique!$C9),0)>0,"OK","⚠ ERREUR")) | F9: TRUE | J9: =IF(B9="","",_xlfn.XLOOKUP(B9,Données!$P$2:$P$11,Données!$Q$2:$Q$11,""))
D10: =IF(OR(Historique!$B10="",Historique!$C10=""),"",IF(IFERROR(COUNTIF(INDEX(Données!$E$2:$Z$100,0,MATCH(Historique!$B10,Données!$E$1:$Z$1,0)),Historique!$C10),0)>0,"OK","⚠ ERREUR")) | F10: FALSE | J10: =IF(B10="","",_xlfn.XLOOKUP(B10,Données!$P$2:$P$11,Données!$Q$2:$Q$11,""))
D11: =IF(OR(Historique!$B11="",Historique!$C11=""),"",IF(IFERROR(COUNTIF(INDEX(Données!$E$2:$Z$100,0,MATCH(Historique!$B11,Données!$E$1:$Z$1,0)),Historique!$C11),0)>0,"OK","⚠ ERREUR")) | F11: FALSE | J11: =IF(B11="","",_xlfn.XLOOKUP(B11,Données!$P$2:$P$11,Données!$Q$2:$Q$11,""))
D12: =IF(OR(Historique!$B12="",Historique!$C12=""),"",IF(IFERROR(COUNTIF(INDEX(Données!$E$2:$Z$100,0,MATCH(Historique!$B12,Données!$E$1:$Z$1,0)),Historique!$C12),0)>0,"OK","⚠ ERREUR")) | F12: FALSE | J12: =IF(B12="","",_xlfn.XLOOKUP(B12,Données!$P$2:$P$11,Données!$Q$2:$Q$11,""))
D13: =IF(OR(Historique!$B13="",Historique!$C13=""),"",IF(IFERROR(COUNTIF(INDEX(Données!$E$2:$Z$100,0,MATCH(Historique!$B13,Données!$E$1:$Z$1,0)),Historique!$C13),0)>0,"OK","⚠ ERREUR")) | F13: FALSE | J13: =IF(B13="","",_xlfn.XLOOKUP(B13,Données!$P$2:$P$11,Données!$Q$2:$Q$11,""))
D14: =IF(OR(Historique!$B14="",Historique!$C14=""),"",IF(IFERROR(COUNTIF(INDEX(Données!$E$2:$Z$100,0,MATCH(Historique!$B14,Données!$E$1:$Z$1,0)),Historique!$C14),0)>0,"OK","⚠ ERREUR")) | F14: FALSE | J14: =IF(B14="","",_xlfn.XLOOKUP(B14,Données!$P$2:$P$11,Données!$Q$2:$Q$11,""))
D15: =IF(OR(Historique!$B15="",Historique!$C15=""),"",IF(IFERROR(COUNTIF(INDEX(Données!$E$2:$Z$100,0,MATCH(Historique!$B15,Données!$E$1:$Z$1,0)),Historique!$C15),0)>0,"OK","⚠ ERREUR")) | F15: FALSE | J15: =IF(B15="","",_xlfn.XLOOKUP(B15,Données!$P$2:$P$11,Données!$Q$2:$Q$11,""))
D16: =IF(OR(Historique!$B16="",Historique!$C16=""),"",IF(IFERROR(COUNTIF(INDEX(Données!$E$2:$Z$100,0,MATCH(Historique!$B16,Données!$E$1:$Z$1,0)),Historique!$C16),0)>0,"OK","⚠ ERREUR")) | F16: FALSE | J16: =IF(B16="","",_xlfn.XLOOKUP(B16,Données!$P$2:$P$11,Données!$Q$2:$Q$11,""))
D17: =IF(OR(Historique!$B17="",Historique!$C17=""),"",IF(IFERROR(COUNTIF(INDEX(Données!$E$2:$Z$100,0,MATCH(Historique!$B17,Données!$E$1:$Z$1,0)),Historique!$C17),0)>0,"OK","⚠ ERREUR")) | F17: FALSE | J17: =IF(B17="","",_xlfn.XLOOKUP(B17,Données!$P$2:$P$11,Données!$Q$2:$Q$11,""))
D18: =IF(OR(Historique!$B18="",Historique!$C18=""),"",IF(IFERROR(COUNTIF(INDEX(Données!$E$2:$Z$100,0,MATCH(Historique!$B18,Données!$E$1:$Z$1,0)),Historique!$C18),0)>0,"OK","⚠ ERREUR")) | F18: FALSE | J18: =IF(B18="","",_xlfn.XLOOKUP(B18,Données!$P$2:$P$11,Données!$Q$2:$Q$11,""))
D19: =IF(OR(Historique!$B19="",Historique!$C19=""),"",IF(IFERROR(COUNTIF(INDEX(Données!$E$2:$Z$100,0,MATCH(Historique!$B19,Données!$E$1:$Z$1,0)),Historique!$C19),0)>0,"OK","⚠ ERREUR")) | F19: FALSE | J19: =IF(B19="","",_xlfn.XLOOKUP(B19,Données!$P$2:$P$11,Données!$Q$2:$Q$11,""))
D20: =IF(OR(Historique!$B20="",Historique!$C20=""),"",IF(IFERROR(COUNTIF(INDEX(Données!$E$2:$Z$100,0,MATCH(Historique!$B20,Données!$E$1:$Z$1,0)),Historique!$C20),0)>0,"OK","⚠ ERREUR")) | F20: FALSE | J20: =IF(B20="","",_xlfn.XLOOKUP(B20,Données!$P$2:$P$11,Données!$Q$2:$Q$11,""))
... D5006: =IF(OR(Historique!$B5006="",Historique!$C5006=""),"",IF(IFERROR(COUNTIF(INDEX(Données!$E$2:$Z$100,0,MATCH(Historique!$B5006,Données!$E$1:$Z$1,0)),Historique!$C5006),0)>0,"OK","⚠ ERREUR")) | F5006: FALSE | J5006: =IF(B5006="","",_xlfn.XLOOKUP(B5006,Données!$P$2:$P$11,Données!$Q$2:$Q$11,""))
D5007: =IF(OR(Historique!$B5007="",Historique!$C5007=""),"",IF(IFERROR(COUNTIF(INDEX(Données!$E$2:$Z$100,0,MATCH(Historique!$B5007,Données!$E$1:$Z$1,0)),Historique!$C5007),0)>0,"OK","⚠ ERREUR")) | F5007: FALSE

Sheet Analyse
A1: Analyse du budget - Vue synthétique des revenus, dépenses et du reste à vivre -
A5: MOIS ANALYSÉ | B5: Octobre
A7: REVENUS | E7: DÉPENSES FIXES | H7: DÉPENSES VARIABLES | L7: RESTE
A8: =SUMIFS( Historique_Montant, Historique_Mois,$B$5, Historique_Section,"Revenus", Historique_Enregistre,TRUE, Historique_Statut,"OK") -> 0 | B8: {=_xlfn.LET( _xlpm.actuel,INDEX($B$50:$B$61,MATCH($B$5,$A$50:$A$61,0)), _xlpm.precedent,IFERROR(INDEX($B$50:$B$61,MATCH($B$5,$A$50:$A$61,0)-1),0), _xlpm.moisPrec,IFERROR(INDEX({"Jan";"Fév";"Mars";"Avr";"Mai";"Juin";"Juil";"Août";"Sept";"Oct";"Nov";"Déc"},MATCH($B$5,$A$50:$A$61,0)-1),""), IF(OR(_xlpm.actuel=0,_xlpm.precedent=0),"",TEXT(_xlpm.actuel-_xlpm.precedent,"+0€;-0€;0€")&" / "&_xlpm.moisPrec) )} | E8: =SUMIFS( Historique_Montant, Historique_Mois,$B$5, Historique_Section,"Dépenses fixes - "&$A$14, Historique_Enregistre,TRUE, Historique_Statut,"OK") +SUMIFS( Historique_Montant, Historique_Mois,$B$5, Historique_Section,"Dépenses fixes - "&$A$15, Historique_Enregistre,TRUE, Historique_Statut,"OK") +SUMIFS( Historique_Montant, Historique_Mois,$B$5, Historique_Section,"Dépenses fixes - "&$A$16, Historique_Enregistre,TRUE, Historique_Statut,"OK") +SUMIFS( Historique_Montant, Historique_Mois,$B$5, Historique_Section,"Dépenses fixes - "&$A$17, Historique_Enregistre,TRUE, Historique_Statut,"OK") +SUMIFS( Historique_Montant, Historique_Mois,$B$5, Historique_Section,"Dépenses fixes - "&$A$18, Historique_Enregistre,TRUE, Historique_Statut,"OK") -> 0 | F8: {=_xlfn.LET( _xlpm.actuel,INDEX($C$50:$C$61,MATCH($B$5,$A$50:$A$61,0)), _xlpm.precedent,IFERROR(INDEX($C$50:$C$61,MATCH($B$5,$A$50:$A$61,0)-1),0), _xlpm.moisPrec,IFERROR(INDEX({"Jan";"Fév";"Mars";"Avr";"Mai";"Juin";"Juil";"Août";"Sept";"Oct";"Nov";"Déc"},MATCH($B$5,$A$50:$A$61,0)-1),""), IF(OR(_xlpm.actuel=0,_xlpm.precedent=0),"",TEXT(_xlpm.actuel-_xlpm.precedent,"+0€;-0€;0€")&" / "&_xlpm.moisPrec) )} | H8: =SUMIFS( Historique_Montant, Historique_Mois,$B$5, Historique_Section,"Dépenses variables - "&$H$14, Historique_Enregistre,TRUE, Historique_Statut,"OK") +SUMIFS( Historique_Montant, Historique_Mois,$B$5, Historique_Section,"Dépenses variables - "&$H$15, Historique_Enregistre,TRUE, Historique_Statut,"OK") +SUMIFS( Historique_Montant, Historique_Mois,$B$5, Historique_Section,"Dépenses variables - "&$H$16, Historique_Enregistre,TRUE, Historique_Statut,"OK") +SUMIFS( Historique_Montant, Historique_Mois,$B$5, Historique_Section,"Dépenses variables - "&$H$17, Historique_Enregistre,TRUE, Historique_Statut,"OK") -> 0 | I8: {=_xlfn.LET( _xlpm.actuel,INDEX($D$50:$D$61,MATCH($B$5,$A$50:$A$61,0)), _xlpm.precedent,IFERROR(INDEX($D$50:$D$61,MATCH($B$5,$A$50:$A$61,0)-1),0), _xlpm.moisPrec,IFERROR(INDEX({"Jan";"Fév";"Mars";"Avr";"Mai";"Juin";"Juil";"Août";"Sept";"Oct";"Nov";"Déc"},MATCH($B$5,$A$50:$A$61,0)-1),""), IF(OR(_xlpm.actuel=0,_xlpm.precedent=0),"",TEXT(_xlpm.actuel-_xlpm.precedent,"+0€;-0€;0€")&" / "&_xlpm.moisPrec) )} | L8: =A8-E8-H8 -> 0
A9: SALAIRE DE RÉFÉRENCE | B9: {=_xlfn.LET( _xlpm.mois,_xlfn.UNIQUE(Historique_Mois), _xlpm.salaires,SUMIFS( Historique_Montant, Historique_Mois,_xlpm.mois, Historique_Categorie,Budget_mensuel!$A$8, Historique_Enregistre,TRUE, Historique_Statut,"OK"), AVERAGE(_xlfn._xlws.FILTER(_xlpm.salaires,_xlpm.salaires>0)) )} -> 1800 | E9: TAUX D'ÉPARGNE | F9: =_xlfn.LET( _xlpm.salaires,SUMIFS( Historique_Montant, Historique_Mois,B5, Historique_Categorie,Budget_mensuel!$A$8, Historique_Enregistre,TRUE, Historique_Statut,"OK"), IFERROR(B17/_xlpm.salaires,0)) -> 0 | H9: TAUX DÉPENSES VARIABLES | I9: =IFERROR(H8/A8,0) -> 0 | L9: TAUX DE RESTE | M9: =IFERROR(L8/B9,0) -> 0
A12: DÉPENSES FIXES | E12: DÉPENSES FIXES / CATÉGORIE | H12: DÉPENSES VARIABLES | L12: DÉPENSES VARIABLES / CATÉGORIE
A13: Section | B13: Montant | E13: Catégorie | F13: Montant | H13: Section | I13: Montant | L13: Catégorie | M13: Montant
A14: =Budget_mensuel!$A$20 -> Logement | B14: =SUMIFS( Historique_Montant, Historique_Mois,$B$5, Historique_Section,"Dépenses fixes - "&$A14, Historique_Enregistre,TRUE, Historique_Statut,"OK") -> 0 | E14: {=_xlfn.LET( _xlpm.liste,Budget_mensuel!$A$19:$A$59, _xlfn._xlws.FILTER( _xlpm.liste, (_xlpm.liste<>"")* (LEFT(_xlpm.liste,6)<>"TOTAL ")* (LEFT(_xlpm.liste,5)<>"RESTE")* (_xlpm.liste<>Budget_mensuel!$A$7)* (_xlpm.liste<>Budget_mensuel!$A$19)* (_xlpm.liste<>Budget_mensuel!$A$65)* (_xlpm.liste<>Budget_mensuel!$A$20)* (_xlpm.liste<>Budget_mensuel!$A$29)* (_xlpm.liste<>Budget_mensuel!$A$35)* (_xlpm.liste<>Budget_mensuel!$A$45)* (_xlpm.liste<>Budget_mensuel!$A$54)* (_xlpm.liste<>Budget_mensuel!$A$66)* (_xlpm.liste<>Budget_mensuel!$A$82)* (_xlpm.liste<>Budget_mensuel!$A$90) ) )} -> Loyer | F14: =IF(E14="","", _xlfn.LET( _xlpm.categorie,E14, _xlpm.position,MATCH(_xlpm.categorie,Budget_mensuel!$A$19:$A$59,0), _xlpm.section,IF(_xlpm.position<=10,Budget_mensuel!$A$20, IF(_xlpm.position<=18,Budget_mensuel!$A$29, IF(_xlpm.position<=28,Budget_mensuel!$A$35, IF(_xlpm.position<=37,Budget_mensuel!$A$45, Budget_mensuel!$A$54 )))), SUMIFS( Historique_Montant, Historique_Mois,$B$5, Historique_Section,"Dépenses fixes - "&_xlpm.section, Historique_Categorie,_xlpm.categorie, Historique_Enregistre,TRUE, Historique_Statut,"OK") )) -> 0 | H14: =Budget_mensuel!$A$66 -> Vie quotidienne | I14: =SUMIFS( Historique_Montant, Historique_Mois,$B$5, Historique_Section,"Dépenses variables - "&$H14, Historique_Enregistre,TRUE, Historique_Statut,"OK") -> 0 | L14: {=_xlfn.LET( _xlpm.liste,Budget_mensuel!$A$65:$A$92, _xlfn._xlws.FILTER( _xlpm.liste, (_xlpm.liste<>"")* (LEFT(_xlpm.liste,6)<>"TOTAL ")* (LEFT(_xlpm.liste,5)<>"RESTE")* (_xlpm.liste<>Budget_mensuel!$A$7)* (_xlpm.liste<>Budget_mensuel!$A$19)* (_xlpm.liste<>Budget_mensuel!$A$65)* (_xlpm.liste<>Budget_mensuel!$A$20)* (_xlpm.liste<>Budget_mensuel!$A$29)* (_xlpm.liste<>Budget_mensuel!$A$35)* (_xlpm.liste<>Budget_mensuel!$A$45)* (_xlpm.liste<>Budget_mensuel!$A$54)* (_xlpm.liste<>Budget_mensuel!$A$66)* (_xlpm.liste<>Budget_mensuel!$A$82)* (_xlpm.liste<>Budget_mensuel!$A$90) ) )} -> Restaurants, bar et cantine | M14: =IF(L14="","", _xlfn.LET( _xlpm.categorie,L14, _xlpm.position,MATCH(_xlpm.categorie,Budget_mensuel!$A$65:$A$92,0), _xlpm.section,IF(_xlpm.position<=9,Budget_mensuel!$A$66, IF(_xlpm.position<=17,Budget_mensuel!$A$74, IF(_xlpm.position<=25,Budget_mensuel!$A$82, Budget_mensuel!$A$90 ))), SUMIFS( Historique_Montant, Historique_Mois,$B$5, Historique_Section,"Dépenses variables - "&_xlpm.section, Historique_Categorie,_xlpm.categorie, Historique_Enregistre,TRUE, Historique_Statut,"OK") )) -> 0
A15: =Budget_mensuel!$A$29 -> Transport | B15: =SUMIFS( Historique_Montant, Historique_Mois,$B$5, Historique_Section,"Dépenses fixes - "&$A15, Historique_Enregistre,TRUE, Historique_Statut,"OK") -> 0 | E15: Charges de copropriété | F15: =IF(E15="","", _xlfn.LET( _xlpm.categorie,E15, _xlpm.position,MATCH(_xlpm.categorie,Budget_mensuel!$A$19:$A$59,0), _xlpm.section,IF(_xlpm.position<=10,Budget_mensuel!$A$20, IF(_xlpm.position<=18,Budget_mensuel!$A$29, IF(_xlpm.position<=28,Budget_mensuel!$A$35, IF(_xlpm.position<=37,Budget_mensuel!$A$45, Budget_mensuel!$A$54 )))), SUMIFS( Historique_Montant, Historique_Mois,$B$5, Historique_Section,"Dépenses fixes - "&_xlpm.section, Historique_Categorie,_xlpm.categorie, Historique_Enregistre,TRUE, Historique_Statut,"OK") )) -> 0 | H15: =Budget_mensuel!$A$74 -> Transport | I15: =SUMIFS( Historique_Montant, Historique_Mois,$B$5, Historique_Section,"Dépenses variables - "&$H15, Historique_Enregistre,TRUE, Historique_Statut,"OK") -> 0 | L15: Courses alimentaires | M15: =IF(L15="","", _xlfn.LET( _xlpm.categorie,L15, _xlpm.position,MATCH(_xlpm.categorie,Budget_mensuel!$A$65:$A$92,0), _xlpm.section,IF(_xlpm.position<=9,Budget_mensuel!$A$66, IF(_xlpm.position<=17,Budget_mensuel!$A$74, IF(_xlpm.position<=25,Budget_mensuel!$A$82, Budget_mensuel!$A$90 ))), SUMIFS( Historique_Montant, Historique_Mois,$B$5, Historique_Section,"Dépenses variables - "&_xlpm.section, Historique_Categorie,_xlpm.categorie, Historique_Enregistre,TRUE, Historique_Statut,"OK") )) -> 0
A16: =Budget_mensuel!$A$35 -> Abonnements | B16: =SUMIFS( Historique_Montant, Historique_Mois,$B$5, Historique_Section,"Dépenses fixes - "&$A16, Historique_Enregistre,TRUE, Historique_Statut,"OK") -> 0 | E16: Taxe d'habitation, taxe foncière | F16: =IF(E16="","", _xlfn.LET( _xlpm.categorie,E16, _xlpm.position,MATCH(_xlpm.categorie,Budget_mensuel!$A$19:$A$59,0), _xlpm.section,IF(_xlpm.position<=10,Budget_mensuel!$A$20, IF(_xlpm.position<=18,Budget_mensuel!$A$29, IF(_xlpm.position<=28,Budget_mensuel!$A$35, IF(_xlpm.position<=37,Budget_mensuel!$A$45, Budget_mensuel!$A$54 )))), SUMIFS( Historique_Montant, Historique_Mois,$B$5, Historique_Section,"Dépenses fixes - "&_xlpm.section, Historique_Categorie,_xlpm.categorie, Historique_Enregistre,TRUE, Historique_Statut,"OK") )) -> 0 | H16: =Budget_mensuel!$A$82 -> Loisirs, voyages et cadeaux | I16: =SUMIFS( Historique_Montant, Historique_Mois,$B$5, Historique_Section,"Dépenses variables - "&$H16, Historique_Enregistre,TRUE, Historique_Statut,"OK") -> 0 | L16: Achats courants | M16: =IF(L16="","", _xlfn.LET( _xlpm.categorie,L16, _xlpm.position,MATCH(_xlpm.categorie,Budget_mensuel!$A$65:$A$92,0), _xlpm.section,IF(_xlpm.position<=9,Budget_mensuel!$A$66, IF(_xlpm.position<=17,Budget_mensuel!$A$74, IF(_xlpm.position<=25,Budget_mensuel!$A$82, Budget_mensuel!$A$90 ))), SUMIFS( Historique_Montant, Historique_Mois,$B$5, Historique_Section,"Dépenses variables - "&_xlpm.section, Historique_Categorie,_xlpm.categorie, Historique_Enregistre,TRUE, Historique_Statut,"OK") )) -> 0
A17: =Budget_mensuel!$A$45 -> Epargne et investissement | B17: =SUMIFS( Historique_Montant, Historique_Mois,$B$5, Historique_Section,"Dépenses fixes - "&$A17, Historique_Enregistre,TRUE, Historique_Statut,"OK") -> 0 | E17: Charge appartement | F17: =IF(E17="","", _xlfn.LET( _xlpm.categorie,E17, _xlpm.position,MATCH(_xlpm.categorie,Budget_mensuel!$A$19:$A$59,0), _xlpm.section,IF(_xlpm.position<=10,Budget_mensuel!$A$20, IF(_xlpm.position<=18,Budget_mensuel!$A$29, IF(_xlpm.position<=28,Budget_mensuel!$A$35, IF(_xlpm.position<=37,Budget_mensuel!$A$45, Budget_mensuel!$A$54 )))), SUMIFS( Historique_Montant, Historique_Mois,$B$5, Historique_Section,"Dépenses fixes - "&_xlpm.section, Historique_Categorie,_xlpm.categorie, Historique_Enregistre,TRUE, Historique_Statut,"OK") )) -> 0 | H17: =Budget_mensuel!$A$90 -> Autres | I17: =SUMIFS( Historique_Montant, Historique_Mois,$B$5, Historique_Section,"Dépenses variables - "&$H17, Historique_Enregistre,TRUE, Historique_Statut,"OK") -> 0 | L17: Esthétique | M17: =IF(L17="","", _xlfn.LET( _xlpm.categorie,L17, _xlpm.position,MATCH(_xlpm.categorie,Budget_mensuel!$A$65:$A$92,0), _xlpm.section,IF(_xlpm.position<=9,Budget_mensuel!$A$66, IF(_xlpm.position<=17,Budget_mensuel!$A$74, IF(_xlpm.position<=25,Budget_mensuel!$A$82, Budget_mensuel!$A$90 ))), SUMIFS( Historique_Montant, Historique_Mois,$B$5, Historique_Section,"Dépenses variables - "&_xlpm.section, Historique_Categorie,_xlpm.categorie, Historique_Enregistre,TRUE, Historique_Statut,"OK") )) -> 0
A18: =Budget_mensuel!$A$54 -> Obligations publiques | B18: =SUMIFS( Historique_Montant, Historique_Mois,$B$5, Historique_Section,"Dépenses fixes - "&$A18, Historique_Enregistre,TRUE, Historique_Statut,"OK") -> 0 | E18: Assurance habitation | F18: =IF(E18="","", _xlfn.LET( _xlpm.categorie,E18, _xlpm.position,MATCH(_xlpm.categorie,Budget_mensuel!$A$19:$A$59,0), _xlpm.section,IF(_xlpm.position<=10,Budget_mensuel!$A$20, IF(_xlpm.position<=18,Budget_mensuel!$A$29, IF(_xlpm.position<=28,Budget_mensuel!$A$35, IF(_xlpm.position<=37,Budget_mensuel!$A$45, Budget_mensuel!$A$54 )))), SUMIFS( Historique_Montant, Historique_Mois,$B$5, Historique_Section,"Dépenses fixes - "&_xlpm.section, Historique_Categorie,_xlpm.categorie, Historique_Enregistre,TRUE, Historique_Statut,"OK") )) -> 0 | L18: Frais de santé | M18: =IF(L18="","", _xlfn.LET( _xlpm.categorie,L18, _xlpm.position,MATCH(_xlpm.categorie,Budget_mensuel!$A$65:$A$92,0), _xlpm.section,IF(_xlpm.position<=9,Budget_mensuel!$A$66, IF(_xlpm.position<=17,Budget_mensuel!$A$74, IF(_xlpm.position<=25,Budget_mensuel!$A$82, Budget_mensuel!$A$90 ))), SUMIFS( Historique_Montant, Historique_Mois,$B$5, Historique_Section,"Dépenses variables - "&_xlpm.section, Historique_Categorie,_xlpm.categorie, Historique_Enregistre,TRUE, Historique_Statut,"OK") )) -> 0
E19: Autres (logement) | F19: =IF(E19="","", _xlfn.LET( _xlpm.categorie,E19, _xlpm.position,MATCH(_xlpm.categorie,Budget_mensuel!$A$19:$A$59,0), _xlpm.section,IF(_xlpm.position<=10,Budget_mensuel!$A$20, IF(_xlpm.position<=18,Budget_mensuel!$A$29, IF(_xlpm.position<=28,Budget_mensuel!$A$35, IF(_xlpm.position<=37,Budget_mensuel!$A$45, Budget_mensuel!$A$54 )))), SUMIFS( Historique_Montant, Historique_Mois,$B$5, Historique_Section,"Dépenses fixes - "&_xlpm.section, Historique_Categorie,_xlpm.categorie, Historique_Enregistre,TRUE, Historique_Statut,"OK") )) -> 0 | L19: Entretien voiture | M19: =IF(L19="","", _xlfn.LET( _xlpm.categorie,L19, _xlpm.position,MATCH(_xlpm.categorie,Budget_mensuel!$A$65:$A$92,0), _xlpm.section,IF(_xlpm.position<=9,Budget_mensuel!$A$66, IF(_xlpm.position<=17,Budget_mensuel!$A$74, IF(_xlpm.position<=25,Budget_mensuel!$A$82, Budget_mensuel!$A$90 ))), SUMIFS( Historique_Montant, Historique_Mois,$B$5, Historique_Section,"Dépenses variables - "&_xlpm.section, Historique_Categorie,_xlpm.categorie, Historique_Enregistre,TRUE, Historique_Statut,"OK") )) -> 0
E20: Crédit auto | F20: =IF(E20="","", _xlfn.LET( _xlpm.categorie,E20, _xlpm.position,MATCH(_xlpm.categorie,Budget_mensuel!$A$19:$A$59,0), _xlpm.section,IF(_xlpm.position<=10,Budget_mensuel!$A$20, IF(_xlpm.position<=18,Budget_mensuel!$A$29, IF(_xlpm.position<=28,Budget_mensuel!$A$35, IF(_xlpm.position<=37,Budget_mensuel!$A$45, Budget_mensuel!$A$54 )))), SUMIFS( Historique_Montant, Historique_Mois,$B$5, Historique_Section,"Dépenses fixes - "&_xlpm.section, Historique_Categorie,_xlpm.categorie, Historique_Enregistre,TRUE, Historique_Statut,"OK") )) -> 0 | L20: Carburant | M20: =IF(L20="","", _xlfn.LET( _xlpm.categorie,L20, _xlpm.position,MATCH(_xlpm.categorie,Budget_mensuel!$A$65:$A$92,0), _xlpm.section,IF(_xlpm.position<=9,Budget_mensuel!$A$66, IF(_xlpm.position<=17,Budget_mensuel!$A$74, IF(_xlpm.position<=25,Budget_mensuel!$A$82, Budget_mensuel!$A$90 ))), SUMIFS( Historique_Montant, Historique_Mois,$B$5, Historique_Section,"Dépenses variables - "&_xlpm.section, Historique_Categorie,_xlpm.categorie, Historique_Enregistre,TRUE, Historique_Statut,"OK") )) -> 0
E21: Assurance auto | F21: =IF(E21="","", _xlfn.LET( _xlpm.categorie,E21, _xlpm.position,MATCH(_xlpm.categorie,Budget_mensuel!$A$19:$A$59,0), _xlpm.section,IF(_xlpm.position<=10,Budget_mensuel!$A$20, IF(_xlpm.position<=18,Budget_mensuel!$A$29, IF(_xlpm.position<=28,Budget_mensuel!$A$35, IF(_xlpm.position<=37,Budget_mensuel!$A$45, Budget_mensuel!$A$54 )))), SUMIFS( Historique_Montant, Historique_Mois,$B$5, Historique_Section,"Dépenses fixes - "&_xlpm.section, Historique_Categorie,_xlpm.categorie, Historique_Enregistre,TRUE, Historique_Statut,"OK") )) -> 0 | L21: Parking | M21: =IF(L21="","", _xlfn.LET( _xlpm.categorie,L21, _xlpm.position,MATCH(_xlpm.categorie,Budget_mensuel!$A$65:$A$92,0), _xlpm.section,IF(_xlpm.position<=9,Budget_mensuel!$A$66, IF(_xlpm.position<=17,Budget_mensuel!$A$74, IF(_xlpm.position<=25,Budget_mensuel!$A$82, Budget_mensuel!$A$90 ))), SUMIFS( Historique_Montant, Historique_Mois,$B$5, Historique_Section,"Dépenses variables - "&_xlpm.section, Historique_Categorie,_xlpm.categorie, Historique_Enregistre,TRUE, Historique_Statut,"OK") )) -> 0
E22: Autres (transport) | F22: =IF(E22="","", _xlfn.LET( _xlpm.categorie,E22, _xlpm.position,MATCH(_xlpm.categorie,Budget_mensuel!$A$19:$A$59,0), _xlpm.section,IF(_xlpm.position<=10,Budget_mensuel!$A$20, IF(_xlpm.position<=18,Budget_mensuel!$A$29, IF(_xlpm.position<=28,Budget_mensuel!$A$35, IF(_xlpm.position<=37,Budget_mensuel!$A$45, Budget_mensuel!$A$54 )))), SUMIFS( Historique_Montant, Historique_Mois,$B$5, Historique_Section,"Dépenses fixes - "&_xlpm.section, Historique_Categorie,_xlpm.categorie, Historique_Enregistre,TRUE, Historique_Statut,"OK") )) -> 0 | L22: Péage | M22: =IF(L22="","", _xlfn.LET( _xlpm.categorie,L22, _xlpm.position,MATCH(_xlpm.categorie,Budget_mensuel!$A$65:$A$92,0), _xlpm.section,IF(_xlpm.position<=9,Budget_mensuel!$A$66, IF(_xlpm.position<=17,Budget_mensuel!$A$74, IF(_xlpm.position<=25,Budget_mensuel!$A$82, Budget_mensuel!$A$90 ))), SUMIFS( Historique_Montant, Historique_Mois,$B$5, Historique_Section,"Dépenses variables - "&_xlpm.section, Historique_Categorie,_xlpm.categorie, Historique_Enregistre,TRUE, Historique_Statut,"OK") )) -> 0
E23: Mutuelle | F23: =IF(E23="","", _xlfn.LET( _xlpm.categorie,E23, _xlpm.position,MATCH(_xlpm.categorie,Budget_mensuel!$A$19:$A$59,0), _xlpm.section,IF(_xlpm.position<=10,Budget_mensuel!$A$20, IF(_xlpm.position<=18,Budget_mensuel!$A$29, IF(_xlpm.position<=28,Budget_mensuel!$A$35, IF(_xlpm.position<=37,Budget_mensuel!$A$45, Budget_mensuel!$A$54 )))), SUMIFS( Historique_Montant, Historique_Mois,$B$5, Historique_Section,"Dépenses fixes - "&_xlpm.section, Historique_Categorie,_xlpm.categorie, Historique_Enregistre,TRUE, Historique_Statut,"OK") )) -> 0 | L23: Transport en commun | M23: =IF(L23="","", _xlfn.LET( _xlpm.categorie,L23, _xlpm.position,MATCH(_xlpm.categorie,Budget_mensuel!$A$65:$A$92,0), _xlpm.section,IF(_xlpm.position<=9,Budget_mensuel!$A$66, IF(_xlpm.position<=17,Budget_mensuel!$A$74, IF(_xlpm.position<=25,Budget_mensuel!$A$82, Budget_mensuel!$A$90 ))), SUMIFS( Historique_Montant, Historique_Mois,$B$5, Historique_Section,"Dépenses variables - "&_xlpm.section, Historique_Categorie,_xlpm.categorie, Historique_Enregistre,TRUE, Historique_Statut,"OK") )) -> 0
E24: Box, internet, forfait(s) mobile(s) | F24: =IF(E24="","", _xlfn.LET( _xlpm.categorie,E24, _xlpm.position,MATCH(_xlpm.categorie,Budget_mensuel!$A$19:$A$59,0), _xlpm.section,IF(_xlpm.position<=10,Budget_mensuel!$A$20, IF(_xlpm.position<=18,Budget_mensuel!$A$29, IF(_xlpm.position<=28,Budget_mensuel!$A$35, IF(_xlpm.position<=37,Budget_mensuel!$A$45, Budget_mensuel!$A$54 )))), SUMIFS( Historique_Montant, Historique_Mois,$B$5, Historique_Section,"Dépenses fixes - "&_xlpm.section, Historique_Categorie,_xlpm.categorie, Historique_Enregistre,TRUE, Historique_Statut,"OK") )) -> 0 | L24: Sorties | M24: =IF(L24="","", _xlfn.LET( _xlpm.categorie,L24, _xlpm.position,MATCH(_xlpm.categorie,Budget_mensuel!$A$65:$A$92,0), _xlpm.section,IF(_xlpm.position<=9,Budget_mensuel!$A$66, IF(_xlpm.position<=17,Budget_mensuel!$A$74, IF(_xlpm.position<=25,Budget_mensuel!$A$82, Budget_mensuel!$A$90 ))), SUMIFS( Historique_Montant, Historique_Mois,$B$5, Historique_Section,"Dépenses variables - "&_xlpm.section, Historique_Categorie,_xlpm.categorie, Historique_Enregistre,TRUE, Historique_Statut,"OK") )) -> 0
E25: Vidéo (Netflix, Canal+…) | F25: =IF(E25="","", _xlfn.LET( _xlpm.categorie,E25, _xlpm.position,MATCH(_xlpm.categorie,Budget_mensuel!$A$19:$A$59,0), _xlpm.section,IF(_xlpm.position<=10,Budget_mensuel!$A$20, IF(_xlpm.position<=18,Budget_mensuel!$A$29, IF(_xlpm.position<=28,Budget_mensuel!$A$35, IF(_xlpm.position<=37,Budget_mensuel!$A$45, Budget_mensuel!$A$54 )))), SUMIFS( Historique_Montant, Historique_Mois,$B$5, Historique_Section,"Dépenses fixes - "&_xlpm.section, Historique_Categorie,_xlpm.categorie, Historique_Enregistre,TRUE, Historique_Statut,"OK") )) -> 0 | L25: Vacances et voyages | M25: =IF(L25="","", _xlfn.LET( _xlpm.categorie,L25, _xlpm.position,MATCH(_xlpm.categorie,Budget_mensuel!$A$65:$A$92,0), _xlpm.section,IF(_xlpm.position<=9,Budget_mensuel!$A$66, IF(_xlpm.position<=17,Budget_mensuel!$A$74, IF(_xlpm.position<=25,Budget_mensuel!$A$82, Budget_mensuel!$A$90 ))), SUMIFS( Historique_Montant, Historique_Mois,$B$5, Historique_Section,"Dépenses variables - "&_xlpm.section, Historique_Categorie,_xlpm.categorie, Historique_Enregistre,TRUE, Historique_Statut,"OK") )) -> 0
E26: Musique (Spotify…) | F26: =IF(E26="","", _xlfn.LET( _xlpm.categorie,E26, _xlpm.position,MATCH(_xlpm.categorie,Budget_mensuel!$A$19:$A$59,0), _xlpm.section,IF(_xlpm.position<=10,Budget_mensuel!$A$20, IF(_xlpm.position<=18,Budget_mensuel!$A$29, IF(_xlpm.position<=28,Budget_mensuel!$A$35, IF(_xlpm.position<=37,Budget_mensuel!$A$45, Budget_mensuel!$A$54 )))), SUMIFS( Historique_Montant, Historique_Mois,$B$5, Historique_Section,"Dépenses fixes - "&_xlpm.section, Historique_Categorie,_xlpm.categorie, Historique_Enregistre,TRUE, Historique_Statut,"OK") )) -> 0 | L26: Anniversaire et cadeaux | M26: =IF(L26="","", _xlfn.LET( _xlpm.categorie,L26, _xlpm.position,MATCH(_xlpm.categorie,Budget_mensuel!$A$65:$A$92,0), _xlpm.section,IF(_xlpm.position<=9,Budget_mensuel!$A$66, IF(_xlpm.position<=17,Budget_mensuel!$A$74, IF(_xlpm.position<=25,Budget_mensuel!$A$82, Budget_mensuel!$A$90 ))), SUMIFS( Historique_Montant, Historique_Mois,$B$5, Historique_Section,"Dépenses variables - "&_xlpm.section, Historique_Categorie,_xlpm.categorie, Historique_Enregistre,TRUE, Historique_Statut,"OK") )) -> 0
E27: Shopping (Amazon Prime…) | F27: =IF(E27="","", _xlfn.LET( _xlpm.categorie,E27, _xlpm.position,MATCH(_xlpm.categorie,Budget_mensuel!$A$19:$A$59,0), _xlpm.section,IF(_xlpm.position<=10,Budget_mensuel!$A$20, IF(_xlpm.position<=18,Budget_mensuel!$A$29, IF(_xlpm.position<=28,Budget_mensuel!$A$35, IF(_xlpm.position<=37,Budget_mensuel!$A$45, Budget_mensuel!$A$54 )))), SUMIFS( Historique_Montant, Historique_Mois,$B$5, Historique_Section,"Dépenses fixes - "&_xlpm.section, Historique_Categorie,_xlpm.categorie, Historique_Enregistre,TRUE, Historique_Statut,"OK") )) -> 0 | L27: Livres, musique et jeux | M27: =IF(L27="","", _xlfn.LET( _xlpm.categorie,L27, _xlpm.position,MATCH(_xlpm.categorie,Budget_mensuel!$A$65:$A$92,0), _xlpm.section,IF(_xlpm.position<=9,Budget_mensuel!$A$66, IF(_xlpm.position<=17,Budget_mensuel!$A$74, IF(_xlpm.position<=25,Budget_mensuel!$A$82, Budget_mensuel!$A$90 ))), SUMIFS( Historique_Montant, Historique_Mois,$B$5, Historique_Section,"Dépenses variables - "&_xlpm.section, Historique_Categorie,_xlpm.categorie, Historique_Enregistre,TRUE, Historique_Statut,"OK") )) -> 0
E28: Sport (salle, club…) | F28: =IF(E28="","", _xlfn.LET( _xlpm.categorie,E28, _xlpm.position,MATCH(_xlpm.categorie,Budget_mensuel!$A$19:$A$59,0), _xlpm.section,IF(_xlpm.position<=10,Budget_mensuel!$A$20, IF(_xlpm.position<=18,Budget_mensuel!$A$29, IF(_xlpm.position<=28,Budget_mensuel!$A$35, IF(_xlpm.position<=37,Budget_mensuel!$A$45, Budget_mensuel!$A$54 )))), SUMIFS( Historique_Montant, Historique_Mois,$B$5, Historique_Section,"Dépenses fixes - "&_xlpm.section, Historique_Categorie,_xlpm.categorie, Historique_Enregistre,TRUE, Historique_Statut,"OK") )) -> 0 | L28: Sport (escalade, etc..) | M28: =IF(L28="","", _xlfn.LET( _xlpm.categorie,L28, _xlpm.position,MATCH(_xlpm.categorie,Budget_mensuel!$A$65:$A$92,0), _xlpm.section,IF(_xlpm.position<=9,Budget_mensuel!$A$66, IF(_xlpm.position<=17,Budget_mensuel!$A$74, IF(_xlpm.position<=25,Budget_mensuel!$A$82, Budget_mensuel!$A$90 ))), SUMIFS( Historique_Montant, Historique_Mois,$B$5, Historique_Section,"Dépenses variables - "&_xlpm.section, Historique_Categorie,_xlpm.categorie, Historique_Enregistre,TRUE, Historique_Statut,"OK") )) -> 0
E29: Frais bancaire | F29: =IF(E29="","", _xlfn.LET( _xlpm.categorie,E29, _xlpm.position,MATCH(_xlpm.categorie,Budget_mensuel!$A$19:$A$59,0), _xlpm.section,IF(_xlpm.position<=10,Budget_mensuel!$A$20, IF(_xlpm.position<=18,Budget_mensuel!$A$29, IF(_xlpm.position<=28,Budget_mensuel!$A$35, IF(_xlpm.position<=37,Budget_mensuel!$A$45, Budget_mensuel!$A$54 )))), SUMIFS( Historique_Montant, Historique_Mois,$B$5, Historique_Section,"Dépenses fixes - "&_xlpm.section, Historique_Categorie,_xlpm.categorie, Historique_Enregistre,TRUE, Historique_Statut,"OK") )) -> 0 | L29: Autres (dépenses variables) | M29: =IF(L29="","", _xlfn.LET( _xlpm.categorie,L29, _xlpm.position,MATCH(_xlpm.categorie,Budget_mensuel!$A$65:$A$92,0), _xlpm.section,IF(_xlpm.position<=9,Budget_mensuel!$A$66, IF(_xlpm.position<=17,Budget_mensuel!$A$74, IF(_xlpm.position<=25,Budget_mensuel!$A$82, Budget_mensuel!$A$90 ))), SUMIFS( Historique_Montant, Historique_Mois,$B$5, Historique_Section,"Dépenses variables - "&_xlpm.section, Historique_Categorie,_xlpm.categorie, Historique_Enregistre,TRUE, Historique_Statut,"OK") )) -> 0
E30: Autres (abonnements) | F30: =IF(E30="","", _xlfn.LET( _xlpm.categorie,E30, _xlpm.position,MATCH(_xlpm.categorie,Budget_mensuel!$A$19:$A$59,0), _xlpm.section,IF(_xlpm.position<=10,Budget_mensuel!$A$20, IF(_xlpm.position<=18,Budget_mensuel!$A$29, IF(_xlpm.position<=28,Budget_mensuel!$A$35, IF(_xlpm.position<=37,Budget_mensuel!$A$45, Budget_mensuel!$A$54 )))), SUMIFS( Historique_Montant, Historique_Mois,$B$5, Historique_Section,"Dépenses fixes - "&_xlpm.section, Historique_Categorie,_xlpm.categorie, Historique_Enregistre,TRUE, Historique_Statut,"OK") )) -> 0 | M30: =IF(L30="","", _xlfn.LET( _xlpm.categorie,L30, _xlpm.position,MATCH(_xlpm.categorie,Budget_mensuel!$A$65:$A$92,0), _xlpm.section,IF(_xlpm.position<=9,Budget_mensuel!$A$66, IF(_xlpm.position<=17,Budget_mensuel!$A$74, IF(_xlpm.position<=25,Budget_mensuel!$A$82, Budget_mensuel!$A$90 ))), SUMIFS( Historique_Montant, Historique_Mois,$B$5, Historique_Section,"Dépenses variables - "&_xlpm.section, Historique_Categorie,_xlpm.categorie, Historique_Enregistre,TRUE, Historique_Statut,"OK") )) | N30: =IF(M30="","", _xlfn.LET( _xlpm.categorie,M30, _xlpm.position,MATCH(_xlpm.categorie,Budget_mensuel!$A$65:$A$92,0), _xlpm.section,IF(_xlpm.position<=9,Budget_mensuel!$A$66, IF(_xlpm.position<=17,Budget_mensuel!$A$74, IF(_xlpm.position<=25,Budget_mensuel!$A$82, Budget_mensuel!$A$90 ))), SUMIFS( Historique!$E$6:$E$332, Historique!$A$6:$A$332,$B$5, Historique!$B$6:$B$332,"Dépenses variables - "&_xlpm.section, Historique!$C$6:$C$332,_xlpm.categorie, Historique!$F$6:$F$332,TRUE ) ))
E31: Assurance vie | F31: =IF(E31="","", _xlfn.LET( _xlpm.categorie,E31, _xlpm.position,MATCH(_xlpm.categorie,Budget_mensuel!$A$19:$A$59,0), _xlpm.section,IF(_xlpm.position<=10,Budget_mensuel!$A$20, IF(_xlpm.position<=18,Budget_mensuel!$A$29, IF(_xlpm.position<=28,Budget_mensuel!$A$35, IF(_xlpm.position<=37,Budget_mensuel!$A$45, Budget_mensuel!$A$54 )))), SUMIFS( Historique_Montant, Historique_Mois,$B$5, Historique_Section,"Dépenses fixes - "&_xlpm.section, Historique_Categorie,_xlpm.categorie, Historique_Enregistre,TRUE, Historique_Statut,"OK") )) -> 0 | M31: =IF(L31="","", _xlfn.LET( _xlpm.categorie,L31, _xlpm.position,MATCH(_xlpm.categorie,Budget_mensuel!$A$65:$A$92,0), _xlpm.section,IF(_xlpm.position<=9,Budget_mensuel!$A$66, IF(_xlpm.position<=17,Budget_mensuel!$A$74, IF(_xlpm.position<=25,Budget_mensuel!$A$82, Budget_mensuel!$A$90 ))), SUMIFS( Historique_Montant, Historique_Mois,$B$5, Historique_Section,"Dépenses variables - "&_xlpm.section, Historique_Categorie,_xlpm.categorie, Historique_Enregistre,TRUE, Historique_Statut,"OK") )) | N31: =IF(M31="","", _xlfn.LET( _xlpm.categorie,M31, _xlpm.position,MATCH(_xlpm.categorie,Budget_mensuel!$A$65:$A$92,0), _xlpm.section,IF(_xlpm.position<=9,Budget_mensuel!$A$66, IF(_xlpm.position<=17,Budget_mensuel!$A$74, IF(_xlpm.position<=25,Budget_mensuel!$A$82, Budget_mensuel!$A$90 ))), SUMIFS( Historique!$E$6:$E$332, Historique!$A$6:$A$332,$B$5, Historique!$B$6:$B$332,"Dépenses variables - "&_xlpm.section, Historique!$C$6:$C$332,_xlpm.categorie, Historique!$F$6:$F$332,TRUE ) ))
E32: PER | F32: =IF(E32="","", _xlfn.LET( _xlpm.categorie,E32, _xlpm.position,MATCH(_xlpm.categorie,Budget_mensuel!$A$19:$A$59,0), _xlpm.section,IF(_xlpm.position<=10,Budget_mensuel!$A$20, IF(_xlpm.position<=18,Budget_mensuel!$A$29, IF(_xlpm.position<=28,Budget_mensuel!$A$35, IF(_xlpm.position<=37,Budget_mensuel!$A$45, Budget_mensuel!$A$54 )))), SUMIFS( Historique_Montant, Historique_Mois,$B$5, Historique_Section,"Dépenses fixes - "&_xlpm.section, Historique_Categorie,_xlpm.categorie, Historique_Enregistre,TRUE, Historique_Statut,"OK") )) -> 0 | M32: =IF(L32="","", _xlfn.LET( _xlpm.categorie,L32, _xlpm.position,MATCH(_xlpm.categorie,Budget_mensuel!$A$65:$A$92,0), _xlpm.section,IF(_xlpm.position<=9,Budget_mensuel!$A$66, IF(_xlpm.position<=17,Budget_mensuel!$A$74, IF(_xlpm.position<=25,Budget_mensuel!$A$82, Budget_mensuel!$A$90 ))), SUMIFS( Historique_Montant, Historique_Mois,$B$5, Historique_Section,"Dépenses variables - "&_xlpm.section, Historique_Categorie,_xlpm.categorie, Historique_Enregistre,TRUE, Historique_Statut,"OK") )) | N32: =IF(M32="","", _xlfn.LET( _xlpm.categorie,M32, _xlpm.position,MATCH(_xlpm.categorie,Budget_mensuel!$A$65:$A$92,0), _xlpm.section,IF(_xlpm.position<=9,Budget_mensuel!$A$66, IF(_xlpm.position<=17,Budget_mensuel!$A$74, IF(_xlpm.position<=25,Budget_mensuel!$A$82, Budget_mensuel!$A$90 ))), SUMIFS( Historique!$E$6:$E$332, Historique!$A$6:$A$332,$B$5, Historique!$B$6:$B$332,"Dépenses variables - "&_xlpm.section, Historique!$C$6:$C$332,_xlpm.categorie, Historique!$F$6:$F$332,TRUE ) ))
E33: PEA | F33: =IF(E33="","", _xlfn.LET( _xlpm.categorie,E33, _xlpm.position,MATCH(_xlpm.categorie,Budget_mensuel!$A$19:$A$59,0), _xlpm.section,IF(_xlpm.position<=10,Budget_mensuel!$A$20, IF(_xlpm.position<=18,Budget_mensuel!$A$29, IF(_xlpm.position<=28,Budget_mensuel!$A$35, IF(_xlpm.position<=37,Budget_mensuel!$A$45, Budget_mensuel!$A$54 )))), SUMIFS( Historique_Montant, Historique_Mois,$B$5, Historique_Section,"Dépenses fixes - "&_xlpm.section, Historique_Categorie,_xlpm.categorie, Historique_Enregistre,TRUE, Historique_Statut,"OK") )) -> 0 | M33: =IF(L33="","", _xlfn.LET( _xlpm.categorie,L33, _xlpm.position,MATCH(_xlpm.categorie,Budget_mensuel!$A$65:$A$92,0), _xlpm.section,IF(_xlpm.position<=9,Budget_mensuel!$A$66, IF(_xlpm.position<=17,Budget_mensuel!$A$74, IF(_xlpm.position<=25,Budget_mensuel!$A$82, Budget_mensuel!$A$90 ))), SUMIFS( Historique_Montant, Historique_Mois,$B$5, Historique_Section,"Dépenses variables - "&_xlpm.section, Historique_Categorie,_xlpm.categorie, Historique_Enregistre,TRUE, Historique_Statut,"OK") )) | N33: =IF(M33="","", _xlfn.LET( _xlpm.categorie,M33, _xlpm.position,MATCH(_xlpm.categorie,Budget_mensuel!$A$65:$A$92,0), _xlpm.section,IF(_xlpm.position<=9,Budget_mensuel!$A$66, IF(_xlpm.position<=17,Budget_mensuel!$A$74, IF(_xlpm.position<=25,Budget_mensuel!$A$82, Budget_mensuel!$A$90 ))), SUMIFS( Historique!$E$6:$E$332, Historique!$A$6:$A$332,$B$5, Historique!$B$6:$B$332,"Dépenses variables - "&_xlpm.section, Historique!$C$6:$C$332,_xlpm.categorie, Historique!$F$6:$F$332,TRUE ) ))
E34: Epargne de sécurité | F34: =IF(E34="","", _xlfn.LET( _xlpm.categorie,E34, _xlpm.position,MATCH(_xlpm.categorie,Budget_mensuel!$A$19:$A$59,0), _xlpm.section,IF(_xlpm.position<=10,Budget_mensuel!$A$20, IF(_xlpm.position<=18,Budget_mensuel!$A$29, IF(_xlpm.position<=28,Budget_mensuel!$A$35, IF(_xlpm.position<=37,Budget_mensuel!$A$45, Budget_mensuel!$A$54 )))), SUMIFS( Historique_Montant, Historique_Mois,$B$5, Historique_Section,"Dépenses fixes - "&_xlpm.section, Historique_Categorie,_xlpm.categorie, Historique_Enregistre,TRUE, Historique_Statut,"OK") )) -> 0 | M34: =IF(L34="","", _xlfn.LET( _xlpm.categorie,L34, _xlpm.position,MATCH(_xlpm.categorie,Budget_mensuel!$A$65:$A$92,0), _xlpm.section,IF(_xlpm.position<=9,Budget_mensuel!$A$66, IF(_xlpm.position<=17,Budget_mensuel!$A$74, IF(_xlpm.position<=25,Budget_mensuel!$A$82, Budget_mensuel!$A$90 ))), SUMIFS( Historique_Montant, Historique_Mois,$B$5, Historique_Section,"Dépenses variables - "&_xlpm.section, Historique_Categorie,_xlpm.categorie, Historique_Enregistre,TRUE, Historique_Statut,"OK") )) | N34: =IF(M34="","", _xlfn.LET( _xlpm.categorie,M34, _xlpm.position,MATCH(_xlpm.categorie,Budget_mensuel!$A$65:$A$92,0), _xlpm.section,IF(_xlpm.position<=9,Budget_mensuel!$A$66, IF(_xlpm.position<=17,Budget_mensuel!$A$74, IF(_xlpm.position<=25,Budget_mensuel!$A$82, Budget_mensuel!$A$90 ))), SUMIFS( Historique!$E$6:$E$332, Historique!$A$6:$A$332,$B$5, Historique!$B$6:$B$332,"Dépenses variables - "&_xlpm.section, Historique!$C$6:$C$332,_xlpm.categorie, Historique!$F$6:$F$332,TRUE ) ))
E35: Compte joint | F35: =IF(E35="","", _xlfn.LET( _xlpm.categorie,E35, _xlpm.position,MATCH(_xlpm.categorie,Budget_mensuel!$A$19:$A$59,0), _xlpm.section,IF(_xlpm.position<=10,Budget_mensuel!$A$20, IF(_xlpm.position<=18,Budget_mensuel!$A$29, IF(_xlpm.position<=28,Budget_mensuel!$A$35, IF(_xlpm.position<=37,Budget_mensuel!$A$45, Budget_mensuel!$A$54 )))), SUMIFS( Historique_Montant, Historique_Mois,$B$5, Historique_Section,"Dépenses fixes - "&_xlpm.section, Historique_Categorie,_xlpm.categorie, Historique_Enregistre,TRUE, Historique_Statut,"OK") )) -> 0 | M35: =IF(L35="","", _xlfn.LET( _xlpm.categorie,L35, _xlpm.position,MATCH(_xlpm.categorie,Budget_mensuel!$A$65:$A$92,0), _xlpm.section,IF(_xlpm.position<=9,Budget_mensuel!$A$66, IF(_xlpm.position<=17,Budget_mensuel!$A$74, IF(_xlpm.position<=25,Budget_mensuel!$A$82, Budget_mensuel!$A$90 ))), SUMIFS( Historique_Montant, Historique_Mois,$B$5, Historique_Section,"Dépenses variables - "&_xlpm.section, Historique_Categorie,_xlpm.categorie, Historique_Enregistre,TRUE, Historique_Statut,"OK") )) | N35: =IF(M35="","", _xlfn.LET( _xlpm.categorie,M35, _xlpm.position,MATCH(_xlpm.categorie,Budget_mensuel!$A$65:$A$92,0), _xlpm.section,IF(_xlpm.position<=9,Budget_mensuel!$A$66, IF(_xlpm.position<=17,Budget_mensuel!$A$74, IF(_xlpm.position<=25,Budget_mensuel!$A$82, Budget_mensuel!$A$90 ))), SUMIFS( Historique!$E$6:$E$332, Historique!$A$6:$A$332,$B$5, Historique!$B$6:$B$332,"Dépenses variables - "&_xlpm.section, Historique!$C$6:$C$332,_xlpm.categorie, Historique!$F$6:$F$332,TRUE ) ))
E36: Autres (épargne et investissement) | F36: =IF(E36="","", _xlfn.LET( _xlpm.categorie,E36, _xlpm.position,MATCH(_xlpm.categorie,Budget_mensuel!$A$19:$A$59,0), _xlpm.section,IF(_xlpm.position<=10,Budget_mensuel!$A$20, IF(_xlpm.position<=18,Budget_mensuel!$A$29, IF(_xlpm.position<=28,Budget_mensuel!$A$35, IF(_xlpm.position<=37,Budget_mensuel!$A$45, Budget_mensuel!$A$54 )))), SUMIFS( Historique_Montant, Historique_Mois,$B$5, Historique_Section,"Dépenses fixes - "&_xlpm.section, Historique_Categorie,_xlpm.categorie, Historique_Enregistre,TRUE, Historique_Statut,"OK") )) -> 0 | M36: =IF(L36="","", _xlfn.LET( _xlpm.categorie,L36, _xlpm.position,MATCH(_xlpm.categorie,Budget_mensuel!$A$65:$A$92,0), _xlpm.section,IF(_xlpm.position<=9,Budget_mensuel!$A$66, IF(_xlpm.position<=17,Budget_mensuel!$A$74, IF(_xlpm.position<=25,Budget_mensuel!$A$82, Budget_mensuel!$A$90 ))), SUMIFS( Historique!$E$6:$E$332, Historique!$A$6:$A$332,$B$5, Historique!$B$6:$B$332,"Dépenses variables - "&_xlpm.section, Historique!$C$6:$C$332,_xlpm.categorie, Historique!$F$6:$F$332,TRUE ) )) | N36: =IF(M36="","", _xlfn.LET( _xlpm.categorie,M36, _xlpm.position,MATCH(_xlpm.categorie,Budget_mensuel!$A$65:$A$92,0), _xlpm.section,IF(_xlpm.position<=9,Budget_mensuel!$A$66, IF(_xlpm.position<=17,Budget_mensuel!$A$74, IF(_xlpm.position<=25,Budget_mensuel!$A$82, Budget_mensuel!$A$90 ))), SUMIFS( Historique!$E$6:$E$332, Historique!$A$6:$A$332,$B$5, Historique!$B$6:$B$332,"Dépenses variables - "&_xlpm.section, Historique!$C$6:$C$332,_xlpm.categorie, Historique!$F$6:$F$332,TRUE ) ))
E37: Impôts, taxes et amendes | F37: =IF(E37="","", _xlfn.LET( _xlpm.categorie,E37, _xlpm.position,MATCH(_xlpm.categorie,Budget_mensuel!$A$19:$A$59,0), _xlpm.section,IF(_xlpm.position<=10,Budget_mensuel!$A$20, IF(_xlpm.position<=18,Budget_mensuel!$A$29, IF(_xlpm.position<=28,Budget_mensuel!$A$35, IF(_xlpm.position<=37,Budget_mensuel!$A$45, Budget_mensuel!$A$54 )))), SUMIFS( Historique_Montant, Historique_Mois,$B$5, Historique_Section,"Dépenses fixes - "&_xlpm.section, Historique_Categorie,_xlpm.categorie, Historique_Enregistre,TRUE, Historique_Statut,"OK") )) -> 0 | M37: =IF(L37="","", _xlfn.LET( _xlpm.categorie,L37, _xlpm.position,MATCH(_xlpm.categorie,Budget_mensuel!$A$65:$A$92,0), _xlpm.section,IF(_xlpm.position<=9,Budget_mensuel!$A$66, IF(_xlpm.position<=17,Budget_mensuel!$A$74, IF(_xlpm.position<=25,Budget_mensuel!$A$82, Budget_mensuel!$A$90 ))), SUMIFS( Historique!$E$6:$E$332, Historique!$A$6:$A$332,$B$5, Historique!$B$6:$B$332,"Dépenses variables - "&_xlpm.section, Historique!$C$6:$C$332,_xlpm.categorie, Historique!$F$6:$F$332,TRUE ) )) | N37: =IF(M37="","", _xlfn.LET( _xlpm.categorie,M37, _xlpm.position,MATCH(_xlpm.categorie,Budget_mensuel!$A$65:$A$92,0), _xlpm.section,IF(_xlpm.position<=9,Budget_mensuel!$A$66, IF(_xlpm.position<=17,Budget_mensuel!$A$74, IF(_xlpm.position<=25,Budget_mensuel!$A$82, Budget_mensuel!$A$90 ))), SUMIFS( Historique!$E$6:$E$332, Historique!$A$6:$A$332,$B$5, Historique!$B$6:$B$332,"Dépenses variables - "&_xlpm.section, Historique!$C$6:$C$332,_xlpm.categorie, Historique!$F$6:$F$332,TRUE ) ))
E38: Autres (obligations publiques) | F38: =IF(E38="","", _xlfn.LET( _xlpm.categorie,E38, _xlpm.position,MATCH(_xlpm.categorie,Budget_mensuel!$A$19:$A$59,0), _xlpm.section,IF(_xlpm.position<=10,Budget_mensuel!$A$20, IF(_xlpm.position<=18,Budget_mensuel!$A$29, IF(_xlpm.position<=28,Budget_mensuel!$A$35, IF(_xlpm.position<=37,Budget_mensuel!$A$45, Budget_mensuel!$A$54 )))), SUMIFS( Historique_Montant, Historique_Mois,$B$5, Historique_Section,"Dépenses fixes - "&_xlpm.section, Historique_Categorie,_xlpm.categorie, Historique_Enregistre,TRUE, Historique_Statut,"OK") )) -> 0 | M38: =IF(L38="","", _xlfn.LET( _xlpm.categorie,L38, _xlpm.position,MATCH(_xlpm.categorie,Budget_mensuel!$A$65:$A$92,0), _xlpm.section,IF(_xlpm.position<=9,Budget_mensuel!$A$66, IF(_xlpm.position<=17,Budget_mensuel!$A$74, IF(_xlpm.position<=25,Budget_mensuel!$A$82, Budget_mensuel!$A$90 ))), SUMIFS( Historique!$E$6:$E$332, Historique!$A$6:$A$332,$B$5, Historique!$B$6:$B$332,"Dépenses variables - "&_xlpm.section, Historique!$C$6:$C$332,_xlpm.categorie, Historique!$F$6:$F$332,TRUE ) )) | N38: =IF(M38="","", _xlfn.LET( _xlpm.categorie,M38, _xlpm.position,MATCH(_xlpm.categorie,Budget_mensuel!$A$65:$A$92,0), _xlpm.section,IF(_xlpm.position<=9,Budget_mensuel!$A$66, IF(_xlpm.position<=17,Budget_mensuel!$A$74, IF(_xlpm.position<=25,Budget_mensuel!$A$82, Budget_mensuel!$A$90 ))), SUMIFS( Historique!$E$6:$E$332, Historique!$A$6:$A$332,$B$5, Historique!$B$6:$B$332,"Dépenses variables - "&_xlpm.section, Historique!$C$6:$C$332,_xlpm.categorie, Historique!$F$6:$F$332,TRUE ) ))
F39: =IF(E39="","", _xlfn.LET( _xlpm.categorie,E39, _xlpm.position,MATCH(_xlpm.categorie,Budget_mensuel!$A$19:$A$59,0), _xlpm.section,IF(_xlpm.position<=10,Budget_mensuel!$A$20, IF(_xlpm.position<=18,Budget_mensuel!$A$29, IF(_xlpm.position<=28,Budget_mensuel!$A$35, IF(_xlpm.position<=37,Budget_mensuel!$A$45, Budget_mensuel!$A$54 )))), SUMIFS( Historique_Montant, Historique_Mois,$B$5, Historique_Section,"Dépenses fixes - "&_xlpm.section, Historique_Categorie,_xlpm.categorie, Historique_Enregistre,TRUE, Historique_Statut,"OK") )) | M39: =IF(L39="","", _xlfn.LET( _xlpm.categorie,L39, _xlpm.position,MATCH(_xlpm.categorie,Budget_mensuel!$A$65:$A$92,0), _xlpm.section,IF(_xlpm.position<=9,Budget_mensuel!$A$66, IF(_xlpm.position<=17,Budget_mensuel!$A$74, IF(_xlpm.position<=25,Budget_mensuel!$A$82, Budget_mensuel!$A$90 ))), SUMIFS( Historique!$E$6:$E$332, Historique!$A$6:$A$332,$B$5, Historique!$B$6:$B$332,"Dépenses variables - "&_xlpm.section, Historique!$C$6:$C$332,_xlpm.categorie, Historique!$F$6:$F$332,TRUE ) )) | N39: =IF(M39="","", _xlfn.LET( _xlpm.categorie,M39, _xlpm.position,MATCH(_xlpm.categorie,Budget_mensuel!$A$65:$A$92,0), _xlpm.section,IF(_xlpm.position<=9,Budget_mensuel!$A$66, IF(_xlpm.position<=17,Budget_mensuel!$A$74, IF(_xlpm.position<=25,Budget_mensuel!$A$82, Budget_mensuel!$A$90 ))), SUMIFS( Historique!$E$6:$E$332, Historique!$A$6:$A$332,$B$5, Historique!$B$6:$B$332,"Dépenses variables - "&_xlpm.section, Historique!$C$6:$C$332,_xlpm.categorie, Historique!$F$6:$F$332,TRUE ) ))
F40: =IF(E40="","", _xlfn.LET( _xlpm.categorie,E40, _xlpm.position,MATCH(_xlpm.categorie,Budget_mensuel!$A$19:$A$59,0), _xlpm.section,IF(_xlpm.position<=10,Budget_mensuel!$A$20, IF(_xlpm.position<=18,Budget_mensuel!$A$29, IF(_xlpm.position<=28,Budget_mensuel!$A$35, IF(_xlpm.position<=37,Budget_mensuel!$A$45, Budget_mensuel!$A$54 )))), SUMIFS( Historique_Montant, Historique_Mois,$B$5, Historique_Section,"Dépenses fixes - "&_xlpm.section, Historique_Categorie,_xlpm.categorie, Historique_Enregistre,TRUE, Historique_Statut,"OK") )) | M40: =IF(L40="","", _xlfn.LET( _xlpm.categorie,L40, _xlpm.position,MATCH(_xlpm.categorie,Budget_mensuel!$A$65:$A$92,0), _xlpm.section,IF(_xlpm.position<=9,Budget_mensuel!$A$66, IF(_xlpm.position<=17,Budget_mensuel!$A$74, IF(_xlpm.position<=25,Budget_mensuel!$A$82, Budget_mensuel!$A$90 ))), SUMIFS( Historique!$E$6:$E$332, Historique!$A$6:$A$332,$B$5, Historique!$B$6:$B$332,"Dépenses variables - "&_xlpm.section, Historique!$C$6:$C$332,_xlpm.categorie, Historique!$F$6:$F$332,TRUE ) )) | N40: =IF(M40="","", _xlfn.LET( _xlpm.categorie,M40, _xlpm.position,MATCH(_xlpm.categorie,Budget_mensuel!$A$65:$A$92,0), _xlpm.section,IF(_xlpm.position<=9,Budget_mensuel!$A$66, IF(_xlpm.position<=17,Budget_mensuel!$A$74, IF(_xlpm.position<=25,Budget_mensuel!$A$82, Budget_mensuel!$A$90 ))), SUMIFS( Historique!$E$6:$E$332, Historique!$A$6:$A$332,$B$5, Historique!$B$6:$B$332,"Dépenses variables - "&_xlpm.section, Historique!$C$6:$C$332,_xlpm.categorie, Historique!$F$6:$F$332,TRUE ) ))
F41: =IF(E41="","", _xlfn.LET( _xlpm.categorie,E41, _xlpm.position,MATCH(_xlpm.categorie,Budget_mensuel!$A$19:$A$59,0), _xlpm.section,IF(_xlpm.position<=10,Budget_mensuel!$A$20, IF(_xlpm.position<=18,Budget_mensuel!$A$29, IF(_xlpm.position<=28,Budget_mensuel!$A$35, IF(_xlpm.position<=37,Budget_mensuel!$A$45, Budget_mensuel!$A$54 )))), SUMIFS( Historique_Montant, Historique_Mois,$B$5, Historique_Section,"Dépenses fixes - "&_xlpm.section, Historique_Categorie,_xlpm.categorie, Historique_Enregistre,TRUE, Historique_Statut,"OK") )) | M41: =IF(L41="","", _xlfn.LET( _xlpm.categorie,L41, _xlpm.position,MATCH(_xlpm.categorie,Budget_mensuel!$A$65:$A$92,0), _xlpm.section,IF(_xlpm.position<=9,Budget_mensuel!$A$66, IF(_xlpm.position<=17,Budget_mensuel!$A$74, IF(_xlpm.position<=25,Budget_mensuel!$A$82, Budget_mensuel!$A$90 ))), SUMIFS( Historique!$E$6:$E$332, Historique!$A$6:$A$332,$B$5, Historique!$B$6:$B$332,"Dépenses variables - "&_xlpm.section, Historique!$C$6:$C$332,_xlpm.categorie, Historique!$F$6:$F$332,TRUE ) )) | N41: =IF(M41="","", _xlfn.LET( _xlpm.categorie,M41, _xlpm.position,MATCH(_xlpm.categorie,Budget_mensuel!$A$65:$A$92,0), _xlpm.section,IF(_xlpm.position<=9,Budget_mensuel!$A$66, IF(_xlpm.position<=17,Budget_mensuel!$A$74, IF(_xlpm.position<=25,Budget_mensuel!$A$82, Budget_mensuel!$A$90 ))), SUMIFS( Historique!$E$6:$E$332, Historique!$A$6:$A$332,$B$5, Historique!$B$6:$B$332,"Dépenses variables - "&_xlpm.section, Historique!$C$6:$C$332,_xlpm.categorie, Historique!$F$6:$F$332,TRUE ) ))
F42: =IF(E42="","", _xlfn.LET( _xlpm.categorie,E42, _xlpm.position,MATCH(_xlpm.categorie,Budget_mensuel!$A$19:$A$59,0), _xlpm.section,IF(_xlpm.position<=10,Budget_mensuel!$A$20, IF(_xlpm.position<=18,Budget_mensuel!$A$29, IF(_xlpm.position<=28,Budget_mensuel!$A$35, IF(_xlpm.position<=37,Budget_mensuel!$A$45, Budget_mensuel!$A$54 )))), SUMIFS( Historique_Montant, Historique_Mois,$B$5, Historique_Section,"Dépenses fixes - "&_xlpm.section, Historique_Categorie,_xlpm.categorie, Historique_Enregistre,TRUE, Historique_Statut,"OK") )) | M42: =IF(L42="","", _xlfn.LET( _xlpm.categorie,L42, _xlpm.position,MATCH(_xlpm.categorie,Budget_mensuel!$A$65:$A$92,0), _xlpm.section,IF(_xlpm.position<=9,Budget_mensuel!$A$66, IF(_xlpm.position<=17,Budget_mensuel!$A$74, IF(_xlpm.position<=25,Budget_mensuel!$A$82, Budget_mensuel!$A$90 ))), SUMIFS( Historique!$E$6:$E$332, Historique!$A$6:$A$332,$B$5, Historique!$B$6:$B$332,"Dépenses variables - "&_xlpm.section, Historique!$C$6:$C$332,_xlpm.categorie, Historique!$F$6:$F$332,TRUE ) )) | N42: =IF(M42="","", _xlfn.LET( _xlpm.categorie,M42, _xlpm.position,MATCH(_xlpm.categorie,Budget_mensuel!$A$65:$A$92,0), _xlpm.section,IF(_xlpm.position<=9,Budget_mensuel!$A$66, IF(_xlpm.position<=17,Budget_mensuel!$A$74, IF(_xlpm.position<=25,Budget_mensuel!$A$82, Budget_mensuel!$A$90 ))), SUMIFS( Historique!$E$6:$E$332, Historique!$A$6:$A$332,$B$5, Historique!$B$6:$B$332,"Dépenses variables - "&_xlpm.section, Historique!$C$6:$C$332,_xlpm.categorie, Historique!$F$6:$F$332,TRUE ) ))
F43: =IF(E43="","", _xlfn.LET( _xlpm.categorie,E43, _xlpm.position,MATCH(_xlpm.categorie,Budget_mensuel!$A$19:$A$59,0), _xlpm.section,IF(_xlpm.position<=10,Budget_mensuel!$A$20, IF(_xlpm.position<=18,Budget_mensuel!$A$29, IF(_xlpm.position<=28,Budget_mensuel!$A$35, IF(_xlpm.position<=37,Budget_mensuel!$A$45, Budget_mensuel!$A$54 )))), SUMIFS( Historique_Montant, Historique_Mois,$B$5, Historique_Section,"Dépenses fixes - "&_xlpm.section, Historique_Categorie,_xlpm.categorie, Historique_Enregistre,TRUE, Historique_Statut,"OK") )) | M43: =IF(L43="","", _xlfn.LET( _xlpm.categorie,L43, _xlpm.position,MATCH(_xlpm.categorie,Budget_mensuel!$A$65:$A$92,0), _xlpm.section,IF(_xlpm.position<=9,Budget_mensuel!$A$66, IF(_xlpm.position<=17,Budget_mensuel!$A$74, IF(_xlpm.position<=25,Budget_mensuel!$A$82, Budget_mensuel!$A$90 ))), SUMIFS( Historique!$E$6:$E$332, Historique!$A$6:$A$332,$B$5, Historique!$B$6:$B$332,"Dépenses variables - "&_xlpm.section, Historique!$C$6:$C$332,_xlpm.categorie, Historique!$F$6:$F$332,TRUE ) )) | N43: =IF(M43="","", _xlfn.LET( _xlpm.categorie,M43, _xlpm.position,MATCH(_xlpm.categorie,Budget_mensuel!$A$65:$A$92,0), _xlpm.section,IF(_xlpm.position<=9,Budget_mensuel!$A$66, IF(_xlpm.position<=17,Budget_mensuel!$A$74, IF(_xlpm.position<=25,Budget_mensuel!$A$82, Budget_mensuel!$A$90 ))), SUMIFS( Historique!$E$6:$E$332, Historique!$A$6:$A$332,$B$5, Historique!$B$6:$B$332,"Dépenses variables - "&_xlpm.section, Historique!$C$6:$C$332,_xlpm.categorie, Historique!$F$6:$F$332,TRUE ) ))
F44: =IF(E44="","", _xlfn.LET( _xlpm.categorie,E44, _xlpm.position,MATCH(_xlpm.categorie,Budget_mensuel!$A$19:$A$59,0), _xlpm.section,IF(_xlpm.position<=10,Budget_mensuel!$A$20, IF(_xlpm.position<=18,Budget_mensuel!$A$29, IF(_xlpm.position<=28,Budget_mensuel!$A$35, IF(_xlpm.position<=37,Budget_mensuel!$A$45, Budget_mensuel!$A$54 )))), SUMIFS( Historique_Montant, Historique_Mois,$B$5, Historique_Section,"Dépenses fixes - "&_xlpm.section, Historique_Categorie,_xlpm.categorie, Historique_Enregistre,TRUE, Historique_Statut,"OK") )) | M44: =IF(L44="","", _xlfn.LET( _xlpm.categorie,L44, _xlpm.position,MATCH(_xlpm.categorie,Budget_mensuel!$A$65:$A$92,0), _xlpm.section,IF(_xlpm.position<=9,Budget_mensuel!$A$66, IF(_xlpm.position<=17,Budget_mensuel!$A$74, IF(_xlpm.position<=25,Budget_mensuel!$A$82, Budget_mensuel!$A$90 ))), SUMIFS( Historique!$E$6:$E$332, Historique!$A$6:$A$332,$B$5, Historique!$B$6:$B$332,"Dépenses variables - "&_xlpm.section, Historique!$C$6:$C$332,_xlpm.categorie, Historique!$F$6:$F$332,TRUE ) )) | N44: =IF(M44="","", _xlfn.LET( _xlpm.categorie,M44, _xlpm.position,MATCH(_xlpm.categorie,Budget_mensuel!$A$65:$A$92,0), _xlpm.section,IF(_xlpm.position<=9,Budget_mensuel!$A$66, IF(_xlpm.position<=17,Budget_mensuel!$A$74, IF(_xlpm.position<=25,Budget_mensuel!$A$82, Budget_mensuel!$A$90 ))), SUMIFS( Historique!$E$6:$E$332, Historique!$A$6:$A$332,$B$5, Historique!$B$6:$B$332,"Dépenses variables - "&_xlpm.section, Historique!$C$6:$C$332,_xlpm.categorie, Historique!$F$6:$F$332,TRUE ) ))
F45: =IF(E45="","", _xlfn.LET( _xlpm.categorie,E45, _xlpm.position,MATCH(_xlpm.categorie,Budget_mensuel!$A$19:$A$59,0), _xlpm.section,IF(_xlpm.position<=10,Budget_mensuel!$A$20, IF(_xlpm.position<=18,Budget_mensuel!$A$29, IF(_xlpm.position<=28,Budget_mensuel!$A$35, IF(_xlpm.position<=37,Budget_mensuel!$A$45, Budget_mensuel!$A$54 )))), SUMIFS( Historique_Montant, Historique_Mois,$B$5, Historique_Section,"Dépenses fixes - "&_xlpm.section, Historique_Categorie,_xlpm.categorie, Historique_Enregistre,TRUE, Historique_Statut,"OK") )) | M45: =IF(L45="","", _xlfn.LET( _xlpm.categorie,L45, _xlpm.position,MATCH(_xlpm.categorie,Budget_mensuel!$A$65:$A$92,0), _xlpm.section,IF(_xlpm.position<=9,Budget_mensuel!$A$66, IF(_xlpm.position<=17,Budget_mensuel!$A$74, IF(_xlpm.position<=25,Budget_mensuel!$A$82, Budget_mensuel!$A$90 ))), SUMIFS( Historique!$E$6:$E$332, Historique!$A$6:$A$332,$B$5, Historique!$B$6:$B$332,"Dépenses variables - "&_xlpm.section, Historique!$C$6:$C$332,_xlpm.categorie, Historique!$F$6:$F$332,TRUE ) )) | N45: =IF(M45="","", _xlfn.LET( _xlpm.categorie,M45, _xlpm.position,MATCH(_xlpm.categorie,Budget_mensuel!$A$65:$A$92,0), _xlpm.section,IF(_xlpm.position<=9,Budget_mensuel!$A$66, IF(_xlpm.position<=17,Budget_mensuel!$A$74, IF(_xlpm.position<=25,Budget_mensuel!$A$82, Budget_mensuel!$A$90 ))), SUMIFS( Historique!$E$6:$E$332, Historique!$A$6:$A$332,$B$5, Historique!$B$6:$B$332,"Dépenses variables - "&_xlpm.section, Historique!$C$6:$C$332,_xlpm.categorie, Historique!$F$6:$F$332,TRUE ) ))
F46: =IF(E46="","", _xlfn.LET( _xlpm.categorie,E46, _xlpm.position,MATCH(_xlpm.categorie,Budget_mensuel!$A$19:$A$59,0), _xlpm.section,IF(_xlpm.position<=10,Budget_mensuel!$A$20, IF(_xlpm.position<=18,Budget_mensuel!$A$29, IF(_xlpm.position<=28,Budget_mensuel!$A$35, IF(_xlpm.position<=37,Budget_mensuel!$A$45, Budget_mensuel!$A$54 )))), SUMIFS( Historique_Montant, Historique_Mois,$B$5, Historique_Section,"Dépenses fixes - "&_xlpm.section, Historique_Categorie,_xlpm.categorie, Historique_Enregistre,TRUE, Historique_Statut,"OK") )) | M46: =IF(L46="","", _xlfn.LET( _xlpm.categorie,L46, _xlpm.position,MATCH(_xlpm.categorie,Budget_mensuel!$A$65:$A$92,0), _xlpm.section,IF(_xlpm.position<=9,Budget_mensuel!$A$66, IF(_xlpm.position<=17,Budget_mensuel!$A$74, IF(_xlpm.position<=25,Budget_mensuel!$A$82, Budget_mensuel!$A$90 ))), SUMIFS( Historique!$E$6:$E$332, Historique!$A$6:$A$332,$B$5, Historique!$B$6:$B$332,"Dépenses variables - "&_xlpm.section, Historique!$C$6:$C$332,_xlpm.categorie, Historique!$F$6:$F$332,TRUE ) )) | N46: =IF(M46="","", _xlfn.LET( _xlpm.categorie,M46, _xlpm.position,MATCH(_xlpm.categorie,Budget_mensuel!$A$65:$A$92,0), _xlpm.section,IF(_xlpm.position<=9,Budget_mensuel!$A$66, IF(_xlpm.position<=17,Budget_mensuel!$A$74, IF(_xlpm.position<=25,Budget_mensuel!$A$82, Budget_mensuel!$A$90 ))), SUMIFS( Historique!$E$6:$E$332, Historique!$A$6:$A$332,$B$5, Historique!$B$6:$B$332,"Dépenses variables - "&_xlpm.section, Historique!$C$6:$C$332,_xlpm.categorie, Historique!$F$6:$F$332,TRUE ) ))
F47: =IF(E47="","", _xlfn.LET( _xlpm.categorie,E47, _xlpm.position,MATCH(_xlpm.categorie,Budget_mensuel!$A$19:$A$59,0), _xlpm.section,IF(_xlpm.position<=10,Budget_mensuel!$A$20, IF(_xlpm.position<=18,Budget_mensuel!$A$29, IF(_xlpm.position<=28,Budget_mensuel!$A$35, IF(_xlpm.position<=37,Budget_mensuel!$A$45, Budget_mensuel!$A$54 )))), SUMIFS( Historique!$E$6:$E$332, Historique!$A$6:$A$332,$B$5, Historique!$B$6:$B$332,"Dépenses fixes - "&_xlpm.section, Historique!$C$6:$C$332,_xlpm.categorie, Historique!$F$6:$F$332,TRUE ) )) | N47: =IF(M47="","", _xlfn.LET( _xlpm.categorie,M47, _xlpm.position,MATCH(_xlpm.categorie,Budget_mensuel!$A$65:$A$92,0), _xlpm.section,IF(_xlpm.position<=9,Budget_mensuel!$A$66, IF(_xlpm.position<=17,Budget_mensuel!$A$74, IF(_xlpm.position<=25,Budget_mensuel!$A$82, Budget_mensuel!$A$90 ))), SUMIFS( Historique!$E$6:$E$332, Historique!$A$6:$A$332,$B$5, Historique!$B$6:$B$332,"Dépenses variables - "&_xlpm.section, Historique!$C$6:$C$332,_xlpm.categorie, Historique!$F$6:$F$332,TRUE ) ))
A48: ÉVOLUTION ANNUELLE | F48: =IF(E48="","", _xlfn.LET( _xlpm.categorie,E48, _xlpm.position,MATCH(_xlpm.categorie,Budget_mensuel!$A$19:$A$59,0), _xlpm.section,IF(_xlpm.position<=10,Budget_mensuel!$A$20, IF(_xlpm.position<=18,Budget_mensuel!$A$29, IF(_xlpm.position<=28,Budget_mensuel!$A$35, IF(_xlpm.position<=37,Budget_mensuel!$A$45, Budget_mensuel!$A$54 )))), SUMIFS( Historique!$E$6:$E$332, Historique!$A$6:$A$332,$B$5, Historique!$B$6:$B$332,"Dépenses fixes - "&_xlpm.section, Historique!$C$6:$C$332,_xlpm.categorie, Historique!$F$6:$F$332,TRUE ) )) | N48: =IF(M48="","", _xlfn.LET( _xlpm.categorie,M48, _xlpm.position,MATCH(_xlpm.categorie,Budget_mensuel!$A$65:$A$92,0), _xlpm.section,IF(_xlpm.position<=9,Budget_mensuel!$A$66, IF(_xlpm.position<=17,Budget_mensuel!$A$74, IF(_xlpm.position<=25,Budget_mensuel!$A$82, Budget_mensuel!$A$90 ))), SUMIFS( Historique!$E$6:$E$332, Historique!$A$6:$A$332,$B$5, Historique!$B$6:$B$332,"Dépenses variables - "&_xlpm.section, Historique!$C$6:$C$332,_xlpm.categorie, Historique!$F$6:$F$332,TRUE ) ))
A49: Mois | B49: Revenus | C49: Dépenses fixes | D49: Dépenses variables | F49: =IF(E49="","", _xlfn.LET( _xlpm.categorie,E49, _xlpm.position,MATCH(_xlpm.categorie,Budget_mensuel!$A$19:$A$59,0), _xlpm.section,IF(_xlpm.position<=10,Budget_mensuel!$A$20, IF(_xlpm.position<=18,Budget_mensuel!$A$29, IF(_xlpm.position<=28,Budget_mensuel!$A$35, IF(_xlpm.position<=37,Budget_mensuel!$A$45, Budget_mensuel!$A$54 )))), SUMIFS( Historique!$E$6:$E$332, Historique!$A$6:$A$332,$B$5, Historique!$B$6:$B$332,"Dépenses fixes - "&_xlpm.section, Historique!$C$6:$C$332,_xlpm.categorie, Historique!$F$6:$F$332,TRUE ) )) | N49: =IF(M49="","", _xlfn.LET( _xlpm.categorie,M49, _xlpm.position,MATCH(_xlpm.categorie,Budget_mensuel!$A$65:$A$92,0), _xlpm.section,IF(_xlpm.position<=9,Budget_mensuel!$A$66, IF(_xlpm.position<=17,Budget_mensuel!$A$74, IF(_xlpm.position<=25,Budget_mensuel!$A$82, Budget_mensuel!$A$90 ))), SUMIFS( Historique!$E$6:$E$332, Historique!$A$6:$A$332,$B$5, Historique!$B$6:$B$332,"Dépenses variables - "&_xlpm.section, Historique!$C$6:$C$332,_xlpm.categorie, Historique!$F$6:$F$332,TRUE ) ))
A50: Janvier | B50: =SUMIFS( Historique_Montant, Historique_Mois,$A50, Historique_Section,"Revenus", Historique_Enregistre,TRUE, Historique_Statut,"OK") -> 1800 | C50: =SUMIFS( Historique_Montant, Historique_Mois,$A50, Historique_Section,"Dépenses fixes - "&$A$14, Historique_Enregistre,TRUE, Historique_Statut,"OK") +SUMIFS( Historique_Montant, Historique_Mois,$A50, Historique_Section,"Dépenses fixes - "&$A$15, Historique_Enregistre,TRUE, Historique_Statut,"OK") +SUMIFS( Historique_Montant, Historique_Mois,$A50, Historique_Section,"Dépenses fixes - "&$A$16, Historique_Enregistre,TRUE, Historique_Statut,"OK") +SUMIFS( Historique_Montant, Historique_Mois,$A50, Historique_Section,"Dépenses fixes - "&$A$17, Historique_Enregistre,TRUE, Historique_Statut,"OK") +SUMIFS( Historique_Montant, Historique_Mois,$A50, Historique_Section,"Dépenses fixes - "&$A$18, Historique_Enregistre,TRUE, Historique_Statut,"OK") -> 0 | D50: =SUMIFS( Historique_Montant, Historique_Mois,$A50, Historique_Section,"Dépenses variables - "&$H$14, Historique_Enregistre,TRUE, Historique_Statut,"OK") +SUMIFS( Historique_Montant, Historique_Mois,$A50, Historique_Section,"Dépenses variables - "&$H$15, Historique_Enregistre,TRUE, Historique_Statut,"OK") +SUMIFS( Historique_Montant, Historique_Mois,$A50, Historique_Section,"Dépenses variables - "&$H$16, Historique_Enregistre,TRUE, Historique_Statut,"OK") +SUMIFS( Historique_Montant, Historique_Mois,$A50, Historique_Section,"Dépenses variables - "&$H$17, Historique_Enregistre,TRUE, Historique_Statut,"OK") -> 0
A51: Février | B51: =SUMIFS( Historique_Montant, Historique_Mois,$A51, Historique_Section,"Revenus", Historique_Enregistre,TRUE, Historique_Statut,"OK") -> 0 | C51: =SUMIFS( Historique_Montant, Historique_Mois,$A51, Historique_Section,"Dépenses fixes - "&$A$14, Historique_Enregistre,TRUE, Historique_Statut,"OK") +SUMIFS( Historique_Montant, Historique_Mois,$A51, Historique_Section,"Dépenses fixes - "&$A$15, Historique_Enregistre,TRUE, Historique_Statut,"OK") +SUMIFS( Historique_Montant, Historique_Mois,$A51, Historique_Section,"Dépenses fixes - "&$A$16, Historique_Enregistre,TRUE, Historique_Statut,"OK") +SUMIFS( Historique_Montant, Historique_Mois,$A51, Historique_Section,"Dépenses fixes - "&$A$17, Historique_Enregistre,TRUE, Historique_Statut,"OK") +SUMIFS( Historique_Montant, Historique_Mois,$A51, Historique_Section,"Dépenses fixes - "&$A$18, Historique_Enregistre,TRUE, Historique_Statut,"OK") -> 0 | D51: =SUMIFS( Historique_Montant, Historique_Mois,$A51, Historique_Section,"Dépenses variables - "&$H$14, Historique_Enregistre,TRUE, Historique_Statut,"OK") +SUMIFS( Historique_Montant, Historique_Mois,$A51, Historique_Section,"Dépenses variables - "&$H$15, Historique_Enregistre,TRUE, Historique_Statut,"OK") +SUMIFS( Historique_Montant, Historique_Mois,$A51, Historique_Section,"Dépenses variables - "&$H$16, Historique_Enregistre,TRUE, Historique_Statut,"OK") +SUMIFS( Historique_Montant, Historique_Mois,$A51, Historique_Section,"Dépenses variables - "&$H$17, Historique_Enregistre,TRUE, Historique_Statut,"OK") -> 0
A52: Mars | B52: =SUMIFS( Historique_Montant, Historique_Mois,$A52, Historique_Section,"Revenus", Historique_Enregistre,TRUE, Historique_Statut,"OK") -> 0 | C52: =SUMIFS( Historique_Montant, Historique_Mois,$A52, Historique_Section,"Dépenses fixes - "&$A$14, Historique_Enregistre,TRUE, Historique_Statut,"OK") +SUMIFS( Historique_Montant, Historique_Mois,$A52, Historique_Section,"Dépenses fixes - "&$A$15, Historique_Enregistre,TRUE, Historique_Statut,"OK") +SUMIFS( Historique_Montant, Historique_Mois,$A52, Historique_Section,"Dépenses fixes - "&$A$16, Historique_Enregistre,TRUE, Historique_Statut,"OK") +SUMIFS( Historique_Montant, Historique_Mois,$A52, Historique_Section,"Dépenses fixes - "&$A$17, Historique_Enregistre,TRUE, Historique_Statut,"OK") +SUMIFS( Historique_Montant, Historique_Mois,$A52, Historique_Section,"Dépenses fixes - "&$A$18, Historique_Enregistre,TRUE, Historique_Statut,"OK") -> 0 | D52: =SUMIFS( Historique_Montant, Historique_Mois,$A52, Historique_Section,"Dépenses variables - "&$H$14, Historique_Enregistre,TRUE, Historique_Statut,"OK") +SUMIFS( Historique_Montant, Historique_Mois,$A52, Historique_Section,"Dépenses variables - "&$H$15, Historique_Enregistre,TRUE, Historique_Statut,"OK") +SUMIFS( Historique_Montant, Historique_Mois,$A52, Historique_Section,"Dépenses variables - "&$H$16, Historique_Enregistre,TRUE, Historique_Statut,"OK") +SUMIFS( Historique_Montant, Historique_Mois,$A52, Historique_Section,"Dépenses variables - "&$H$17, Historique_Enregistre,TRUE, Historique_Statut,"OK") -> 0
A53: Avril | B53: =SUMIFS( Historique_Montant, Historique_Mois,$A53, Historique_Section,"Revenus", Historique_Enregistre,TRUE, Historique_Statut,"OK") -> 0 | C53: =SUMIFS( Historique_Montant, Historique_Mois,$A53, Historique_Section,"Dépenses fixes - "&$A$14, Historique_Enregistre,TRUE, Historique_Statut,"OK") +SUMIFS( Historique_Montant, Historique_Mois,$A53, Historique_Section,"Dépenses fixes - "&$A$15, Historique_Enregistre,TRUE, Historique_Statut,"OK") +SUMIFS( Historique_Montant, Historique_Mois,$A53, Historique_Section,"Dépenses fixes - "&$A$16, Historique_Enregistre,TRUE, Historique_Statut,"OK") +SUMIFS( Historique_Montant, Historique_Mois,$A53, Historique_Section,"Dépenses fixes - "&$A$17, Historique_Enregistre,TRUE, Historique_Statut,"OK") +SUMIFS( Historique_Montant, Historique_Mois,$A53, Historique_Section,"Dépenses fixes - "&$A$18, Historique_Enregistre,TRUE, Historique_Statut,"OK") -> 0 | D53: =SUMIFS( Historique_Montant, Historique_Mois,$A53, Historique_Section,"Dépenses variables - "&$H$14, Historique_Enregistre,TRUE, Historique_Statut,"OK") +SUMIFS( Historique_Montant, Historique_Mois,$A53, Historique_Section,"Dépenses variables - "&$H$15, Historique_Enregistre,TRUE, Historique_Statut,"OK") +SUMIFS( Historique_Montant, Historique_Mois,$A53, Historique_Section,"Dépenses variables - "&$H$16, Historique_Enregistre,TRUE, Historique_Statut,"OK") +SUMIFS( Historique_Montant, Historique_Mois,$A53, Historique_Section,"Dépenses variables - "&$H$17, Historique_Enregistre,TRUE, Historique_Statut,"OK") -> 0
A54: Mai | B54: =SUMIFS( Historique_Montant, Historique_Mois,$A54, Historique_Section,"Revenus", Historique_Enregistre,TRUE, Historique_Statut,"OK") -> 0 | C54: =SUMIFS( Historique_Montant, Historique_Mois,$A54, Historique_Section,"Dépenses fixes - "&$A$14, Historique_Enregistre,TRUE, Historique_Statut,"OK") +SUMIFS( Historique_Montant, Historique_Mois,$A54, Historique_Section,"Dépenses fixes - "&$A$15, Historique_Enregistre,TRUE, Historique_Statut,"OK") +SUMIFS( Historique_Montant, Historique_Mois,$A54, Historique_Section,"Dépenses fixes - "&$A$16, Historique_Enregistre,TRUE, Historique_Statut,"OK") +SUMIFS( Historique_Montant, Historique_Mois,$A54, Historique_Section,"Dépenses fixes - "&$A$17, Historique_Enregistre,TRUE, Historique_Statut,"OK") +SUMIFS( Historique_Montant, Historique_Mois,$A54, Historique_Section,"Dépenses fixes - "&$A$18, Historique_Enregistre,TRUE, Historique_Statut,"OK") -> 0 | D54: =SUMIFS( Historique_Montant, Historique_Mois,$A54, Historique_Section,"Dépenses variables - "&$H$14, Historique_Enregistre,TRUE, Historique_Statut,"OK") +SUMIFS( Historique_Montant, Historique_Mois,$A54, Historique_Section,"Dépenses variables - "&$H$15, Historique_Enregistre,TRUE, Historique_Statut,"OK") +SUMIFS( Historique_Montant, Historique_Mois,$A54, Historique_Section,"Dépenses variables - "&$H$16, Historique_Enregistre,TRUE, Historique_Statut,"OK") +SUMIFS( Historique_Montant, Historique_Mois,$A54, Historique_Section,"Dépenses variables - "&$H$17, Historique_Enregistre,TRUE, Historique_Statut,"OK") -> 0
A55: Juin | B55: =SUMIFS( Historique_Montant, Historique_Mois,$A55, Historique_Section,"Revenus", Historique_Enregistre,TRUE, Historique_Statut,"OK") -> 0 | C55: =SUMIFS( Historique_Montant, Historique_Mois,$A55, Historique_Section,"Dépenses fixes - "&$A$14, Historique_Enregistre,TRUE, Historique_Statut,"OK") +SUMIFS( Historique_Montant, Historique_Mois,$A55, Historique_Section,"Dépenses fixes - "&$A$15, Historique_Enregistre,TRUE, Historique_Statut,"OK") +SUMIFS( Historique_Montant, Historique_Mois,$A55, Historique_Section,"Dépenses fixes - "&$A$16, Historique_Enregistre,TRUE, Historique_Statut,"OK") +SUMIFS( Historique_Montant, Historique_Mois,$A55, Historique_Section,"Dépenses fixes - "&$A$17, Historique_Enregistre,TRUE, Historique_Statut,"OK") +SUMIFS( Historique_Montant, Historique_Mois,$A55, Historique_Section,"Dépenses fixes - "&$A$18, Historique_Enregistre,TRUE, Historique_Statut,"OK") -> 0 | D55: =SUMIFS( Historique_Montant, Historique_Mois,$A55, Historique_Section,"Dépenses variables - "&$H$14, Historique_Enregistre,TRUE, Historique_Statut,"OK") +SUMIFS( Historique_Montant, Historique_Mois,$A55, Historique_Section,"Dépenses variables - "&$H$15, Historique_Enregistre,TRUE, Historique_Statut,"OK") +SUMIFS( Historique_Montant, Historique_Mois,$A55, Historique_Section,"Dépenses variables - "&$H$16, Historique_Enregistre,TRUE, Historique_Statut,"OK") +SUMIFS( Historique_Montant, Historique_Mois,$A55, Historique_Section,"Dépenses variables - "&$H$17, Historique_Enregistre,TRUE, Historique_Statut,"OK") -> 0
A56: Juillet | B56: =SUMIFS( Historique_Montant, Historique_Mois,$A56, Historique_Section,"Revenus", Historique_Enregistre,TRUE, Historique_Statut,"OK") -> 0 | C56: =SUMIFS( Historique_Montant, Historique_Mois,$A56, Historique_Section,"Dépenses fixes - "&$A$14, Historique_Enregistre,TRUE, Historique_Statut,"OK") +SUMIFS( Historique_Montant, Historique_Mois,$A56, Historique_Section,"Dépenses fixes - "&$A$15, Historique_Enregistre,TRUE, Historique_Statut,"OK") +SUMIFS( Historique_Montant, Historique_Mois,$A56, Historique_Section,"Dépenses fixes - "&$A$16, Historique_Enregistre,TRUE, Historique_Statut,"OK") +SUMIFS( Historique_Montant, Historique_Mois,$A56, Historique_Section,"Dépenses fixes - "&$A$17, Historique_Enregistre,TRUE, Historique_Statut,"OK") +SUMIFS( Historique_Montant, Historique_Mois,$A56, Historique_Section,"Dépenses fixes - "&$A$18, Historique_Enregistre,TRUE, Historique_Statut,"OK") -> 0 | D56: =SUMIFS( Historique_Montant, Historique_Mois,$A56, Historique_Section,"Dépenses variables - "&$H$14, Historique_Enregistre,TRUE, Historique_Statut,"OK") +SUMIFS( Historique_Montant, Historique_Mois,$A56, Historique_Section,"Dépenses variables - "&$H$15, Historique_Enregistre,TRUE, Historique_Statut,"OK") +SUMIFS( Historique_Montant, Historique_Mois,$A56, Historique_Section,"Dépenses variables - "&$H$16, Historique_Enregistre,TRUE, Historique_Statut,"OK") +SUMIFS( Historique_Montant, Historique_Mois,$A56, Historique_Section,"Dépenses variables - "&$H$17, Historique_Enregistre,TRUE, Historique_Statut,"OK") -> 0
A57: Août | B57: =SUMIFS( Historique_Montant, Historique_Mois,$A57, Historique_Section,"Revenus", Historique_Enregistre,TRUE, Historique_Statut,"OK") -> 0 | C57: =SUMIFS( Historique_Montant, Historique_Mois,$A57, Historique_Section,"Dépenses fixes - "&$A$14, Historique_Enregistre,TRUE, Historique_Statut,"OK") +SUMIFS( Historique_Montant, Historique_Mois,$A57, Historique_Section,"Dépenses fixes - "&$A$15, Historique_Enregistre,TRUE, Historique_Statut,"OK") +SUMIFS( Historique_Montant, Historique_Mois,$A57, Historique_Section,"Dépenses fixes - "&$A$16, Historique_Enregistre,TRUE, Historique_Statut,"OK") +SUMIFS( Historique_Montant, Historique_Mois,$A57, Historique_Section,"Dépenses fixes - "&$A$17, Historique_Enregistre,TRUE, Historique_Statut,"OK") +SUMIFS( Historique_Montant, Historique_Mois,$A57, Historique_Section,"Dépenses fixes - "&$A$18, Historique_Enregistre,TRUE, Historique_Statut,"OK") -> 0 | D57: =SUMIFS( Historique_Montant, Historique_Mois,$A57, Historique_Section,"Dépenses variables - "&$H$14, Historique_Enregistre,TRUE, Historique_Statut,"OK") +SUMIFS( Historique_Montant, Historique_Mois,$A57, Historique_Section,"Dépenses variables - "&$H$15, Historique_Enregistre,TRUE, Historique_Statut,"OK") +SUMIFS( Historique_Montant, Historique_Mois,$A57, Historique_Section,"Dépenses variables - "&$H$16, Historique_Enregistre,TRUE, Historique_Statut,"OK") +SUMIFS( Historique_Montant, Historique_Mois,$A57, Historique_Section,"Dépenses variables - "&$H$17, Historique_Enregistre,TRUE, Historique_Statut,"OK") -> 0
A58: Septembre | B58: =SUMIFS( Historique_Montant, Historique_Mois,$A58, Historique_Section,"Revenus", Historique_Enregistre,TRUE, Historique_Statut,"OK") -> 0 | C58: =SUMIFS( Historique_Montant, Historique_Mois,$A58, Historique_Section,"Dépenses fixes - "&$A$14, Historique_Enregistre,TRUE, Historique_Statut,"OK") +SUMIFS( Historique_Montant, Historique_Mois,$A58, Historique_Section,"Dépenses fixes - "&$A$15, Historique_Enregistre,TRUE, Historique_Statut,"OK") +SUMIFS( Historique_Montant, Historique_Mois,$A58, Historique_Section,"Dépenses fixes - "&$A$16, Historique_Enregistre,TRUE, Historique_Statut,"OK") +SUMIFS( Historique_Montant, Historique_Mois,$A58, Historique_Section,"Dépenses fixes - "&$A$17, Historique_Enregistre,TRUE, Historique_Statut,"OK") +SUMIFS( Historique_Montant, Historique_Mois,$A58, Historique_Section,"Dépenses fixes - "&$A$18, Historique_Enregistre,TRUE, Historique_Statut,"OK") -> 0 | D58: =SUMIFS( Historique_Montant, Historique_Mois,$A58, Historique_Section,"Dépenses variables - "&$H$14, Historique_Enregistre,TRUE, Historique_Statut,"OK") +SUMIFS( Historique_Montant, Historique_Mois,$A58, Historique_Section,"Dépenses variables - "&$H$15, Historique_Enregistre,TRUE, Historique_Statut,"OK") +SUMIFS( Historique_Montant, Historique_Mois,$A58, Historique_Section,"Dépenses variables - "&$H$16, Historique_Enregistre,TRUE, Historique_Statut,"OK") +SUMIFS( Historique_Montant, Historique_Mois,$A58, Historique_Section,"Dépenses variables - "&$H$17, Historique_Enregistre,TRUE, Historique_Statut,"OK") -> 0
A59: Octobre | B59: =SUMIFS( Historique_Montant, Historique_Mois,$A59, Historique_Section,"Revenus", Historique_Enregistre,TRUE, Historique_Statut,"OK") -> 0 | C59: =SUMIFS( Historique_Montant, Historique_Mois,$A59, Historique_Section,"Dépenses fixes - "&$A$14, Historique_Enregistre,TRUE, Historique_Statut,"OK") +SUMIFS( Historique_Montant, Historique_Mois,$A59, Historique_Section,"Dépenses fixes - "&$A$15, Historique_Enregistre,TRUE, Historique_Statut,"OK") +SUMIFS( Historique_Montant, Historique_Mois,$A59, Historique_Section,"Dépenses fixes - "&$A$16, Historique_Enregistre,TRUE, Historique_Statut,"OK") +SUMIFS( Historique_Montant, Historique_Mois,$A59, Historique_Section,"Dépenses fixes - "&$A$17, Historique_Enregistre,TRUE, Historique_Statut,"OK") +SUMIFS( Historique_Montant, Historique_Mois,$A59, Historique_Section,"Dépenses fixes - "&$A$18, Historique_Enregistre,TRUE, Historique_Statut,"OK") -> 0 | D59: =SUMIFS( Historique_Montant, Historique_Mois,$A59, Historique_Section,"Dépenses variables - "&$H$14, Historique_Enregistre,TRUE, Historique_Statut,"OK") +SUMIFS( Historique_Montant, Historique_Mois,$A59, Historique_Section,"Dépenses variables - "&$H$15, Historique_Enregistre,TRUE, Historique_Statut,"OK") +SUMIFS( Historique_Montant, Historique_Mois,$A59, Historique_Section,"Dépenses variables - "&$H$16, Historique_Enregistre,TRUE, Historique_Statut,"OK") +SUMIFS( Historique_Montant, Historique_Mois,$A59, Historique_Section,"Dépenses variables - "&$H$17, Historique_Enregistre,TRUE, Historique_Statut,"OK") -> 0
A60: Novembre | B60: =SUMIFS( Historique_Montant, Historique_Mois,$A60, Historique_Section,"Revenus", Historique_Enregistre,TRUE, Historique_Statut,"OK") -> 0 | C60: =SUMIFS( Historique_Montant, Historique_Mois,$A60, Historique_Section,"Dépenses fixes - "&$A$14, Historique_Enregistre,TRUE, Historique_Statut,"OK") +SUMIFS( Historique_Montant, Historique_Mois,$A60, Historique_Section,"Dépenses fixes - "&$A$15, Historique_Enregistre,TRUE, Historique_Statut,"OK") +SUMIFS( Historique_Montant, Historique_Mois,$A60, Historique_Section,"Dépenses fixes - "&$A$16, Historique_Enregistre,TRUE, Historique_Statut,"OK") +SUMIFS( Historique_Montant, Historique_Mois,$A60, Historique_Section,"Dépenses fixes - "&$A$17, Historique_Enregistre,TRUE, Historique_Statut,"OK") +SUMIFS( Historique_Montant, Historique_Mois,$A60, Historique_Section,"Dépenses fixes - "&$A$18, Historique_Enregistre,TRUE, Historique_Statut,"OK") -> 0 | D60: =SUMIFS( Historique_Montant, Historique_Mois,$A60, Historique_Section,"Dépenses variables - "&$H$14, Historique_Enregistre,TRUE, Historique_Statut,"OK") +SUMIFS( Historique_Montant, Historique_Mois,$A60, Historique_Section,"Dépenses variables - "&$H$15, Historique_Enregistre,TRUE, Historique_Statut,"OK") +SUMIFS( Historique_Montant, Historique_Mois,$A60, Historique_Section,"Dépenses variables - "&$H$16, Historique_Enregistre,TRUE, Historique_Statut,"OK") +SUMIFS( Historique_Montant, Historique_Mois,$A60, Historique_Section,"Dépenses variables - "&$H$17, Historique_Enregistre,TRUE, Historique_Statut,"OK") -> 0
A61: Décembre | B61: =SUMIFS( Historique_Montant, Historique_Mois,$A61, Historique_Section,"Revenus", Historique_Enregistre,TRUE, Historique_Statut,"OK") -> 0 | C61: =SUMIFS( Historique_Montant, Historique_Mois,$A61, Historique_Section,"Dépenses fixes - "&$A$14, Historique_Enregistre,TRUE, Historique_Statut,"OK") +SUMIFS( Historique_Montant, Historique_Mois,$A61, Historique_Section,"Dépenses fixes - "&$A$15, Historique_Enregistre,TRUE, Historique_Statut,"OK") +SUMIFS( Historique_Montant, Historique_Mois,$A61, Historique_Section,"Dépenses fixes - "&$A$16, Historique_Enregistre,TRUE, Historique_Statut,"OK") +SUMIFS( Historique_Montant, Historique_Mois,$A61, Historique_Section,"Dépenses fixes - "&$A$17, Historique_Enregistre,TRUE, Historique_Statut,"OK") +SUMIFS( Historique_Montant, Historique_Mois,$A61, Historique_Section,"Dépenses fixes - "&$A$18, Historique_Enregistre,TRUE, Historique_Statut,"OK") -> 0 | D61: =SUMIFS( Historique_Montant, Historique_Mois,$A61, Historique_Section,"Dépenses variables - "&$H$14, Historique_Enregistre,TRUE, Historique_Statut,"OK") +SUMIFS( Historique_Montant, Historique_Mois,$A61, Historique_Section,"Dépenses variables - "&$H$15, Historique_Enregistre,TRUE, Historique_Statut,"OK") +SUMIFS( Historique_Montant, Historique_Mois,$A61, Historique_Section,"Dépenses variables - "&$H$16, Historique_Enregistre,TRUE, Historique_Statut,"OK") +SUMIFS( Historique_Montant, Historique_Mois,$A61, Historique_Section,"Dépenses variables - "&$H$17, Historique_Enregistre,TRUE, Historique_Statut,"OK") -> 0
F75: =IF(E75="","", _xlfn.LET( _xlpm.categorie,E75, _xlpm.position,MATCH(_xlpm.categorie,Budget_mensuel!$A$65:$A$92,0), _xlpm.section,IF(_xlpm.position<=9,Budget_mensuel!$A$66, IF(_xlpm.position<=17,Budget_mensuel!$A$74, IF(_xlpm.position<=25,Budget_mensuel!$A$82, Budget_mensuel!$A$90 ))), SUMIFS( Historique!$E$6:$E$332, Historique!$A$6:$A$332,$B$5, Historique!$B$6:$B$332,"Dépenses variables - "&_xlpm.section, Historique!$C$6:$C$332,_xlpm.categorie, Historique!$F$6:$F$332,TRUE ) ))
F76: =IF(E76="","", _xlfn.LET( _xlpm.categorie,E76, _xlpm.position,MATCH(_xlpm.categorie,Budget_mensuel!$A$65:$A$92,0), _xlpm.section,IF(_xlpm.position<=9,Budget_mensuel!$A$66, IF(_xlpm.position<=17,Budget_mensuel!$A$74, IF(_xlpm.position<=25,Budget_mensuel!$A$82, Budget_mensuel!$A$90 ))), SUMIFS( Historique!$E$6:$E$332, Historique!$A$6:$A$332,$B$5, Historique!$B$6:$B$332,"Dépenses variables - "&_xlpm.section, Historique!$C$6:$C$332,_xlpm.categorie, Historique!$F$6:$F$332,TRUE ) ))

Sheet Données
A1: Janvier | B1: Revenus | D1: Revenus | E1: =B1 -> Revenus | F1: =B2 -> Dépenses fixes - Logement | G1: =B3 -> Dépenses fixes - Transport | H1: =B4 -> Dépenses fixes - Abonnements | I1: =B5 -> Dépenses fixes - Epargne et investissement | J1: =B6 -> Dépenses fixes - Obligations publiques | K1: =B7 -> Dépenses variables - Vie quotidienne | L1: =B8 -> Dépenses variables - Transport | M1: =B9 -> Dépenses variables - Loisirs, voyages et cadeaux | N1: =B10 -> Dépenses variables - Autres | P1: Section | Q1: Liste
A2: Février | B2: ="Dépenses fixes - "&Budget_mensuel!$A$20 -> Dépenses fixes - Logement | D2: #336600 | E2: {=_xlfn._xlws.FILTER(Budget_mensuel!$A$8:$A$15,Budget_mensuel!$A$8:$A$15<>"")} -> Salaire et retraite | F2: {=_xlfn._xlws.FILTER(Budget_mensuel!$A$21:$A$28,Budget_mensuel!$A$21:$A$28<>"")} -> Loyer | G2: {=_xlfn._xlws.FILTER(Budget_mensuel!$A$30:$A$34,Budget_mensuel!$A$30:$A$34<>"")} -> Crédit auto | H2: {=_xlfn._xlws.FILTER(Budget_mensuel!$A$36:$A$44,Budget_mensuel!$A$36:$A$44<>"")} -> Mutuelle | I2: {=_xlfn._xlws.FILTER(Budget_mensuel!$A$46:$A$53,Budget_mensuel!$A$46:$A$53<>"")} -> Assurance vie | J2: {=_xlfn._xlws.FILTER(Budget_mensuel!$A$55:$A$58,Budget_mensuel!$A$55:$A$58<>"")} -> Impôts, taxes et amendes | K2: {=_xlfn._xlws.FILTER(Budget_mensuel!$A$67:$A$73,Budget_mensuel!$A$67:$A$73<>"")} -> Restaurants, bar et cantine | L2: {=_xlfn._xlws.FILTER(Budget_mensuel!$A$75:$A$81,Budget_mensuel!$A$75:$A$81<>"")} -> Entretien voiture | M2: {=_xlfn._xlws.FILTER(Budget_mensuel!$A$83:$A$89,Budget_mensuel!$A$83:$A$89<>"")} -> Sorties | N2: =IF(Budget_mensuel!$A$91="","",Budget_mensuel!$A$91) -> Autres (dépenses variables) | P2: =B1 -> Revenus | Q2: Cat_Revenus
A3: Mars | B3: ="Dépenses fixes - "&Budget_mensuel!$A$29 -> Dépenses fixes - Transport | D3: #3F7E00 | E3: Allocations et prestations sociales | F3: Charges de copropriété | G3: Assurance auto | H3: Box, internet, forfait(s) mobile(s) | I3: PER | J3: Autres (obligations publiques) | K3: Courses alimentaires | L3: Carburant | M3: Vacances et voyages | P3: =B2 -> Dépenses fixes - Logement | Q3: Cat_DF_Logement
A4: Avril | B4: ="Dépenses fixes - "&Budget_mensuel!$A$35 -> Dépenses fixes - Abonnements | D4: #D5EAC8 | E4: Loyers | F4: Taxe d'habitation, taxe foncière | G4: Autres (transport) | H4: Vidéo (Netflix, Canal+…) | I4: PEA | K4: Achats courants | L4: Parking | M4: Anniversaire et cadeaux | P4: =B3 -> Dépenses fixes - Transport | Q4: Cat_DF_Transport
A5: Mai | B5: ="Dépenses fixes - "&Budget_mensuel!$A$45 -> Dépenses fixes - Epargne et investissement | D5: #F1F7ED | E5: Remboursements et virements | F5: Charge appartement | H5: Musique (Spotify…) | I5: Epargne de sécurité | K5: Esthétique | L5: Péage | M5: Livres, musique et jeux | P5: =B4 -> Dépenses fixes - Abonnements | Q5: Cat_DF_Abonnements
A6: Juin | B6: ="Dépenses fixes - "&Budget_mensuel!$A$54 -> Dépenses fixes - Obligations publiques | E6: Vente d'objets | F6: Assurance habitation | H6: Shopping (Amazon Prime…) | I6: Compte joint | K6: Frais de santé | L6: Transport en commun | M6: Sport (escalade, etc..) | P6: =B5 -> Dépenses fixes - Epargne et investissement | Q6: Cat_DF_Epargne
A7: Juillet | B7: ="Dépenses variables - "&Budget_mensuel!$A$66 -> Dépenses variables - Vie quotidienne | E7: Autres (revenus) | F7: Autres (logement) | H7: Sport (salle, club…) | I7: Autres (épargne et investissement) | P7: =B6 -> Dépenses fixes - Obligations publiques | Q7: Cat_DF_Obligations
A8: Août | B8: ="Dépenses variables - "&Budget_mensuel!$A$74 -> Dépenses variables - Transport | D8: DF | H8: Frais bancaire | P8: =B7 -> Dépenses variables - Vie quotidienne | Q8: Cat_DV_VieQuotidienne
A9: Septembre | B9: ="Dépenses variables - "&Budget_mensuel!$A$82 -> Dépenses variables - Loisirs, voyages et cadeaux | D9: #632523 | H9: Autres (abonnements) | P9: =B8 -> Dépenses variables - Transport | Q9: Cat_DV_Transport
A10: Octobre | B10: ="Dépenses variables - "&Budget_mensuel!$A$90 -> Dépenses variables - Autres | D10: #963634 | P10: =B9 -> Dépenses variables - Loisirs, voyages et cadeaux | Q10: Cat_DV_Loisirs
A11: Novembre | D11: #DA9694 | P11: =B10 -> Dépenses variables - Autres | Q11: Cat_DV_Autres
A12: Décembre | D12: #F8EDEC
D15: DV
D16: #C65911
D17: #FC942C
D18: #FABF8F
D19: #FEEFE2
